Workbook

Sheet Dimensionador
A1: DIMENSIONADOR DE BESS — LOAD SHIFTING
A2: Preencha as células em AZUL. A planilha calcula o número sugerido e todos os indicadores.
A4: ① ENTRADA: CONSUMO E DIMENSIONAMENTO
B5: Consumo médio de ponta desejado | C5: 6900 | D5: kWh/mês | E5: Média mensal de energia a deslocar do HP para HFP
B6: ⟹ Nº sugerido de BESS (calculado) | C6: =CEILING(C5/(Premissas!$C$12),1) -> 2 | D6: unidades | E6: Arredondamento para cima (energia útil 1 BESS = C12 da aba Premissas)
B7: ✏️ Nº de BESS adotado (você define) | C7: 2 | D7: unidades | E7: ⬅ EDITE AQUI: confirme ou altere o número sugerido acima
B8: CAPEX total negociado (todos os BESS) | C8: 1100000 | D8: R$ | E8: Valor total com instalação, frete e comissionamento
A10: ② PARÂMETROS DO EQUIPAMENTO (vinculados à aba Premissas)
B11: Potência nominal | C11: =Premissas!C5 -> 241 | D11: kW
B12: DoD | C12: =Premissas!C6 -> 1 | D12: p.u.
B13: η BESS round-trip | C13: =Premissas!C7 -> 0.9556 | D13: p.u.
B14: η Elétrica | C14: =Premissas!C8 -> 0.98 | D14: p.u.
B15: η Operacional | C15: =Premissas!C9 -> 0.99 | D15: p.u.
B16: Dias úteis/mês | C16: =Premissas!C10 -> 21 | D16: dias
B17: Energia útil/ciclo | C17: =Premissas!C11 -> 223.43667 | D17: kWh/ciclo
B18: Energia útil/mês 1 BESS | C18: =Premissas!C12 -> 3450.0001 | D18: kWh/mês
B19: Energia carga/mês 1 BESS | C19: =Premissas!C13 -> 4013.6942 | D19: kWh/mês
A21: ③ ENERGIA CALCULADA COM O Nº DE BESS ADOTADO
B22: Energia útil/mês (N BESS) | C22: =$C$7*Premissas!$C$12 -> 6900.0002 | E22: N BESS × energia útil 1 BESS
B23: Energia carga/mês (N BESS) | C23: =$C$7*Premissas!$C$13 -> 8027.3884 | E23: N BESS × energia de carga 1 BESS
B24: Cobertura do consumo desejado | C24: =C22/C5 -> 1 | E24: Energia disponível ÷ consumo de ponta médio
B25: Receita HP ano 1 (base) | C25: =C22*Premissas!$C$21*12 -> 222663.7 | E25: Energia útil × tarifa HP × 12 meses
B26: Custo HFP ano 1 (base) | C26: =C23*Premissas!$C$20*12 -> 60298.081 | E26: Energia de carga × tarifa HFP × 12 meses
B27: Economia bruta ano 1 (base) | C27: =C25-C26 -> 162365.61 | E27: Receita HP − Custo HFP (sem degradação)
B28: O&M ano 1 (N BESS) | C28: =$C$7*Premissas!$C$25 -> 22000 | E28: N BESS × O&M unitário
B29: Economia líquida ano 1 (base) | C29: =C27-C28 -> 140365.61 | E29: Após O&M, sem degradação ainda
A31: ④ TARIFAS (vinculadas à aba Premissas)
B32: Tarifa HFP total | C32: =Premissas!$C$20 -> 0.625962
B33: Tarifa HP total | C33: =Premissas!$C$21 -> 2.689175
B34: Delta HP − HFP | C34: =Premissas!$C$22 -> 2.063213
B35: Reajuste tarifário anual | C35: =Premissas!$C$26 -> 0.08
A36: ⑥ SISTEMA SOLAR — DIMENSIONAMENTO E ENERGIA
B37: Potência solar instalada | C37: =Premissas!$C$30 -> 475 | E37: Vinculado às Premissas
B38: Performance Ratio (PR) | C38: =Premissas!$C$31 -> 0.75 | E38: Vinculado às Premissas
B39: CAPEX solar total | C39: =Premissas!$C$33 -> 1187500 | E39: Vinculado às Premissas
B40: O&M solar ano 1 | C40: =Premissas!$C$35 -> 11875 | E40: CAPEX solar × % O&M
B41: Geração solar média/mês | C41: =Premissas!$C$65 -> 54179.688 | E41: Média dos 12 meses
B42: Acumulado Ano 20 | C42: ='Fluxo 20 Anos'!C253 -> 20025677
A43: ALOCAÇÃO DA GERAÇÃO SOLAR (mês médio)
B44: Energia necessária p/ carga BESS/mês | C44: =$C$7*Premissas!$C$13 -> 8027.3884 | E44: N BESS × energia de carga 1 BESS
B45: Solar → carga BESS (MIN) | C45: =MIN(C41,C44) -> 8027.3884 | E45: Solar cobre BESS até o limite
B46: Solar → excedente para carga | C46: =MAX(0,C41-C45) -> 46152.299 | E46: Sobra vai para a carga
B47: Cobertura solar do BESS | C47: =IFERROR(C45/C44,0) -> 1 | E47: % do BESS coberto pelo solar
B48: Deficit BESS (complemento rede) | C48: =MAX(0,C44-C45) -> 0 | E48: Energia ainda necessária da rede
A50: ECONOMIA SOLAR ANO 1 (base, sem degradação)
B51: Economia excedente solar (HFP) | C51: =C46*Premissas!$C$20*12 -> 346675.03 | E51: Excedente × HFP × 12
B52: Custo HFP evitado (solar→BESS) | C52: =C45*Premissas!$C$20*12 -> 60298.081 | E52: Solar evita custo de carga da rede
B53: Economia solar total ano 1 | C53: =C51+C52 -> 406973.11 | E53: Bruta total
B54: O&M solar ano 1 | C54: =Premissas!$C$35 -> 11875 | E54: Manutenção solar
B55: Economia solar líquida ano 1 | C55: =C53-C54 -> 395098.11 | E55: Após O&M solar
A57: CAPEX CONSOLIDADO (BESS + SOLAR)
B58: CAPEX BESS | C58: =$C$8 -> 1100000
B59: CAPEX Solar | C59: =Premissas!$C$33 -> 1187500
B60: CAPEX Total (BESS + Solar) | C60: =C58+C59 -> 2287500
A62: ⑦ INDICADORES FINANCEIROS CONSOLIDADOS (BESS + Solar)
B63: VPL (TMA Premissas) | C63: ='Fluxo 20 Anos'!C249 -> 4187198
B64: TIR (a.a.) | C64: ='Fluxo 20 Anos'!C250 -> 0.29990854
B65: Payback (meses) | C65: ='Fluxo 20 Anos'!C251 -> 46.465407
B66: Payback (anos) | C66: ='Fluxo 20 Anos'!C252 -> 3.8721173
B67: Acumulado Ano 20 | C67: ='Fluxo 20 Anos'!C253 -> 20025677
B68: Economia Total 20 anos (líq.) | C68: ='Fluxo 20 Anos'!C254 -> 22313177

Sheet Fluxo 20 Anos
A1: FLUXO DE CAIXA — MÊS A MÊS — 20 ANOS | N BESS DINÂMICO
A2: SOH interpolado mensalmente | Reajuste tarifário anual | Degradação contínua ao longo dos 240 meses
A4: Ano | B4: Mês | C4: SOH Mês | D4: Reajuste Tarifário | E4: Receita HP (R$) | F4: Custo HFP (R$) | G4: O&M (R$/mês) | H4: Geração Solar (kWh) | I4: Solar→ BESS (kWh) | J4: Solar→ Exced. (kWh) | K4: O&M Solar (R$/mês) | L4: Eco. Bruta (R$/mês) | M4: Eco. Líq. (R$/mês) | N4: Acumulado (R$) | O4: Eco. Acum. (sem CAPEX) | P4: Payback
A5: 0 | B5: Invest. | M5: =-Dimensionador!$C$8 -> -1100000 | N5: =-(Dimensionador!$C$8+Premissas!$C$33) -> -2287500 | O5: =0 -> 0 | Q5: =-(Dimensionador!$C$8+Premissas!$C$33) -> -2287500 | R5: =-Dimensionador!$C$8 -> -1100000
A6: 1 | B6: Jan | C6: =Premissas!$C$69+0*(Premissas!$C$70-Premissas!$C$69) -> 1 | D6: =(1+Premissas!$C$26)^(0) -> 1 | E6: =Dimensionador!$C$22*(Premissas!$C$69+0*(Premissas!$C$70-Premissas!$C$69))*Premissas!$C$21*(1+Premissas!$C$26)^(0) -> 18555.308 | F6: =Dimensionador!$C$7*Premissas!$C$13*(Premissas!$C$69+0*(Premissas!$C$70-Premissas!$C$69))*Premissas!$C$20*(1+Premissas!$C$26)^(0) -> 5024.8401 | G6: =Dimensionador!$C$7*Premissas!$C$25*(1+Premissas!$C$27)^(0)/12 -> 1833.3333 | H6: =Premissas!$C$52*(1-Premissas!$C$32)^(0) -> 55218.75 | I6: =MIN(H6,Dimensionador!$C$7*Premissas!$C$13*(Premissas!$C$69+0*(Premissas!$C$70-Premissas!$C$69))) -> 8027.3884 | J6: =MAX(0,H6-I6) -> 47191.362 | K6: =Premissas!$C$35*(1+Premissas!$C$27)^(0)/12 -> 989.58333 | L6: =E6-F6+(I6+J6)*Premissas!$C$20*(1+Premissas!$C$26)^(0) -> 48095.307 | M6: =L6-G6-K6 -> 45272.39 | N6: =N5+M6 -> -2242227.6 | O6: =M6 -> 45272.39 | P6: "" | Q6: =SUM(M6:M17) -> 533305.61 | R6: =SUM(I6:I17) -> 95048.293
A7: 1 | B7: Fev | C7: =Premissas!$C$69+0.0833333333*(Premissas!$C$70-Premissas!$C$69) -> 0.99758333 | D7: =(1+Premissas!$C$26)^(0) -> 1 | E7: =Dimensionador!$C$22*(Premissas!$C$69+0.0833333333*(Premissas!$C$70-Premissas!$C$69))*Premissas!$C$21*(1+Premissas!$C$26)^(0) -> 18510.466 | F7: =Dimensionador!$C$7*Premissas!$C$13*(Premissas!$C$69+0.0833333333*(Premissas!$C$70-Premissas!$C$69))*Premissas!$C$20*(1+Premissas!$C$26)^(0) -> 5012.6968 | G7: =Dimensionador!$C$7*Premissas!$C$25*(1+Premissas!$C$27)^(0)/12 -> 1833.3333 | H7: =Premissas!$C$53*(1-Premissas!$C$32)^(0) -> 49875 | I7: =MIN(H7,Dimensionador!$C$7*Premissas!$C$13*(Premissas!$C$69+0.0833333333*(Premissas!$C$70-Premissas!$C$69))) -> 8007.9889 | J7: =MAX(0,H7-I7) -> 41867.011 | K7: =Premissas!$C$35*(1+Premissas!$C$27)^(0)/12 -> 989.58333 | L7: =E7-F7+(I7+J7)*Premissas!$C$20*(1+Premissas!$C$26)^(0) -> 44717.624 | M7: =L7-G7-K7 -> 41894.707 | N7: =N6+M7 -> -2200332.9 | O7: =O6+M7 -> 87167.098 | P7: =IF(AND(N7>=0,N6<0),"✅ PAYBACK","") | Q7: =SUM(M18:M29) -> 570863.09 | R7: =SUM(I18:I29) -> 92519.665
A8: 1 | B8: Mar | C8: =Premissas!$C$69+0.1666666667*(Premissas!$C$70-Premissas!$C$69) -> 0.99516667 | D8: =(1+Premissas!$C$26)^(0) -> 1 | E8: =Dimensionador!$C$22*(Premissas!$C$69+0.1666666667*(Premissas!$C$70-Premissas!$C$69))*Premissas!$C$21*(1+Premissas!$C$26)^(0) -> 18465.624 | F8: =Dimensionador!$C$7*Premissas!$C$13*(Premissas!$C$69+0.1666666667*(Premissas!$C$70-Premissas!$C$69))*Premissas!$C$20*(1+Premissas!$C$26)^(0) -> 5000.5534 | G8: =Dimensionador!$C$7*Premissas!$C$25*(1+Premissas!$C$27)^(0)/12 -> 1833.3333 | H8: =Premissas!$C$54*(1-Premissas!$C$32)^(0) -> 55218.75 | I8: =MIN(H8,Dimensionador!$C$7*Premissas!$C$13*(Premissas!$C$69+0.1666666667*(Premissas!$C$70-Premissas!$C$69))) -> 7988.5894 | J8: =MAX(0,H8-I8) -> 47230.161 | K8: =Premissas!$C$35*(1+Premissas!$C$27)^(0)/12 -> 989.58333 | L8: =E8-F8+(I8+J8)*Premissas!$C$20*(1+Premissas!$C$26)^(0) -> 48029.91 | M8: =L8-G8-K8 -> 45206.993 | N8: =N7+M8 -> -2155125.9 | O8: =O7+M8 -> 132374.09 | P8: =IF(AND(N8>=0,N7<0),"✅ PAYBACK","") | Q8: =SUM(M30:M41) -> 611732.89 | R8: =SUM(I30:I41) -> 90392.407
A9: 1 | B9: Abr | C9: =Premissas!$C$69+0.25*(Premissas!$C$70-Premissas!$C$69) -> 0.99275 | D9: =(1+Premissas!$C$26)^(0) -> 1 | E9: =Dimensionador!$C$22*(Premissas!$C$69+0.25*(Premissas!$C$70-Premissas!$C$69))*Premissas!$C$21*(1+Premissas!$C$26)^(0) -> 18420.782 | F9: =Dimensionador!$C$7*Premissas!$C$13*(Premissas!$C$69+0.25*(Premissas!$C$70-Premissas!$C$69))*Premissas!$C$20*(1+Premissas!$C$26)^(0) -> 4988.41 | G9: =Dimensionador!$C$7*Premissas!$C$25*(1+Premissas!$C$27)^(0)/12 -> 1833.3333 | H9: =Premissas!$C$55*(1-Premissas!$C$32)^(0) -> 53437.5 | I9: =MIN(H9,Dimensionador!$C$7*Premissas!$C$13*(Premissas!$C$69+0.25*(Premissas!$C$70-Premissas!$C$69))) -> 7969.1899 | J9: =MAX(0,H9-I9) -> 45468.31 | K9: =Premissas!$C$35*(1+Premissas!$C$27)^(0)/12 -> 989.58333 | L9: =E9-F9+(I9+J9)*Premissas!$C$20*(1+Premissas!$C$26)^(0) -> 46882.216 | M9: =L9-G9-K9 -> 44059.3 | N9: =N8+M9 -> -2111066.6 | O9: =O8+M9 -> 176433.39 | P9: =IF(AND(N9>=0,N8<0),"✅ PAYBACK","") | Q9: =SUM(M42:M53) -> 655729.17 | R9: =SUM(I42:I53) -> 88413.656
A10: 1 | B10: Mai | C10: =Premissas!$C$69+0.3333333333*(Premissas!$C$70-Premissas!$C$69) -> 0.99033333 | D10: =(1+Premissas!$C$26)^(0) -> 1 | E10: =Dimensionador!$C$22*(Premissas!$C$69+0.3333333333*(Premissas!$C$70-Premissas!$C$69))*Premissas!$C$21*(1+Premissas!$C$26)^(0) -> 18375.94 | F10: =Dimensionador!$C$7*Premissas!$C$13*(Premissas!$C$69+0.3333333333*(Premissas!$C$70-Premissas!$C$69))*Premissas!$C$20*(1+Premissas!$C$26)^(0) -> 4976.2667 | G10: =Dimensionador!$C$7*Premissas!$C$25*(1+Premissas!$C$27)^(0)/12 -> 1833.3333 | H10: =Premissas!$C$56*(1-Premissas!$C$32)^(0) -> 55218.75 | I10: =MIN(H10,Dimensionador!$C$7*Premissas!$C$13*(Premissas!$C$69+0.3333333333*(Premissas!$C$70-Premissas!$C$69))) -> 7949.7903 | J10: =MAX(0,H10-I10) -> 47268.96 | K10: =Premissas!$C$35*(1+Premissas!$C$27)^(0)/12 -> 989.58333 | L10: =E10-F10+(I10+J10)*Premissas!$C$20*(1+Premissas!$C$26)^(0) -> 47964.512 | M10: =L10-G10-K10 -> 45141.596 | N10: =N9+M10 -> -2065925 | O10: =O9+M10 -> 221574.99 | P10: =IF(AND(N10>=0,N9<0),"✅ PAYBACK","") | Q10: =SUM(M54:M65) -> 702994.53 | R10: =SUM(I54:I65) -> 86531.234
A11: 1 | B11: Jun | C11: =Premissas!$C$69+0.4166666667*(Premissas!$C$70-Premissas!$C$69) -> 0.98791667 | D11: =(1+Premissas!$C$26)^(0) -> 1 | E11: =Dimensionador!$C$22*(Premissas!$C$69+0.4166666667*(Premissas!$C$70-Premissas!$C$69))*Premissas!$C$21*(1+Premissas!$C$26)^(0) -> 18331.098 | F11: =Dimensionador!$C$7*Premissas!$C$13*(Premissas!$C$69+0.4166666667*(Premissas!$C$70-Premissas!$C$69))*Premissas!$C$20*(1+Premissas!$C$26)^(0) -> 4964.1233 | G11: =Dimensionador!$C$7*Premissas!$C$25*(1+Premissas!$C$27)^(0)/12 -> 1833.3333 | H11: =Premissas!$C$57*(1-Premissas!$C$32)^(0) -> 53437.5 | I11: =MIN(H11,Dimensionador!$C$7*Premissas!$C$13*(Premissas!$C$69+0.4166666667*(Premissas!$C$70-Premissas!$C$69))) -> 7930.3908 | J11: =MAX(0,H11-I11) -> 45507.109 | K11: =Premissas!$C$35*(1+Premissas!$C$27)^(0)/12 -> 989.58333 | L11: =E11-F11+(I11+J11)*Premissas!$C$20*(1+Premissas!$C$26)^(0) -> 46816.819 | M11: =L11-G11-K11 -> 43993.902 | N11: =N10+M11 -> -2021931.1 | O11: =O10+M11 -> 265568.89 | P11: =IF(AND(N11>=0,N10<0),"✅ PAYBACK","") | Q11: =SUM(M66:M77) -> 753786.44 | R11: =SUM(I66:I77) -> 84745.14
A12: 1 | B12: Jul | C12: =Premissas!$C$69+0.5*(Premissas!$C$70-Premissas!$C$69) -> 0.9855 | D12: =(1+Premissas!$C$26)^(0) -> 1 | E12: =Dimensionador!$C$22*(Premissas!$C$69+0.5*(Premissas!$C$70-Premissas!$C$69))*Premissas!$C$21*(1+Premissas!$C$26)^(0) -> 18286.256 | F12: =Dimensionador!$C$7*Premissas!$C$13*(Premissas!$C$69+0.5*(Premissas!$C$70-Premissas!$C$69))*Premissas!$C$20*(1+Premissas!$C$26)^(0) -> 4951.9799 | G12: =Dimensionador!$C$7*Premissas!$C$25*(1+Premissas!$C$27)^(0)/12 -> 1833.3333 | H12: =Premissas!$C$58*(1-Premissas!$C$32)^(0) -> 55218.75 | I12: =MIN(H12,Dimensionador!$C$7*Premissas!$C$13*(Premissas!$C$69+0.5*(Premissas!$C$70-Premissas!$C$69))) -> 7910.9913 | J12: =MAX(0,H12-I12) -> 47307.759 | K12: =Premissas!$C$35*(1+Premissas!$C$27)^(0)/12 -> 989.58333 | L12: =E12-F12+(I12+J12)*Premissas!$C$20*(1+Premissas!$C$26)^(0) -> 47899.115 | M12: =L12-G12-K12 -> 45076.199 | N12: =N11+M12 -> -1976854.9 | O12: =O11+M12 -> 310645.09 | P12: =IF(AND(N12>=0,N11<0),"✅ PAYBACK","") | Q12: =SUM(M78:M89) -> 808265.95 | R12: =SUM(I78:I89) -> 83011.224
A13: 1 | B13: Ago | C13: =Premissas!$C$69+0.5833333333*(Premissas!$C$70-Premissas!$C$69) -> 0.98308333 | D13: =(1+Premissas!$C$26)^(0) -> 1 | E13: =Dimensionador!$C$22*(Premissas!$C$69+0.5833333333*(Premissas!$C$70-Premissas!$C$69))*Premissas!$C$21*(1+Premissas!$C$26)^(0) -> 18241.414 | F13: =Dimensionador!$C$7*Premissas!$C$13*(Premissas!$C$69+0.5833333333*(Premissas!$C$70-Premissas!$C$69))*Premissas!$C$20*(1+Premissas!$C$26)^(0) -> 4939.8366 | G13: =Dimensionador!$C$7*Premissas!$C$25*(1+Premissas!$C$27)^(0)/12 -> 1833.3333 | H13: =Premissas!$C$59*(1-Premissas!$C$32)^(0) -> 55218.75 | I13: =MIN(H13,Dimensionador!$C$7*Premissas!$C$13*(Premissas!$C$69+0.5833333333*(Premissas!$C$70-Premissas!$C$69))) -> 7891.5918 | J13: =MAX(0,H13-I13) -> 47327.158 | K13: =Premissas!$C$35*(1+Premissas!$C$27)^(0)/12 -> 989.58333 | L13: =E13-F13+(I13+J13)*Premissas!$C$20*(1+Premissas!$C$26)^(0) -> 47866.417 | M13: =L13-G13-K13 -> 45043.5 | N13: =N12+M13 -> -1931811.4 | O13: =O12+M13 -> 355688.59 | P13: =IF(AND(N13>=0,N12<0),"✅ PAYBACK","") | Q13: =SUM(M90:M101) -> 866556.78 | R13: =SUM(I90:I101) -> 81277.308
A14: 1 | B14: Set | C14: =Premissas!$C$69+0.6666666667*(Premissas!$C$70-Premissas!$C$69) -> 0.98066667 | D14: =(1+Premissas!$C$26)^(0) -> 1 | E14: =Dimensionador!$C$22*(Premissas!$C$69+0.6666666667*(Premissas!$C$70-Premissas!$C$69))*Premissas!$C$21*(1+Premissas!$C$26)^(0) -> 18196.572 | F14: =Dimensionador!$C$7*Premissas!$C$13*(Premissas!$C$69+0.6666666667*(Premissas!$C$70-Premissas!$C$69))*Premissas!$C$20*(1+Premissas!$C$26)^(0) -> 4927.6932 | G14: =Dimensionador!$C$7*Premissas!$C$25*(1+Premissas!$C$27)^(0)/12 -> 1833.3333 | H14: =Premissas!$C$60*(1-Premissas!$C$32)^(0) -> 53437.5 | I14: =MIN(H14,Dimensionador!$C$7*Premissas!$C$13*(Premissas!$C$69+0.6666666667*(Premissas!$C$70-Premissas!$C$69))) -> 7872.1923 | J14: =MAX(0,H14-I14) -> 45565.308 | K14: =Premissas!$C$35*(1+Premissas!$C$27)^(0)/12 -> 989.58333 | L14: =E14-F14+(I14+J14)*Premissas!$C$20*(1+Premissas!$C$26)^(0) -> 46718.723 | M14: =L14-G14-K14 -> 43895.806 | N14: =N13+M14 -> -1887915.6 | O14: =O13+M14 -> 399584.39 | P14: =IF(AND(N14>=0,N13<0),"✅ PAYBACK","") | Q14: =SUM(M102:M113) -> 929056.14 | R14: =SUM(I102:I113) -> 79587.543
A15: 1 | B15: Out | C15: =Premissas!$C$69+0.75*(Premissas!$C$70-Premissas!$C$69) -> 0.97825 | D15: =(1+Premissas!$C$26)^(0) -> 1 | E15: =Dimensionador!$C$22*(Premissas!$C$69+0.75*(Premissas!$C$70-Premissas!$C$69))*Premissas!$C$21*(1+Premissas!$C$26)^(0) -> 18151.73 | F15: =Dimensionador!$C$7*Premissas!$C$13*(Premissas!$C$69+0.75*(Premissas!$C$70-Premissas!$C$69))*Premissas!$C$20*(1+Premissas!$C$26)^(0) -> 4915.5498 | G15: =Dimensionador!$C$7*Premissas!$C$25*(1+Premissas!$C$27)^(0)/12 -> 1833.3333 | H15: =Premissas!$C$61*(1-Premissas!$C$32)^(0) -> 55218.75 | I15: =MIN(H15,Dimensionador!$C$7*Premissas!$C$13*(Premissas!$C$69+0.75*(Premissas!$C$70-Premissas!$C$69))) -> 7852.7927 | J15: =MAX(0,H15-I15) -> 47365.957 | K15: =Premissas!$C$35*(1+Premissas!$C$27)^(0)/12 -> 989.58333 | L15: =E15-F15+(I15+J15)*Premissas!$C$20*(1+Premissas!$C$26)^(0) -> 47801.019 | M15: =L15-G15-K15 -> 44978.103 | N15: =N14+M15 -> -1842937.5 | O15: =O14+M15 -> 444562.5 | P15: =IF(AND(N15>=0,N14<0),"✅ PAYBACK","") | Q15: =SUM(M114:M125) -> 995951.96 | R15: =SUM(I114:I125) -> 77905.805
A16: 1 | B16: Nov | C16: =Premissas!$C$69+0.8333333333*(Premissas!$C$70-Premissas!$C$69) -> 0.97583333 | D16: =(1+Premissas!$C$26)^(0) -> 1 | E16: =Dimensionador!$C$22*(Premissas!$C$69+0.8333333333*(Premissas!$C$70-Premissas!$C$69))*Premissas!$C$21*(1+Premissas!$C$26)^(0) -> 18106.888 | F16: =Dimensionador!$C$7*Premissas!$C$13*(Premissas!$C$69+0.8333333333*(Premissas!$C$70-Premissas!$C$69))*Premissas!$C$20*(1+Premissas!$C$26)^(0) -> 4903.4065 | G16: =Dimensionador!$C$7*Premissas!$C$25*(1+Premissas!$C$27)^(0)/12 -> 1833.3333 | H16: =Premissas!$C$62*(1-Premissas!$C$32)^(0) -> 53437.5 | I16: =MIN(H16,Dimensionador!$C$7*Premissas!$C$13*(Premissas!$C$69+0.8333333333*(Premissas!$C$70-Premissas!$C$69))) -> 7833.3932 | J16: =MAX(0,H16-I16) -> 45604.107 | K16: =Premissas!$C$35*(1+Premissas!$C$27)^(0)/12 -> 989.58333 | L16: =E16-F16+(I16+J16)*Premissas!$C$20*(1+Premissas!$C$26)^(0) -> 46653.326 | M16: =L16-G16-K16 -> 43830.409 | N16: =N15+M16 -> -1799107.1 | O16: =O15+M16 -> 488392.91 | P16: =IF(AND(N16>=0,N15<0),"✅ PAYBACK","") | Q16: =SUM(M126:M137) -> 1067650.4 | R16: =SUM(I126:I137) -> 76260.19
A17: 1 | B17: Dez | C17: =Premissas!$C$69+0.9166666667*(Premissas!$C$70-Premissas!$C$69) -> 0.97341667 | D17: =(1+Premissas!$C$26)^(0) -> 1 | E17: =Dimensionador!$C$22*(Premissas!$C$69+0.9166666667*(Premissas!$C$70-Premissas!$C$69))*Premissas!$C$21*(1+Premissas!$C$26)^(0) -> 18062.046 | F17: =Dimensionador!$C$7*Premissas!$C$13*(Premissas!$C$69+0.9166666667*(Premissas!$C$70-Premissas!$C$69))*Premissas!$C$20*(1+Premissas!$C$26)^(0) -> 4891.2631 | G17: =Dimensionador!$C$7*Premissas!$C$25*(1+Premissas!$C$27)^(0)/12 -> 1833.3333 | H17: =Premissas!$C$63*(1-Premissas!$C$32)^(0) -> 55218.75 | I17: =MIN(H17,Dimensionador!$C$7*Premissas!$C$13*(Premissas!$C$69+0.9166666667*(Premissas!$C$70-Premissas!$C$69))) -> 7813.9937 | J17: =MAX(0,H17-I17) -> 47404.756 | K17: =Premissas!$C$35*(1+Premissas!$C$27)^(0)/12 -> 989.58333 | L17: =E17-F17+(I17+J17)*Premissas!$C$20*(1+Premissas!$C$26)^(0) -> 47735.622 | M17: =L17-G17-K17 -> 44912.705 | N17: =N16+M17 -> -1754194.4 | O17: =O16+M17 -> 533305.61 | P17: =IF(AND(N17>=0,N16<0),"✅ PAYBACK","") | Q17: =SUM(M138:M149) -> 1144074.8 | R17: =SUM(I138:I149) -> 74542.329
A18: 2 | B18: Jan | C18: =Premissas!$C$70+0*(Premissas!$C$71-Premissas!$C$70) -> 0.971 | D18: =(1+Premissas!$C$26)^(1) -> 1.08 | E18: =Dimensionador!$C$22*(Premissas!$C$70+0*(Premissas!$C$71-Premissas!$C$70))*Premissas!$C$21*(1+Premissas!$C$26)^(1) -> 19458.58 | F18: =Dimensionador!$C$7*Premissas!$C$13*(Premissas!$C$70+0*(Premissas!$C$71-Premissas!$C$70))*Premissas!$C$20*(1+Premissas!$C$26)^(1) -> 5269.4493 | G18: =Dimensionador!$C$7*Premissas!$C$25*(1+Premissas!$C$27)^(1)/12 -> 1888.3333 | H18: =Premissas!$C$52*(1-Premissas!$C$32)^(1) -> 54942.656 | I18: =MIN(H18,Dimensionador!$C$7*Premissas!$C$13*(Premissas!$C$70+0*(Premissas!$C$71-Premissas!$C$70))) -> 7794.5942 | J18: =MAX(0,H18-I18) -> 47148.062 | K18: =Premissas!$C$35*(1+Premissas!$C$27)^(1)/12 -> 1019.2708 | L18: =E18-F18+(I18+J18)*Premissas!$C$20*(1+Premissas!$C$26)^(1) -> 51332.507 | M18: =L18-G18-K18 -> 48424.903 | N18: =N17+M18 -> -1705769.5 | O18: =O17+M18 -> 581730.51 | P18: =IF(AND(N18>=0,N17<0),"✅ PAYBACK","") | Q18: =SUM(M150:M161) -> 1226230.6 | R18: =SUM(I150:I161) -> 72924.81
A19: 2 | B19: Fev | C19: =Premissas!$C$70+0.0833333333*(Premissas!$C$71-Premissas!$C$70) -> 0.96908333 | D19: =(1+Premissas!$C$26)^(1) -> 1.08 | E19: =Dimensionador!$C$22*(Premissas!$C$70+0.0833333333*(Premissas!$C$71-Premissas!$C$70))*Premissas!$C$21*(1+Premissas!$C$26)^(1) -> 19420.171 | F19: =Dimensionador!$C$7*Premissas!$C$13*(Premissas!$C$70+0.0833333333*(Premissas!$C$71-Premissas!$C$70))*Premissas!$C$20*(1+Premissas!$C$26)^(1) -> 5259.0479 | G19: =Dimensionador!$C$7*Premissas!$C$25*(1+Premissas!$C$27)^(1)/12 -> 1888.3333 | H19: =Premissas!$C$53*(1-Premissas!$C$32)^(1) -> 49625.625 | I19: =MIN(H19,Dimensionador!$C$7*Premissas!$C$13*(Premissas!$C$70+0.0833333333*(Premissas!$C$71-Premissas!$C$70))) -> 7779.2083 | J19: =MAX(0,H19-I19) -> 41846.417 | K19: =Premissas!$C$35*(1+Premissas!$C$27)^(1)/12 -> 1019.2708 | L19: =E19-F19+(I19+J19)*Premissas!$C$20*(1+Premissas!$C$26)^(1) -> 47709.979 | M19: =L19-G19-K19 -> 44802.375 | N19: =N18+M19 -> -1660967.1 | O19: =O18+M19 -> 626532.89 | P19: =IF(AND(N19>=0,N18<0),"✅ PAYBACK","") | Q19: =SUM(M162:M173) -> 1315185.3 | R19: =SUM(I162:I173) -> 71540.086
A20: 2 | B20: Mar | C20: =Premissas!$C$70+0.1666666667*(Premissas!$C$71-Premissas!$C$70) -> 0.96716667 | D20: =(1+Premissas!$C$26)^(1) -> 1.08 | E20: =Dimensionador!$C$22*(Premissas!$C$70+0.1666666667*(Premissas!$C$71-Premissas!$C$70))*Premissas!$C$21*(1+Premissas!$C$26)^(1) -> 19381.761 | F20: =Dimensionador!$C$7*Premissas!$C$13*(Premissas!$C$70+0.1666666667*(Premissas!$C$71-Premissas!$C$70))*Premissas!$C$20*(1+Premissas!$C$26)^(1) -> 5248.6465 | G20: =Dimensionador!$C$7*Premissas!$C$25*(1+Premissas!$C$27)^(1)/12 -> 1888.3333 | H20: =Premissas!$C$54*(1-Premissas!$C$32)^(1) -> 54942.656 | I20: =MIN(H20,Dimensionador!$C$7*Premissas!$C$13*(Premissas!$C$70+0.1666666667*(Premissas!$C$71-Premissas!$C$70))) -> 7763.8225 | J20: =MAX(0,H20-I20) -> 47178.834 | K20: =Premissas!$C$35*(1+Premissas!$C$27)^(1)/12 -> 1019.2708 | L20: =E20-F20+(I20+J20)*Premissas!$C$20*(1+Premissas!$C$26)^(1) -> 51276.491 | M20: =L20-G20-K20 -> 48368.887 | N20: =N19+M20 -> -1612598.2 | O20: =O19+M20 -> 674901.78 | P20: =IF(AND(N20>=0,N19<0),"✅ PAYBACK","") | Q20: =SUM(M174:M185) -> 1409657.3 | R20: =SUM(I174:I185) -> 69998.827
A21: 2 | B21: Abr | C21: =Premissas!$C$70+0.25*(Premissas!$C$71-Premissas!$C$70) -> 0.96525 | D21: =(1+Premissas!$C$26)^(1) -> 1.08 | E21: =Dimensionador!$C$22*(Premissas!$C$70+0.25*(Premissas!$C$71-Premissas!$C$70))*Premissas!$C$21*(1+Premissas!$C$26)^(1) -> 19343.352 | F21: =Dimensionador!$C$7*Premissas!$C$13*(Premissas!$C$70+0.25*(Premissas!$C$71-Premissas!$C$70))*Premissas!$C$20*(1+Premissas!$C$26)^(1) -> 5238.2451 | G21: =Dimensionador!$C$7*Premissas!$C$25*(1+Premissas!$C$27)^(1)/12 -> 1888.3333 | H21: =Premissas!$C$55*(1-Premissas!$C$32)^(1) -> 53170.312 | I21: =MIN(H21,Dimensionador!$C$7*Premissas!$C$13*(Premissas!$C$70+0.25*(Premissas!$C$71-Premissas!$C$70))) -> 7748.4367 | J21: =MAX(0,H21-I21) -> 45421.876 | K21: =Premissas!$C$35*(1+Premissas!$C$27)^(1)/12 -> 1019.2708 | L21: =E21-F21+(I21+J21)*Premissas!$C$20*(1+Premissas!$C$26)^(1) -> 50050.31 | M21: =L21-G21-K21 -> 47142.705 | N21: =N20+M21 -> -1565455.5 | O21: =O20+M21 -> 722044.48 | P21: =IF(AND(N21>=0,N20<0),"✅ PAYBACK","") | Q21: =SUM(M186:M197) -> 1510969.6 | R21: =SUM(I186:I197) -> 68501.719
A22: 2 | B22: Mai | C22: =Premissas!$C$70+0.3333333333*(Premissas!$C$71-Premissas!$C$70) -> 0.96333333 | D22: =(1+Premissas!$C$26)^(1) -> 1.08 | E22: =Dimensionador!$C$22*(Premissas!$C$70+0.3333333333*(Premissas!$C$71-Premissas!$C$70))*Premissas!$C$21*(1+Premissas!$C$26)^(1) -> 19304.942 | F22: =Dimensionador!$C$7*Premissas!$C$13*(Premissas!$C$70+0.3333333333*(Premissas!$C$71-Premissas!$C$70))*Premissas!$C$20*(1+Premissas!$C$26)^(1) -> 5227.8437 | G22: =Dimensionador!$C$7*Premissas!$C$25*(1+Premissas!$C$27)^(1)/12 -> 1888.3333 | H22: =Premissas!$C$56*(1-Premissas!$C$32)^(1) -> 54942.656 | I22: =MIN(H22,Dimensionador!$C$7*Premissas!$C$13*(Premissas!$C$70+0.3333333333*(Premissas!$C$71-Premissas!$C$70))) -> 7733.0509 | J22: =MAX(0,H22-I22) -> 47209.605 | K22: =Premissas!$C$35*(1+Premissas!$C$27)^(1)/12 -> 1019.2708 | L22: =E22-F22+(I22+J22)*Premissas!$C$20*(1+Premissas!$C$26)^(1) -> 51220.475 | M22: =L22-G22-K22 -> 48312.871 | N22: =N21+M22 -> -1517142.6 | O22: =O21+M22 -> 770357.35 | P22: =IF(AND(N22>=0,N21<0),"✅ PAYBACK","") | Q22: =SUM(M198:M209) -> 1619675.7 | R22: =SUM(I198:I209) -> 67056.789
A23: 2 | B23: Jun | C23: =Premissas!$C$70+0.4166666667*(Premissas!$C$71-Premissas!$C$70) -> 0.96141667 | D23: =(1+Premissas!$C$26)^(1) -> 1.08 | E23: =Dimensionador!$C$22*(Premissas!$C$70+0.4166666667*(Premissas!$C$71-Premissas!$C$70))*Premissas!$C$21*(1+Premissas!$C$26)^(1) -> 19266.533 | F23: =Dimensionador!$C$7*Premissas!$C$13*(Premissas!$C$70+0.4166666667*(Premissas!$C$71-Premissas!$C$70))*Premissas!$C$20*(1+Premissas!$C$26)^(1) -> 5217.4422 | G23: =Dimensionador!$C$7*Premissas!$C$25*(1+Premissas!$C$27)^(1)/12 -> 1888.3333 | H23: =Premissas!$C$57*(1-Premissas!$C$32)^(1) -> 53170.312 | I23: =MIN(H23,Dimensionador!$C$7*Premissas!$C$13*(Premissas!$C$70+0.4166666667*(Premissas!$C$71-Premissas!$C$70))) -> 7717.665 | J23: =MAX(0,H23-I23) -> 45452.647 | K23: =Premissas!$C$35*(1+Premissas!$C$27)^(1)/12 -> 1019.2708 | L23: =E23-F23+(I23+J23)*Premissas!$C$20*(1+Premissas!$C$26)^(1) -> 49994.293 | M23: =L23-G23-K23 -> 47086.689 | N23: =N22+M23 -> -1470056 | O23: =O22+M23 -> 817444.04 | P23: =IF(AND(N23>=0,N22<0),"✅ PAYBACK","") | Q23: =SUM(M210:M221) -> 1736007.7 | R23: =SUM(I210:I221) -> 65611.859
A24: 2 | B24: Jul | C24: =Premissas!$C$70+0.5*(Premissas!$C$71-Premissas!$C$70) -> 0.9595 | D24: =(1+Premissas!$C$26)^(1) -> 1.08 | E24: =Dimensionador!$C$22*(Premissas!$C$70+0.5*(Premissas!$C$71-Premissas!$C$70))*Premissas!$C$21*(1+Premissas!$C$26)^(1) -> 19228.123 | F24: =Dimensionador!$C$7*Premissas!$C$13*(Premissas!$C$70+0.5*(Premissas!$C$71-Premissas!$C$70))*Premissas!$C$20*(1+Premissas!$C$26)^(1) -> 5207.0408 | G24: =Dimensionador!$C$7*Premissas!$C$25*(1+Premissas!$C$27)^(1)/12 -> 1888.3333 | H24: =Premissas!$C$58*(1-Premissas!$C$32)^(1) -> 54942.656 | I24: =MIN(H24,Dimensionador!$C$7*Premissas!$C$13*(Premissas!$C$70+0.5*(Premissas!$C$71-Premissas!$C$70))) -> 7702.2792 | J24: =MAX(0,H24-I24) -> 47240.377 | K24: =Premissas!$C$35*(1+Premissas!$C$27)^(1)/12 -> 1019.2708 | L24: =E24-F24+(I24+J24)*Premissas!$C$20*(1+Premissas!$C$26)^(1) -> 51164.459 | M24: =L24-G24-K24 -> 48256.855 | N24: =N23+M24 -> -1421799.1 | O24: =O23+M24 -> 865700.9 | P24: =IF(AND(N24>=0,N23<0),"✅ PAYBACK","") | Q24: =SUM(M222:M233) -> 1860785.7 | R24: =SUM(I222:I233) -> 64211.08
A25: 2 | B25: Ago | C25: =Premissas!$C$70+0.5833333333*(Premissas!$C$71-Premissas!$C$70) -> 0.95758333 | D25: =(1+Premissas!$C$26)^(1) -> 1.08 | E25: =Dimensionador!$C$22*(Premissas!$C$70+0.5833333333*(Premissas!$C$71-Premissas!$C$70))*Premissas!$C$21*(1+Premissas!$C$26)^(1) -> 19189.714 | F25: =Dimensionador!$C$7*Premissas!$C$13*(Premissas!$C$70+0.5833333333*(Premissas!$C$71-Premissas!$C$70))*Premissas!$C$20*(1+Premissas!$C$26)^(1) -> 5196.6394 | G25: =Dimensionador!$C$7*Premissas!$C$25*(1+Premissas!$C$27)^(1)/12 -> 1888.3333 | H25: =Premissas!$C$59*(1-Premissas!$C$32)^(1) -> 54942.656 | I25: =MIN(H25,Dimensionador!$C$7*Premissas!$C$13*(Premissas!$C$70+0.5833333333*(Premissas!$C$71-Premissas!$C$70))) -> 7686.8934 | J25: =MAX(0,H25-I25) -> 47255.763 | K25: =Premissas!$C$35*(1+Premissas!$C$27)^(1)/12 -> 1019.2708 | L25: =E25-F25+(I25+J25)*Premissas!$C$20*(1+Premissas!$C$26)^(1) -> 51136.451 | M25: =L25-G25-K25 -> 48228.847 | N25: =N24+M25 -> -1373570.3 | O25: =O24+M25 -> 913929.74 | P25: =IF(AND(N25>=0,N24<0),"✅ PAYBACK","") | Q25: =SUM(M234:M245) -> 1994697.8 | R25: =SUM(I234:I245) -> 62862.479
A26: 2 | B26: Set | C26: =Premissas!$C$70+0.6666666667*(Premissas!$C$71-Premissas!$C$70) -> 0.95566667 | D26: =(1+Premissas!$C$26)^(1) -> 1.08 | E26: =Dimensionador!$C$22*(Premissas!$C$70+0.6666666667*(Premissas!$C$71-Premissas!$C$70))*Premissas!$C$21*(1+Premissas!$C$26)^(1) -> 19151.304 | F26: =Dimensionador!$C$7*Premissas!$C$13*(Premissas!$C$70+0.6666666667*(Premissas!$C$71-Premissas!$C$70))*Premissas!$C$20*(1+Premissas!$C$26)^(1) -> 5186.238 | G26: =Dimensionador!$C$7*Premissas!$C$25*(1+Premissas!$C$27)^(1)/12 -> 1888.3333 | H26: =Premissas!$C$60*(1-Premissas!$C$32)^(1) -> 53170.312 | I26: =MIN(H26,Dimensionador!$C$7*Premissas!$C$13*(Premissas!$C$70+0.6666666667*(Premissas!$C$71-Premissas!$C$70))) -> 7671.5075 | J26: =MAX(0,H26-I26) -> 45498.805 | K26: =Premissas!$C$35*(1+Premissas!$C$27)^(1)/12 -> 1019.2708 | L26: =E26-F26+(I26+J26)*Premissas!$C$20*(1+Premissas!$C$26)^(1) -> 49910.269 | M26: =L26-G26-K26 -> 47002.665 | N26: =N25+M26 -> -1326567.6 | O26: =O25+M26 -> 960932.41 | P26: =IF(AND(N26>=0,N25<0),"✅ PAYBACK","") | Q26: =I26 -> 7671.5075
A27: 2 | B27: Out | C27: =Premissas!$C$70+0.75*(Premissas!$C$71-Premissas!$C$70) -> 0.95375 | D27: =(1+Premissas!$C$26)^(1) -> 1.08 | E27: =Dimensionador!$C$22*(Premissas!$C$70+0.75*(Premissas!$C$71-Premissas!$C$70))*Premissas!$C$21*(1+Premissas!$C$26)^(1) -> 19112.895 | F27: =Dimensionador!$C$7*Premissas!$C$13*(Premissas!$C$70+0.75*(Premissas!$C$71-Premissas!$C$70))*Premissas!$C$20*(1+Premissas!$C$26)^(1) -> 5175.8366 | G27: =Dimensionador!$C$7*Premissas!$C$25*(1+Premissas!$C$27)^(1)/12 -> 1888.3333 | H27: =Premissas!$C$61*(1-Premissas!$C$32)^(1) -> 54942.656 | I27: =MIN(H27,Dimensionador!$C$7*Premissas!$C$13*(Premissas!$C$70+0.75*(Premissas!$C$71-Premissas!$C$70))) -> 7656.1217 | J27: =MAX(0,H27-I27) -> 47286.535 | K27: =Premissas!$C$35*(1+Premissas!$C$27)^(1)/12 -> 1019.2708 | L27: =E27-F27+(I27+J27)*Premissas!$C$20*(1+Premissas!$C$26)^(1) -> 51080.435 | M27: =L27-G27-K27 -> 48172.83 | N27: =N26+M27 -> -1278394.8 | O27: =O26+M27 -> 1009105.2 | P27: =IF(AND(N27>=0,N26<0),"✅ PAYBACK","") | Q27: =I27 -> 7656.1217
A28: 2 | B28: Nov | C28: =Premissas!$C$70+0.8333333333*(Premissas!$C$71-Premissas!$C$70) -> 0.95183333 | D28: =(1+Premissas!$C$26)^(1) -> 1.08 | E28: =Dimensionador!$C$22*(Premissas!$C$70+0.8333333333*(Premissas!$C$71-Premissas!$C$70))*Premissas!$C$21*(1+Premissas!$C$26)^(1) -> 19074.485 | F28: =Dimensionador!$C$7*Premissas!$C$13*(Premissas!$C$70+0.8333333333*(Premissas!$C$71-Premissas!$C$70))*Premissas!$C$20*(1+Premissas!$C$26)^(1) -> 5165.4351 | G28: =Dimensionador!$C$7*Premissas!$C$25*(1+Premissas!$C$27)^(1)/12 -> 1888.3333 | H28: =Premissas!$C$62*(1-Premissas!$C$32)^(1) -> 53170.312 | I28: =MIN(H28,Dimensionador!$C$7*Premissas!$C$13*(Premissas!$C$70+0.8333333333*(Premissas!$C$71-Premissas!$C$70))) -> 7640.7359 | J28: =MAX(0,H28-I28) -> 45529.577 | K28: =Premissas!$C$35*(1+Premissas!$C$27)^(1)/12 -> 1019.2708 | L28: =E28-F28+(I28+J28)*Premissas!$C$20*(1+Premissas!$C$26)^(1) -> 49854.253 | M28: =L28-G28-K28 -> 46946.649 | N28: =N27+M28 -> -1231448.1 | O28: =O27+M28 -> 1056051.9 | P28: =IF(AND(N28>=0,N27<0),"✅ PAYBACK","") | Q28: =I28 -> 7640.7359
A29: 2 | B29: Dez | C29: =Premissas!$C$70+0.9166666667*(Premissas!$C$71-Premissas!$C$70) -> 0.94991667 | D29: =(1+Premissas!$C$26)^(1) -> 1.08 | E29: =Dimensionador!$C$22*(Premissas!$C$70+0.9166666667*(Premissas!$C$71-Premissas!$C$70))*Premissas!$C$21*(1+Premissas!$C$26)^(1) -> 19036.076 | F29: =Dimensionador!$C$7*Premissas!$C$13*(Premissas!$C$70+0.9166666667*(Premissas!$C$71-Premissas!$C$70))*Premissas!$C$20*(1+Premissas!$C$26)^(1) -> 5155.0337 | G29: =Dimensionador!$C$7*Premissas!$C$25*(1+Premissas!$C$27)^(1)/12 -> 1888.3333 | H29: =Premissas!$C$63*(1-Premissas!$C$32)^(1) -> 54942.656 | I29: =MIN(H29,Dimensionador!$C$7*Premissas!$C$13*(Premissas!$C$70+0.9166666667*(Premissas!$C$71-Premissas!$C$70))) -> 7625.3501 | J29: =MAX(0,H29-I29) -> 47317.306 | K29: =Premissas!$C$35*(1+Premissas!$C$27)^(1)/12 -> 1019.2708 | L29: =E29-F29+(I29+J29)*Premissas!$C$20*(1+Premissas!$C$26)^(1) -> 51024.418 | M29: =L29-G29-K29 -> 48116.814 | N29: =N28+M29 -> -1183331.3 | O29: =O28+M29 -> 1104168.7 | P29: =IF(AND(N29>=0,N28<0),"✅ PAYBACK","") | Q29: =I29 -> 7625.3501
A30: 3 | B30: Jan | C30: =Premissas!$C$71+0*(Premissas!$C$72-Premissas!$C$71) -> 0.948 | D30: =(1+Premissas!$C$26)^(2) -> 1.1664 | E30: =Dimensionador!$C$22*(Premissas!$C$71+0*(Premissas!$C$72-Premissas!$C$71))*Premissas!$C$21*(1+Premissas!$C$26)^(2) -> 20517.48 | F30: =Dimensionador!$C$7*Premissas!$C$13*(Premissas!$C$71+0*(Premissas!$C$72-Premissas!$C$71))*Premissas!$C$20*(1+Premissas!$C$26)^(2) -> 5556.2029 | G30: =Dimensionador!$C$7*Premissas!$C$25*(1+Premissas!$C$27)^(2)/12 -> 1944.9833 | H30: =Premissas!$C$52*(1-Premissas!$C$32)^(2) -> 54667.943 | I30: =MIN(H30,Dimensionador!$C$7*Premissas!$C$13*(Premissas!$C$71+0*(Premissas!$C$72-Premissas!$C$71))) -> 7609.9642 | J30: =MAX(0,H30-I30) -> 47057.979 | K30: =Premissas!$C$35*(1+Premissas!$C$27)^(2)/12 -> 1049.849 | L30: =E30-F30+(I30+J30)*Premissas!$C$20*(1+Premissas!$C$26)^(2) -> 54875.549 | M30: =L30-G30-K30 -> 51880.717 | N30: =N29+M30 -> -1131450.6 | O30: =O29+M30 -> 1156049.4 | P30: =IF(AND(N30>=0,N29<0),"✅ PAYBACK","") | Q30: =I30 -> 7609.9642
A31: 3 | B31: Fev | C31: =Premissas!$C$71+0.0833333333*(Premissas!$C$72-Premissas!$C$71) -> 0.94625 | D31: =(1+Premissas!$C$26)^(2) -> 1.1664 | E31: =Dimensionador!$C$22*(Premissas!$C$71+0.0833333333*(Premissas!$C$72-Premissas!$C$71))*Premissas!$C$21*(1+Premissas!$C$26)^(2) -> 20479.605 | F31: =Dimensionador!$C$7*Premissas!$C$13*(Premissas!$C$71+0.0833333333*(Premissas!$C$72-Premissas!$C$71))*Premissas!$C$20*(1+Premissas!$C$26)^(2) -> 5545.9462 | G31: =Dimensionador!$C$7*Premissas!$C$25*(1+Premissas!$C$27)^(2)/12 -> 1944.9833 | H31: =Premissas!$C$53*(1-Premissas!$C$32)^(2) -> 49377.497 | I31: =MIN(H31,Dimensionador!$C$7*Premissas!$C$13*(Premissas!$C$71+0.0833333333*(Premissas!$C$72-Premissas!$C$71))) -> 7595.9163 | J31: =MAX(0,H31-I31) -> 41781.581 | K31: =Premissas!$C$35*(1+Premissas!$C$27)^(2)/12 -> 1049.849 | L31: =E31-F31+(I31+J31)*Premissas!$C$20*(1+Premissas!$C$26)^(2) -> 50985.259 | M31: =L31-G31-K31 -> 47990.427 | N31: =N30+M31 -> -1083460.2 | O31: =O30+M31 -> 1204039.8 | P31: =IF(AND(N31>=0,N30<0),"✅ PAYBACK","") | Q31: =I31 -> 7595.9163
A32: 3 | B32: Mar | C32: =Premissas!$C$71+0.1666666667*(Premissas!$C$72-Premissas!$C$71) -> 0.9445 | D32: =(1+Premissas!$C$26)^(2) -> 1.1664 | E32: =Dimensionador!$C$22*(Premissas!$C$71+0.1666666667*(Premissas!$C$72-Premissas!$C$71))*Premissas!$C$21*(1+Premissas!$C$26)^(2) -> 20441.73 | F32: =Dimensionador!$C$7*Premissas!$C$13*(Premissas!$C$71+0.1666666667*(Premissas!$C$72-Premissas!$C$71))*Premissas!$C$20*(1+Premissas!$C$26)^(2) -> 5535.6895 | G32: =Dimensionador!$C$7*Premissas!$C$25*(1+Premissas!$C$27)^(2)/12 -> 1944.9833 | H32: =Premissas!$C$54*(1-Premissas!$C$32)^(2) -> 54667.943 | I32: =MIN(H32,Dimensionador!$C$7*Premissas!$C$13*(Premissas!$C$71+0.1666666667*(Premissas!$C$72-Premissas!$C$71))) -> 7581.8684 | J32: =MAX(0,H32-I32) -> 47086.075 | K32: =Premissas!$C$35*(1+Premissas!$C$27)^(2)/12 -> 1049.849 | L32: =E32-F32+(I32+J32)*Premissas!$C$20*(1+Premissas!$C$26)^(2) -> 54820.312 | M32: =L32-G32-K32 -> 51825.48 | N32: =N31+M32 -> -1031634.7 | O32: =O31+M32 -> 1255865.3 | P32: =IF(AND(N32>=0,N31<0),"✅ PAYBACK","") | Q32: =I32 -> 7581.8684
A33: 3 | B33: Abr | C33: =Premissas!$C$71+0.25*(Premissas!$C$72-Premissas!$C$71) -> 0.94275 | D33: =(1+Premissas!$C$26)^(2) -> 1.1664 | E33: =Dimensionador!$C$22*(Premissas!$C$71+0.25*(Premissas!$C$72-Premissas!$C$71))*Premissas!$C$21*(1+Premissas!$C$26)^(2) -> 20403.855 | F33: =Dimensionador!$C$7*Premissas!$C$13*(Premissas!$C$71+0.25*(Premissas!$C$72-Premissas!$C$71))*Premissas!$C$20*(1+Premissas!$C$26)^(2) -> 5525.4328 | G33: =Dimensionador!$C$7*Premissas!$C$25*(1+Premissas!$C$27)^(2)/12 -> 1944.9833 | H33: =Premissas!$C$55*(1-Premissas!$C$32)^(2) -> 52904.461 | I33: =MIN(H33,Dimensionador!$C$7*Premissas!$C$13*(Premissas!$C$71+0.25*(Premissas!$C$72-Premissas!$C$71))) -> 7567.8204 | J33: =MAX(0,H33-I33) -> 45336.64 | K33: =Premissas!$C$35*(1+Premissas!$C$27)^(2)/12 -> 1049.849 | L33: =E33-F33+(I33+J33)*Premissas!$C$20*(1+Premissas!$C$26)^(2) -> 53505.137 | M33: =L33-G33-K33 -> 50510.304 | N33: =N32+M33 -> -981124.37 | O33: =O32+M33 -> 1306375.6 | P33: =IF(AND(N33>=0,N32<0),"✅ PAYBACK","") | Q33: =I33 -> 7567.8204
A34: 3 | B34: Mai | C34: =Premissas!$C$71+0.3333333333*(Premissas!$C$72-Premissas!$C$71) -> 0.941 | D34: =(1+Premissas!$C$26)^(2) -> 1.1664 | E34: =Dimensionador!$C$22*(Premissas!$C$71+0.3333333333*(Premissas!$C$72-Premissas!$C$71))*Premissas!$C$21*(1+Premissas!$C$26)^(2) -> 20365.979 | F34: =Dimensionador!$C$7*Premissas!$C$13*(Premissas!$C$71+0.3333333333*(Premissas!$C$72-Premissas!$C$71))*Premissas!$C$20*(1+Premissas!$C$26)^(2) -> 5515.1761 | G34: =Dimensionador!$C$7*Premissas!$C$25*(1+Premissas!$C$27)^(2)/12 -> 1944.9833 | H34: =Premissas!$C$56*(1-Premissas!$C$32)^(2) -> 54667.943 | I34: =MIN(H34,Dimensionador!$C$7*Premissas!$C$13*(Premissas!$C$71+0.3333333333*(Premissas!$C$72-Premissas!$C$71))) -> 7553.7725 | J34: =MAX(0,H34-I34) -> 47114.17 | K34: =Premissas!$C$35*(1+Premissas!$C$27)^(2)/12 -> 1049.849 | L34: =E34-F34+(I34+J34)*Premissas!$C$20*(1+Premissas!$C$26)^(2) -> 54765.075 | M34: =L34-G34-K34 -> 51770.243 | N34: =N33+M34 -> -929354.13 | O34: =O33+M34 -> 1358145.9 | P34: =IF(AND(N34>=0,N33<0),"✅ PAYBACK","") | Q34: =I34 -> 7553.7725
A35: 3 | B35: Jun | C35: =Premissas!$C$71+0.4166666667*(Premissas!$C$72-Premissas!$C$71) -> 0.93925 | D35: =(1+Premissas!$C$26)^(2) -> 1.1664 | E35: =Dimensionador!$C$22*(Premissas!$C$71+0.4166666667*(Premissas!$C$72-Premissas!$C$71))*Premissas!$C$21*(1+Premissas!$C$26)^(2) -> 20328.104 | F35: =Dimensionador!$C$7*Premissas!$C$13*(Premissas!$C$71+0.4166666667*(Premissas!$C$72-Premissas!$C$71))*Premissas!$C$20*(1+Premissas!$C$26)^(2) -> 5504.9194 | G35: =Dimensionador!$C$7*Premissas!$C$25*(1+Premissas!$C$27)^(2)/12 -> 1944.9833 | H35: =Premissas!$C$57*(1-Premissas!$C$32)^(2) -> 52904.461 | I35: =MIN(H35,Dimensionador!$C$7*Premissas!$C$13*(Premissas!$C$71+0.4166666667*(Premissas!$C$72-Premissas!$C$71))) -> 7539.7246 | J35: =MAX(0,H35-I35) -> 45364.736 | K35: =Premissas!$C$35*(1+Premissas!$C$27)^(2)/12 -> 1049.849 | L35: =E35-F35+(I35+J35)*Premissas!$C$20*(1+Premissas!$C$26)^(2) -> 53449.9 | M35: =L35-G35-K35 -> 50455.068 | N35: =N34+M35 -> -878899.06 | O35: =O34+M35 -> 1408600.9 | P35: =IF(AND(N35>=0,N34<0),"✅ PAYBACK","") | Q35: =I35 -> 7539.7246
A36: 3 | B36: Jul | C36: =Premissas!$C$71+0.5*(Premissas!$C$72-Premissas!$C$71) -> 0.9375 | D36: =(1+Premissas!$C$26)^(2) -> 1.1664 | E36: =Dimensionador!$C$22*(Premissas!$C$71+0.5*(Premissas!$C$72-Premissas!$C$71))*Premissas!$C$21*(1+Premissas!$C$26)^(2) -> 20290.229 | F36: =Dimensionador!$C$7*Premissas!$C$13*(Premissas!$C$71+0.5*(Premissas!$C$72-Premissas!$C$71))*Premissas!$C$20*(1+Premissas!$C$26)^(2) -> 5494.6627 | G36: =Dimensionador!$C$7*Premissas!$C$25*(1+Premissas!$C$27)^(2)/12 -> 1944.9833 | H36: =Premissas!$C$58*(1-Premissas!$C$32)^(2) -> 54667.943 | I36: =MIN(H36,Dimensionador!$C$7*Premissas!$C$13*(Premissas!$C$71+0.5*(Premissas!$C$72-Premissas!$C$71))) -> 7525.6767 | J36: =MAX(0,H36-I36) -> 47142.266 | K36: =Premissas!$C$35*(1+Premissas!$C$27)^(2)/12 -> 1049.849 | L36: =E36-F36+(I36+J36)*Premissas!$C$20*(1+Premissas!$C$26)^(2) -> 54709.839 | M36: =L36-G36-K36 -> 51715.006 | N36: =N35+M36 -> -827184.05 | O36: =O35+M36 -> 1460315.9 | P36: =IF(AND(N36>=0,N35<0),"✅ PAYBACK","") | Q36: =I36 -> 7525.6767
A37: 3 | B37: Ago | C37: =Premissas!$C$71+0.5833333333*(Premissas!$C$72-Premissas!$C$71) -> 0.93575 | D37: =(1+Premissas!$C$26)^(2) -> 1.1664 | E37: =Dimensionador!$C$22*(Premissas!$C$71+0.5833333333*(Premissas!$C$72-Premissas!$C$71))*Premissas!$C$21*(1+Premissas!$C$26)^(2) -> 20252.354 | F37: =Dimensionador!$C$7*Premissas!$C$13*(Premissas!$C$71+0.5833333333*(Premissas!$C$72-Premissas!$C$71))*Premissas!$C$20*(1+Premissas!$C$26)^(2) -> 5484.406 | G37: =Dimensionador!$C$7*Premissas!$C$25*(1+Premissas!$C$27)^(2)/12 -> 1944.9833 | H37: =Premissas!$C$59*(1-Premissas!$C$32)^(2) -> 54667.943 | I37: =MIN(H37,Dimensionador!$C$7*Premissas!$C$13*(Premissas!$C$71+0.5833333333*(Premissas!$C$72-Premissas!$C$71))) -> 7511.6287 | J37: =MAX(0,H37-I37) -> 47156.314 | K37: =Premissas!$C$35*(1+Premissas!$C$27)^(2)/12 -> 1049.849 | L37: =E37-F37+(I37+J37)*Premissas!$C$20*(1+Premissas!$C$26)^(2) -> 54682.22 | M37: =L37-G37-K37 -> 51687.388 | N37: =N36+M37 -> -775496.67 | O37: =O36+M37 -> 1512003.3 | P37: =IF(AND(N37>=0,N36<0),"✅ PAYBACK","") | Q37: =I37 -> 7511.6287
A38: 3 | B38: Set | C38: =Premissas!$C$71+0.6666666667*(Premissas!$C$72-Premissas!$C$71) -> 0.934 | D38: =(1+Premissas!$C$26)^(2) -> 1.1664 | E38: =Dimensionador!$C$22*(Premissas!$C$71+0.6666666667*(Premissas!$C$72-Premissas!$C$71))*Premissas!$C$21*(1+Premissas!$C$26)^(2) -> 20214.479 | F38: =Dimensionador!$C$7*Premissas!$C$13*(Premissas!$C$71+0.6666666667*(Premissas!$C$72-Premissas!$C$71))*Premissas!$C$20*(1+Premissas!$C$26)^(2) -> 5474.1493 | G38: =Dimensionador!$C$7*Premissas!$C$25*(1+Premissas!$C$27)^(2)/12 -> 1944.9833 | H38: =Premissas!$C$60*(1-Premissas!$C$32)^(2) -> 52904.461 | I38: =MIN(H38,Dimensionador!$C$7*Premissas!$C$13*(Premissas!$C$71+0.6666666667*(Premissas!$C$72-Premissas!$C$71))) -> 7497.5808 | J38: =MAX(0,H38-I38) -> 45406.88 | K38: =Premissas!$C$35*(1+Premissas!$C$27)^(2)/12 -> 1049.849 | L38: =E38-F38+(I38+J38)*Premissas!$C$20*(1+Premissas!$C$26)^(2) -> 53367.045 | M38: =L38-G38-K38 -> 50372.212 | N38: =N37+M38 -> -725124.45 | O38: =O37+M38 -> 1562375.5 | P38: =IF(AND(N38>=0,N37<0),"✅ PAYBACK","") | Q38: =I38 -> 7497.5808
A39: 3 | B39: Out | C39: =Premissas!$C$71+0.75*(Premissas!$C$72-Premissas!$C$71) -> 0.93225 | D39: =(1+Premissas!$C$26)^(2) -> 1.1664 | E39: =Dimensionador!$C$22*(Premissas!$C$71+0.75*(Premissas!$C$72-Premissas!$C$71))*Premissas!$C$21*(1+Premissas!$C$26)^(2) -> 20176.604 | F39: =Dimensionador!$C$7*Premissas!$C$13*(Premissas!$C$71+0.75*(Premissas!$C$72-Premissas!$C$71))*Premissas!$C$20*(1+Premissas!$C$26)^(2) -> 5463.8926 | G39: =Dimensionador!$C$7*Premissas!$C$25*(1+Premissas!$C$27)^(2)/12 -> 1944.9833 | H39: =Premissas!$C$61*(1-Premissas!$C$32)^(2) -> 54667.943 | I39: =MIN(H39,Dimensionador!$C$7*Premissas!$C$13*(Premissas!$C$71+0.75*(Premissas!$C$72-Premissas!$C$71))) -> 7483.5329 | J39: =MAX(0,H39-I39) -> 47184.41 | K39: =Premissas!$C$35*(1+Premissas!$C$27)^(2)/12 -> 1049.849 | L39: =E39-F39+(I39+J39)*Premissas!$C$20*(1+Premissas!$C$26)^(2) -> 54626.983 | M39: =L39-G39-K39 -> 51632.151 | N39: =N38+M39 -> -673492.3 | O39: =O38+M39 -> 1614007.7 | P39: =IF(AND(N39>=0,N38<0),"✅ PAYBACK","") | Q39: =I39 -> 7483.5329
A40: 3 | B40: Nov | C40: =Premissas!$C$71+0.8333333333*(Premissas!$C$72-Premissas!$C$71) -> 0.9305 | D40: =(1+Premissas!$C$26)^(2) -> 1.1664 | E40: =Dimensionador!$C$22*(Premissas!$C$71+0.8333333333*(Premissas!$C$72-Premissas!$C$71))*Premissas!$C$21*(1+Premissas!$C$26)^(2) -> 20138.729 | F40: =Dimensionador!$C$7*Premissas!$C$13*(Premissas!$C$71+0.8333333333*(Premissas!$C$72-Premissas!$C$71))*Premissas!$C$20*(1+Premissas!$C$26)^(2) -> 5453.6359 | G40: =Dimensionador!$C$7*Premissas!$C$25*(1+Premissas!$C$27)^(2)/12 -> 1944.9833 | H40: =Premissas!$C$62*(1-Premissas!$C$32)^(2) -> 52904.461 | I40: =MIN(H40,Dimensionador!$C$7*Premissas!$C$13*(Premissas!$C$71+0.8333333333*(Premissas!$C$72-Premissas!$C$71))) -> 7469.4849 | J40: =MAX(0,H40-I40) -> 45434.976 | K40: =Premissas!$C$35*(1+Premissas!$C$27)^(2)/12 -> 1049.849 | L40: =E40-F40+(I40+J40)*Premissas!$C$20*(1+Premissas!$C$26)^(2) -> 53311.808 | M40: =L40-G40-K40 -> 50316.976 | N40: =N39+M40 -> -623175.33 | O40: =O39+M40 -> 1664324.7 | P40: =IF(AND(N40>=0,N39<0),"✅ PAYBACK","") | Q40: =I40 -> 7469.4849
A41: 3 | B41: Dez | C41: =Premissas!$C$71+0.9166666667*(Premissas!$C$72-Premissas!$C$71) -> 0.92875 | D41: =(1+Premissas!$C$26)^(2) -> 1.1664 | E41: =Dimensionador!$C$22*(Premissas!$C$71+0.9166666667*(Premissas!$C$72-Premissas!$C$71))*Premissas!$C$21*(1+Premissas!$C$26)^(2) -> 20100.854 | F41: =Dimensionador!$C$7*Premissas!$C$13*(Premissas!$C$71+0.9166666667*(Premissas!$C$72-Premissas!$C$71))*Premissas!$C$20*(1+Premissas!$C$26)^(2) -> 5443.3791 | G41: =Dimensionador!$C$7*Premissas!$C$25*(1+Premissas!$C$27)^(2)/12 -> 1944.9833 | H41: =Premissas!$C$63*(1-Premissas!$C$32)^(2) -> 54667.943 | I41: =MIN(H41,Dimensionador!$C$7*Premissas!$C$13*(Premissas!$C$71+0.9166666667*(Premissas!$C$72-Premissas!$C$71))) -> 7455.437 | J41: =MAX(0,H41-I41) -> 47212.506 | K41: =Premissas!$C$35*(1+Premissas!$C$27)^(2)/12 -> 1049.849 | L41: =E41-F41+(I41+J41)*Premissas!$C$20*(1+Premissas!$C$26)^(2) -> 54571.747 | M41: =L41-G41-K41 -> 51576.914 | N41: =N40+M41 -> -571598.41 | O41: =O40+M41 -> 1715901.6 | P41: =IF(AND(N41>=0,N40<0),"✅ PAYBACK","") | Q41: =I41 -> 7455.437
A42: 4 | B42: Jan | C42: =Premissas!$C$72+0*(Premissas!$C$73-Premissas!$C$72) -> 0.927 | D42: =(1+Premissas!$C$26)^(3) -> 1.259712 | E42: =Dimensionador!$C$22*(Premissas!$C$72+0*(Premissas!$C$73-Premissas!$C$72))*Premissas!$C$21*(1+Premissas!$C$26)^(3) -> 21668.017 | F42: =Dimensionador!$C$7*Premissas!$C$13*(Premissas!$C$72+0*(Premissas!$C$73-Premissas!$C$72))*Premissas!$C$20*(1+Premissas!$C$26)^(3) -> 5867.7722 | G42: =Dimensionador!$C$7*Premissas!$C$25*(1+Premissas!$C$27)^(3)/12 -> 2003.3328 | H42: =Premissas!$C$52*(1-Premissas!$C$32)^(3) -> 54394.603 | I42: =MIN(H42,Dimensionador!$C$7*Premissas!$C$13*(Premissas!$C$72+0*(Premissas!$C$73-Premissas!$C$72))) -> 7441.3891 | J42: =MAX(0,H42-I42) -> 46953.214 | K42: =Premissas!$C$35*(1+Premissas!$C$27)^(3)/12 -> 1081.3444 | L42: =E42-F42+(I42+J42)*Premissas!$C$20*(1+Premissas!$C$26)^(3) -> 58692.121 | M42: =L42-G42-K42 -> 55607.444 | N42: =N41+M42 -> -515990.97 | O42: =O41+M42 -> 1771509 | P42: =IF(AND(N42>=0,N41<0),"✅ PAYBACK","") | Q42: =I42 -> 7441.3891
A43: 4 | B43: Fev | C43: =Premissas!$C$72+0.0833333333*(Premissas!$C$73-Premissas!$C$72) -> 0.92533333 | D43: =(1+Premissas!$C$26)^(3) -> 1.259712 | E43: =Dimensionador!$C$22*(Premissas!$C$72+0.0833333333*(Premissas!$C$73-Premissas!$C$72))*Premissas!$C$21*(1+Premissas!$C$26)^(3) -> 21629.06 | F43: =Dimensionador!$C$7*Premissas!$C$13*(Premissas!$C$72+0.0833333333*(Premissas!$C$73-Premissas!$C$72))*Premissas!$C$20*(1+Premissas!$C$26)^(3) -> 5857.2225 | G43: =Dimensionador!$C$7*Premissas!$C$25*(1+Premissas!$C$27)^(3)/12 -> 2003.3328 | H43: =Premissas!$C$53*(1-Premissas!$C$32)^(3) -> 49130.609 | I43: =MIN(H43,Dimensionador!$C$7*Premissas!$C$13*(Premissas!$C$72+0.0833333333*(Premissas!$C$73-Premissas!$C$72))) -> 7428.0101 | J43: =MAX(0,H43-I43) -> 41702.599 | K43: =Premissas!$C$35*(1+Premissas!$C$27)^(3)/12 -> 1081.3444 | L43: =E43-F43+(I43+J43)*Premissas!$C$20*(1+Premissas!$C$26)^(3) -> 54512.887 | M43: =L43-G43-K43 -> 51428.21 | N43: =N42+M43 -> -464562.76 | O43: =O42+M43 -> 1822937.2 | P43: =IF(AND(N43>=0,N42<0),"✅ PAYBACK","") | Q43: =I43 -> 7428.0101
A44: 4 | B44: Mar | C44: =Premissas!$C$72+0.1666666667*(Premissas!$C$73-Premissas!$C$72) -> 0.92366667 | D44: =(1+Premissas!$C$26)^(3) -> 1.259712 | E44: =Dimensionador!$C$22*(Premissas!$C$72+0.1666666667*(Premissas!$C$73-Premissas!$C$72))*Premissas!$C$21*(1+Premissas!$C$26)^(3) -> 21590.102 | F44: =Dimensionador!$C$7*Premissas!$C$13*(Premissas!$C$72+0.1666666667*(Premissas!$C$73-Premissas!$C$72))*Premissas!$C$20*(1+Premissas!$C$26)^(3) -> 5846.6727 | G44: =Dimensionador!$C$7*Premissas!$C$25*(1+Premissas!$C$27)^(3)/12 -> 2003.3328 | H44: =Premissas!$C$54*(1-Premissas!$C$32)^(3) -> 54394.603 | I44: =MIN(H44,Dimensionador!$C$7*Premissas!$C$13*(Premissas!$C$72+0.1666666667*(Premissas!$C$73-Premissas!$C$72))) -> 7414.6311 | J44: =MAX(0,H44-I44) -> 46979.972 | K44: =Premissas!$C$35*(1+Premissas!$C$27)^(3)/12 -> 1081.3444 | L44: =E44-F44+(I44+J44)*Premissas!$C$20*(1+Premissas!$C$26)^(3) -> 58635.306 | M44: =L44-G44-K44 -> 55550.629 | N44: =N43+M44 -> -409012.13 | O44: =O43+M44 -> 1878487.9 | P44: =IF(AND(N44>=0,N43<0),"✅ PAYBACK","") | Q44: =I44 -> 7414.6311
A45: 4 | B45: Abr | C45: =Premissas!$C$72+0.25*(Premissas!$C$73-Premissas!$C$72) -> 0.922 | D45: =(1+Premissas!$C$26)^(3) -> 1.259712 | E45: =Dimensionador!$C$22*(Premissas!$C$72+0.25*(Premissas!$C$73-Premissas!$C$72))*Premissas!$C$21*(1+Premissas!$C$26)^(3) -> 21551.145 | F45: =Dimensionador!$C$7*Premissas!$C$13*(Premissas!$C$72+0.25*(Premissas!$C$73-Premissas!$C$72))*Premissas!$C$20*(1+Premissas!$C$26)^(3) -> 5836.123 | G45: =Dimensionador!$C$7*Premissas!$C$25*(1+Premissas!$C$27)^(3)/12 -> 2003.3328 | H45: =Premissas!$C$55*(1-Premissas!$C$32)^(3) -> 52639.939 | I45: =MIN(H45,Dimensionador!$C$7*Premissas!$C$13*(Premissas!$C$72+0.25*(Premissas!$C$73-Premissas!$C$72))) -> 7401.2521 | J45: =MAX(0,H45-I45) -> 45238.686 | K45: =Premissas!$C$35*(1+Premissas!$C$27)^(3)/12 -> 1081.3444 | L45: =E45-F45+(I45+J45)*Premissas!$C$20*(1+Premissas!$C$26)^(3) -> 57223.29 | M45: =L45-G45-K45 -> 54138.613 | N45: =N44+M45 -> -354873.52 | O45: =O44+M45 -> 1932626.5 | P45: =IF(AND(N45>=0,N44<0),"✅ PAYBACK","") | Q45: =I45 -> 7401.2521
A46: 4 | B46: Mai | C46: =Premissas!$C$72+0.3333333333*(Premissas!$C$73-Premissas!$C$72) -> 0.92033333 | D46: =(1+Premissas!$C$26)^(3) -> 1.259712 | E46: =Dimensionador!$C$22*(Premissas!$C$72+0.3333333333*(Premissas!$C$73-Premissas!$C$72))*Premissas!$C$21*(1+Premissas!$C$26)^(3) -> 21512.188 | F46: =Dimensionador!$C$7*Premissas!$C$13*(Premissas!$C$72+0.3333333333*(Premissas!$C$73-Premissas!$C$72))*Premissas!$C$20*(1+Premissas!$C$26)^(3) -> 5825.5732 | G46: =Dimensionador!$C$7*Premissas!$C$25*(1+Premissas!$C$27)^(3)/12 -> 2003.3328 | H46: =Premissas!$C$56*(1-Premissas!$C$32)^(3) -> 54394.603 | I46: =MIN(H46,Dimensionador!$C$7*Premissas!$C$13*(Premissas!$C$72+0.3333333333*(Premissas!$C$73-Premissas!$C$72))) -> 7387.8732 | J46: =MAX(0,H46-I46) -> 47006.73 | K46: =Premissas!$C$35*(1+Premissas!$C$27)^(3)/12 -> 1081.3444 | L46: =E46-F46+(I46+J46)*Premissas!$C$20*(1+Premissas!$C$26)^(3) -> 58578.492 | M46: =L46-G46-K46 -> 55493.814 | N46: =N45+M46 -> -299379.7 | O46: =O45+M46 -> 1988120.3 | P46: =IF(AND(N46>=0,N45<0),"✅ PAYBACK","") | Q46: =I46 -> 7387.8732
A47: 4 | B47: Jun | C47: =Premissas!$C$72+0.4166666667*(Premissas!$C$73-Premissas!$C$72) -> 0.91866667 | D47: =(1+Premissas!$C$26)^(3) -> 1.259712 | E47: =Dimensionador!$C$22*(Premissas!$C$72+0.4166666667*(Premissas!$C$73-Premissas!$C$72))*Premissas!$C$21*(1+Premissas!$C$26)^(3) -> 21473.231 | F47: =Dimensionador!$C$7*Premissas!$C$13*(Premissas!$C$72+0.4166666667*(Premissas!$C$73-Premissas!$C$72))*Premissas!$C$20*(1+Premissas!$C$26)^(3) -> 5815.0235 | G47: =Dimensionador!$C$7*Premissas!$C$25*(1+Premissas!$C$27)^(3)/12 -> 2003.3328 | H47: =Premissas!$C$57*(1-Premissas!$C$32)^(3) -> 52639.939 | I47: =MIN(H47,Dimensionador!$C$7*Premissas!$C$13*(Premissas!$C$72+0.4166666667*(Premissas!$C$73-Premissas!$C$72))) -> 7374.4942 | J47: =MAX(0,H47-I47) -> 45265.444 | K47: =Premissas!$C$35*(1+Premissas!$C$27)^(3)/12 -> 1081.3444 | L47: =E47-F47+(I47+J47)*Premissas!$C$20*(1+Premissas!$C$26)^(3) -> 57166.475 | M47: =L47-G47-K47 -> 54081.798 | N47: =N46+M47 -> -245297.91 | O47: =O46+M47 -> 2042202.1 | P47: =IF(AND(N47>=0,N46<0),"✅ PAYBACK","") | Q47: =I47 -> 7374.4942
A48: 4 | B48: Jul | C48: =Premissas!$C$72+0.5*(Premissas!$C$73-Premissas!$C$72) -> 0.917 | D48: =(1+Premissas!$C$26)^(3) -> 1.259712 | E48: =Dimensionador!$C$22*(Premissas!$C$72+0.5*(Premissas!$C$73-Premissas!$C$72))*Premissas!$C$21*(1+Premissas!$C$26)^(3) -> 21434.274 | F48: =Dimensionador!$C$7*Premissas!$C$13*(Premissas!$C$72+0.5*(Premissas!$C$73-Premissas!$C$72))*Premissas!$C$20*(1+Premissas!$C$26)^(3) -> 5804.4737 | G48: =Dimensionador!$C$7*Premissas!$C$25*(1+Premissas!$C$27)^(3)/12 -> 2003.3328 | H48: =Premissas!$C$58*(1-Premissas!$C$32)^(3) -> 54394.603 | I48: =MIN(H48,Dimensionador!$C$7*Premissas!$C$13*(Premissas!$C$72+0.5*(Premissas!$C$73-Premissas!$C$72))) -> 7361.1152 | J48: =MAX(0,H48-I48) -> 47033.488 | K48: =Premissas!$C$35*(1+Premissas!$C$27)^(3)/12 -> 1081.3444 | L48: =E48-F48+(I48+J48)*Premissas!$C$20*(1+Premissas!$C$26)^(3) -> 58521.677 | M48: =L48-G48-K48 -> 55436.999 | N48: =N47+M48 -> -189860.91 | O48: =O47+M48 -> 2097639.1 | P48: =IF(AND(N48>=0,N47<0),"✅ PAYBACK","") | Q48: =I48 -> 7361.1152
A49: 4 | B49: Ago | C49: =Premissas!$C$72+0.5833333333*(Premissas!$C$73-Premissas!$C$72) -> 0.91533333 | D49: =(1+Premissas!$C$26)^(3) -> 1.259712 | E49: =Dimensionador!$C$22*(Premissas!$C$72+0.5833333333*(Premissas!$C$73-Premissas!$C$72))*Premissas!$C$21*(1+Premissas!$C$26)^(3) -> 21395.316 | F49: =Dimensionador!$C$7*Premissas!$C$13*(Premissas!$C$72+0.5833333333*(Premissas!$C$73-Premissas!$C$72))*Premissas!$C$20*(1+Premissas!$C$26)^(3) -> 5793.924 | G49: =Dimensionador!$C$7*Premissas!$C$25*(1+Premissas!$C$27)^(3)/12 -> 2003.3328 | H49: =Premissas!$C$59*(1-Premissas!$C$32)^(3) -> 54394.603 | I49: =MIN(H49,Dimensionador!$C$7*Premissas!$C$13*(Premissas!$C$72+0.5833333333*(Premissas!$C$73-Premissas!$C$72))) -> 7347.7362 | J49: =MAX(0,H49-I49) -> 47046.867 | K49: =Premissas!$C$35*(1+Premissas!$C$27)^(3)/12 -> 1081.3444 | L49: =E49-F49+(I49+J49)*Premissas!$C$20*(1+Premissas!$C$26)^(3) -> 58493.269 | M49: =L49-G49-K49 -> 55408.592 | N49: =N48+M49 -> -134452.31 | O49: =O48+M49 -> 2153047.7 | P49: =IF(AND(N49>=0,N48<0),"✅ PAYBACK","") | Q49: =I49 -> 7347.7362
A50: 4 | B50: Set | C50: =Premissas!$C$72+0.6666666667*(Premissas!$C$73-Premissas!$C$72) -> 0.91366667 | D50: =(1+Premissas!$C$26)^(3) -> 1.259712 | E50: =Dimensionador!$C$22*(Premissas!$C$72+0.6666666667*(Premissas!$C$73-Premissas!$C$72))*Premissas!$C$21*(1+Premissas!$C$26)^(3) -> 21356.359 | F50: =Dimensionador!$C$7*Premissas!$C$13*(Premissas!$C$72+0.6666666667*(Premissas!$C$73-Premissas!$C$72))*Premissas!$C$20*(1+Premissas!$C$26)^(3) -> 5783.3742 | G50: =Dimensionador!$C$7*Premissas!$C$25*(1+Premissas!$C$27)^(3)/12 -> 2003.3328 | H50: =Premissas!$C$60*(1-Premissas!$C$32)^(3) -> 52639.939 | I50: =MIN(H50,Dimensionador!$C$7*Premissas!$C$13*(Premissas!$C$72+0.6666666667*(Premissas!$C$73-Premissas!$C$72))) -> 7334.3572 | J50: =MAX(0,H50-I50) -> 45305.581 | K50: =Premissas!$C$35*(1+Premissas!$C$27)^(3)/12 -> 1081.3444 | L50: =E50-F50+(I50+J50)*Premissas!$C$20*(1+Premissas!$C$26)^(3) -> 57081.253 | M50: =L50-G50-K50 -> 53996.575 | N50: =N49+M50 -> -80455.739 | O50: =O49+M50 -> 2207044.3 | P50: =IF(AND(N50>=0,N49<0),"✅ PAYBACK","") | Q50: =I50 -> 7334.3572
A51: 4 | B51: Out | C51: =Premissas!$C$72+0.75*(Premissas!$C$73-Premissas!$C$72) -> 0.912 | D51: =(1+Premissas!$C$26)^(3) -> 1.259712 | E51: =Dimensionador!$C$22*(Premissas!$C$72+0.75*(Premissas!$C$73-Premissas!$C$72))*Premissas!$C$21*(1+Premissas!$C$26)^(3) -> 21317.402 | F51: =Dimensionador!$C$7*Premissas!$C$13*(Premissas!$C$72+0.75*(Premissas!$C$73-Premissas!$C$72))*Premissas!$C$20*(1+Premissas!$C$26)^(3) -> 5772.8245 | G51: =Dimensionador!$C$7*Premissas!$C$25*(1+Premissas!$C$27)^(3)/12 -> 2003.3328 | H51: =Premissas!$C$61*(1-Premissas!$C$32)^(3) -> 54394.603 | I51: =MIN(H51,Dimensionador!$C$7*Premissas!$C$13*(Premissas!$C$72+0.75*(Premissas!$C$73-Premissas!$C$72))) -> 7320.9782 | J51: =MAX(0,H51-I51) -> 47073.625 | K51: =Premissas!$C$35*(1+Premissas!$C$27)^(3)/12 -> 1081.3444 | L51: =E51-F51+(I51+J51)*Premissas!$C$20*(1+Premissas!$C$26)^(3) -> 58436.454 | M51: =L51-G51-K51 -> 55351.777 | N51: =N50+M51 -> -25103.962 | O51: =O50+M51 -> 2262396 | P51: =IF(AND(N51>=0,N50<0),"✅ PAYBACK","") | Q51: =I51 -> 7320.9782
A52: 4 | B52: Nov | C52: =Premissas!$C$72+0.8333333333*(Premissas!$C$73-Premissas!$C$72) -> 0.91033333 | D52: =(1+Premissas!$C$26)^(3) -> 1.259712 | E52: =Dimensionador!$C$22*(Premissas!$C$72+0.8333333333*(Premissas!$C$73-Premissas!$C$72))*Premissas!$C$21*(1+Premissas!$C$26)^(3) -> 21278.445 | F52: =Dimensionador!$C$7*Premissas!$C$13*(Premissas!$C$72+0.8333333333*(Premissas!$C$73-Premissas!$C$72))*Premissas!$C$20*(1+Premissas!$C$26)^(3) -> 5762.2747 | G52: =Dimensionador!$C$7*Premissas!$C$25*(1+Premissas!$C$27)^(3)/12 -> 2003.3328 | H52: =Premissas!$C$62*(1-Premissas!$C$32)^(3) -> 52639.939 | I52: =MIN(H52,Dimensionador!$C$7*Premissas!$C$13*(Premissas!$C$72+0.8333333333*(Premissas!$C$73-Premissas!$C$72))) -> 7307.5993 | J52: =MAX(0,H52-I52) -> 45332.339 | K52: =Premissas!$C$35*(1+Premissas!$C$27)^(3)/12 -> 1081.3444 | L52: =E52-F52+(I52+J52)*Premissas!$C$20*(1+Premissas!$C$26)^(3) -> 57024.438 | M52: =L52-G52-K52 -> 53939.76 | N52: =N51+M52 -> 28835.798 | O52: =O51+M52 -> 2316335.8 | P52: =IF(AND(N52>=0,N51<0),"✅ PAYBACK","") -> ✅ PAYBACK | Q52: =I52 -> 7307.5993
A53: 4 | B53: Dez | C53: =Premissas!$C$72+0.9166666667*(Premissas!$C$73-Premissas!$C$72) -> 0.90866667 | D53: =(1+Premissas!$C$26)^(3) -> 1.259712 | E53: =Dimensionador!$C$22*(Premissas!$C$72+0.9166666667*(Premissas!$C$73-Premissas!$C$72))*Premissas!$C$21*(1+Premissas!$C$26)^(3) -> 21239.487 | F53: =Dimensionador!$C$7*Premissas!$C$13*(Premissas!$C$72+0.9166666667*(Premissas!$C$73-Premissas!$C$72))*Premissas!$C$20*(1+Premissas!$C$26)^(3) -> 5751.725 | G53: =Dimensionador!$C$7*Premissas!$C$25*(1+Premissas!$C$27)^(3)/12 -> 2003.3328 | H53: =Premissas!$C$63*(1-Premissas!$C$32)^(3) -> 54394.603 | I53: =MIN(H53,Dimensionador!$C$7*Premissas!$C$13*(Premissas!$C$72+0.9166666667*(Premissas!$C$73-Premissas!$C$72))) -> 7294.2203 | J53: =MAX(0,H53-I53) -> 47100.383 | K53: =Premissas!$C$35*(1+Premissas!$C$27)^(3)/12 -> 1081.3444 | L53: =E53-F53+(I53+J53)*Premissas!$C$20*(1+Premissas!$C$26)^(3) -> 58379.639 | M53: =L53-G53-K53 -> 55294.962 | N53: =N52+M53 -> 84130.76 | O53: =O52+M53 -> 2371630.8 | P53: =IF(AND(N53>=0,N52<0),"✅ PAYBACK","") | Q53: =I53 -> 7294.2203
A54: 5 | B54: Jan | C54: =Premissas!$C$73+0*(Premissas!$C$74-Premissas!$C$73) -> 0.907 | D54: =(1+Premissas!$C$26)^(4) -> 1.360489 | E54: =Dimensionador!$C$22*(Premissas!$C$73+0*(Premissas!$C$74-Premissas!$C$73))*Premissas!$C$21*(1+Premissas!$C$26)^(4) -> 22896.572 | F54: =Dimensionador!$C$7*Premissas!$C$13*(Premissas!$C$73+0*(Premissas!$C$74-Premissas!$C$73))*Premissas!$C$20*(1+Premissas!$C$26)^(4) -> 6200.4692 | G54: =Dimensionador!$C$7*Premissas!$C$25*(1+Premissas!$C$27)^(4)/12 -> 2063.4328 | H54: =Premissas!$C$52*(1-Premissas!$C$32)^(4) -> 54122.63 | I54: =MIN(H54,Dimensionador!$C$7*Premissas!$C$13*(Premissas!$C$73+0*(Premissas!$C$74-Premissas!$C$73))) -> 7280.8413 | J54: =MAX(0,H54-I54) -> 46841.789 | K54: =Premissas!$C$35*(1+Premissas!$C$27)^(4)/12 -> 1113.7848 | L54: =E54-F54+(I54+J54)*Premissas!$C$20*(1+Premissas!$C$26)^(4) -> 62787.714 | M54: =L54-G54-K54 -> 59610.496 | N54: =N53+M54 -> 143741.26 | O54: =O53+M54 -> 2431241.3 | P54: =IF(AND(N54>=0,N53<0),"✅ PAYBACK","") | Q54: =I54 -> 7280.8413
A55: 5 | B55: Fev | C55: =Premissas!$C$73+0.0833333333*(Premissas!$C$74-Premissas!$C$73) -> 0.90541667 | D55: =(1+Premissas!$C$26)^(4) -> 1.360489 | E55: =Dimensionador!$C$22*(Premissas!$C$73+0.0833333333*(Premissas!$C$74-Premissas!$C$73))*Premissas!$C$21*(1+Premissas!$C$26)^(4) -> 22856.602 | F55: =Dimensionador!$C$7*Premissas!$C$13*(Premissas!$C$73+0.0833333333*(Premissas!$C$74-Premissas!$C$73))*Premissas!$C$20*(1+Premissas!$C$26)^(4) -> 6189.6452 | G55: =Dimensionador!$C$7*Premissas!$C$25*(1+Premissas!$C$27)^(4)/12 -> 2063.4328 | H55: =Premissas!$C$53*(1-Premissas!$C$32)^(4) -> 48884.956 | I55: =MIN(H55,Dimensionador!$C$7*Premissas!$C$13*(Premissas!$C$73+0.0833333333*(Premissas!$C$74-Premissas!$C$73))) -> 7268.1313 | J55: =MAX(0,H55-I55) -> 41616.825 | K55: =Premissas!$C$35*(1+Premissas!$C$27)^(4)/12 -> 1113.7848 | L55: =E55-F55+(I55+J55)*Premissas!$C$20*(1+Premissas!$C$26)^(4) -> 58298.089 | M55: =L55-G55-K55 -> 55120.872 | N55: =N54+M55 -> 198862.13 | O55: =O54+M55 -> 2486362.1 | P55: =IF(AND(N55>=0,N54<0),"✅ PAYBACK","") | Q55: =I55 -> 7268.1313
A56: 5 | B56: Mar | C56: =Premissas!$C$73+0.1666666667*(Premissas!$C$74-Premissas!$C$73) -> 0.90383333 | D56: =(1+Premissas!$C$26)^(4) -> 1.360489 | E56: =Dimensionador!$C$22*(Premissas!$C$73+0.1666666667*(Premissas!$C$74-Premissas!$C$73))*Premissas!$C$21*(1+Premissas!$C$26)^(4) -> 22816.632 | F56: =Dimensionador!$C$7*Premissas!$C$13*(Premissas!$C$73+0.1666666667*(Premissas!$C$74-Premissas!$C$73))*Premissas!$C$20*(1+Premissas!$C$26)^(4) -> 6178.8211 | G56: =Dimensionador!$C$7*Premissas!$C$25*(1+Premissas!$C$27)^(4)/12 -> 2063.4328 | H56: =Premissas!$C$54*(1-Premissas!$C$32)^(4) -> 54122.63 | I56: =MIN(H56,Dimensionador!$C$7*Premissas!$C$13*(Premissas!$C$73+0.1666666667*(Premissas!$C$74-Premissas!$C$73))) -> 7255.4212 | J56: =MAX(0,H56-I56) -> 46867.209 | K56: =Premissas!$C$35*(1+Premissas!$C$27)^(4)/12 -> 1113.7848 | L56: =E56-F56+(I56+J56)*Premissas!$C$20*(1+Premissas!$C$26)^(4) -> 62729.422 | M56: =L56-G56-K56 -> 59552.204 | N56: =N55+M56 -> 258414.33 | O56: =O55+M56 -> 2545914.3 | P56: =IF(AND(N56>=0,N55<0),"✅ PAYBACK","") | Q56: =I56 -> 7255.4212
A57: 5 | B57: Abr | C57: =Premissas!$C$73+0.25*(Premissas!$C$74-Premissas!$C$73) -> 0.90225 | D57: =(1+Premissas!$C$26)^(4) -> 1.360489 | E57: =Dimensionador!$C$22*(Premissas!$C$73+0.25*(Premissas!$C$74-Premissas!$C$73))*Premissas!$C$21*(1+Premissas!$C$26)^(4) -> 22776.662 | F57: =Dimensionador!$C$7*Premissas!$C$13*(Premissas!$C$73+0.25*(Premissas!$C$74-Premissas!$C$73))*Premissas!$C$20*(1+Premissas!$C$26)^(4) -> 6167.9971 | G57: =Dimensionador!$C$7*Premissas!$C$25*(1+Premissas!$C$27)^(4)/12 -> 2063.4328 | H57: =Premissas!$C$55*(1-Premissas!$C$32)^(4) -> 52376.739 | I57: =MIN(H57,Dimensionador!$C$7*Premissas!$C$13*(Premissas!$C$73+0.25*(Premissas!$C$74-Premissas!$C$73))) -> 7242.7112 | J57: =MAX(0,H57-I57) -> 45134.028 | K57: =Premissas!$C$35*(1+Premissas!$C$27)^(4)/12 -> 1113.7848 | L57: =E57-F57+(I57+J57)*Premissas!$C$20*(1+Premissas!$C$26)^(4) -> 61213.45 | M57: =L57-G57-K57 -> 58036.232 | N57: =N56+M57 -> 316450.56 | O57: =O56+M57 -> 2603950.6 | P57: =IF(AND(N57>=0,N56<0),"✅ PAYBACK","") | Q57: =I57 -> 7242.7112
A58: 5 | B58: Mai | C58: =Premissas!$C$73+0.3333333333*(Premissas!$C$74-Premissas!$C$73) -> 0.90066667 | D58: =(1+Premissas!$C$26)^(4) -> 1.360489 | E58: =Dimensionador!$C$22*(Premissas!$C$73+0.3333333333*(Premissas!$C$74-Premissas!$C$73))*Premissas!$C$21*(1+Premissas!$C$26)^(4) -> 22736.692 | F58: =Dimensionador!$C$7*Premissas!$C$13*(Premissas!$C$73+0.3333333333*(Premissas!$C$74-Premissas!$C$73))*Premissas!$C$20*(1+Premissas!$C$26)^(4) -> 6157.173 | G58: =Dimensionador!$C$7*Premissas!$C$25*(1+Premissas!$C$27)^(4)/12 -> 2063.4328 | H58: =Premissas!$C$56*(1-Premissas!$C$32)^(4) -> 54122.63 | I58: =MIN(H58,Dimensionador!$C$7*Premissas!$C$13*(Premissas!$C$73+0.3333333333*(Premissas!$C$74-Premissas!$C$73))) -> 7230.0012 | J58: =MAX(0,H58-I58) -> 46892.629 | K58: =Premissas!$C$35*(1+Premissas!$C$27)^(4)/12 -> 1113.7848 | L58: =E58-F58+(I58+J58)*Premissas!$C$20*(1+Premissas!$C$26)^(4) -> 62671.13 | M58: =L58-G58-K58 -> 59493.912 | N58: =N57+M58 -> 375944.48 | O58: =O57+M58 -> 2663444.5 | P58: =IF(AND(N58>=0,N57<0),"✅ PAYBACK","") | Q58: =I58 -> 7230.0012
A59: 5 | B59: Jun | C59: =Premissas!$C$73+0.4166666667*(Premissas!$C$74-Premissas!$C$73) -> 0.89908333 | D59: =(1+Premissas!$C$26)^(4) -> 1.360489 | E59: =Dimensionador!$C$22*(Premissas!$C$73+0.4166666667*(Premissas!$C$74-Premissas!$C$73))*Premissas!$C$21*(1+Premissas!$C$26)^(4) -> 22696.722 | F59: =Dimensionador!$C$7*Premissas!$C$13*(Premissas!$C$73+0.4166666667*(Premissas!$C$74-Premissas!$C$73))*Premissas!$C$20*(1+Premissas!$C$26)^(4) -> 6146.349 | G59: =Dimensionador!$C$7*Premissas!$C$25*(1+Premissas!$C$27)^(4)/12 -> 2063.4328 | H59: =Premissas!$C$57*(1-Premissas!$C$32)^(4) -> 52376.739 | I59: =MIN(H59,Dimensionador!$C$7*Premissas!$C$13*(Premissas!$C$73+0.4166666667*(Premissas!$C$74-Premissas!$C$73))) -> 7217.2911 | J59: =MAX(0,H59-I59) -> 45159.448 | K59: =Premissas!$C$35*(1+Premissas!$C$27)^(4)/12 -> 1113.7848 | L59: =E59-F59+(I59+J59)*Premissas!$C$20*(1+Premissas!$C$26)^(4) -> 61155.157 | M59: =L59-G59-K59 -> 57977.94 | N59: =N58+M59 -> 433922.42 | O59: =O58+M59 -> 2721422.4 | P59: =IF(AND(N59>=0,N58<0),"✅ PAYBACK","") | Q59: =I59 -> 7217.2911
A60: 5 | B60: Jul | C60: =Premissas!$C$73+0.5*(Premissas!$C$74-Premissas!$C$73) -> 0.8975 | D60: =(1+Premissas!$C$26)^(4) -> 1.360489 | E60: =Dimensionador!$C$22*(Premissas!$C$73+0.5*(Premissas!$C$74-Premissas!$C$73))*Premissas!$C$21*(1+Premissas!$C$26)^(4) -> 22656.752 | F60: =Dimensionador!$C$7*Premissas!$C$13*(Premissas!$C$73+0.5*(Premissas!$C$74-Premissas!$C$73))*Premissas!$C$20*(1+Premissas!$C$26)^(4) -> 6135.525 | G60: =Dimensionador!$C$7*Premissas!$C$25*(1+Premissas!$C$27)^(4)/12 -> 2063.4328 | H60: =Premissas!$C$58*(1-Premissas!$C$32)^(4) -> 54122.63 | I60: =MIN(H60,Dimensionador!$C$7*Premissas!$C$13*(Premissas!$C$73+0.5*(Premissas!$C$74-Premissas!$C$73))) -> 7204.5811 | J60: =MAX(0,H60-I60) -> 46918.049 | K60: =Premissas!$C$35*(1+Premissas!$C$27)^(4)/12 -> 1113.7848 | L60: =E60-F60+(I60+J60)*Premissas!$C$20*(1+Premissas!$C$26)^(4) -> 62612.838 | M60: =L60-G60-K60 -> 59435.62 | N60: =N59+M60 -> 493358.04 | O60: =O59+M60 -> 2780858 | P60: =IF(AND(N60>=0,N59<0),"✅ PAYBACK","") | Q60: =I60 -> 7204.5811
A61: 5 | B61: Ago | C61: =Premissas!$C$73+0.5833333333*(Premissas!$C$74-Premissas!$C$73) -> 0.89591667 | D61: =(1+Premissas!$C$26)^(4) -> 1.360489 | E61: =Dimensionador!$C$22*(Premissas!$C$73+0.5833333333*(Premissas!$C$74-Premissas!$C$73))*Premissas!$C$21*(1+Premissas!$C$26)^(4) -> 22616.782 | F61: =Dimensionador!$C$7*Premissas!$C$13*(Premissas!$C$73+0.5833333333*(Premissas!$C$74-Premissas!$C$73))*Premissas!$C$20*(1+Premissas!$C$26)^(4) -> 6124.7009 | G61: =Dimensionador!$C$7*Premissas!$C$25*(1+Premissas!$C$27)^(4)/12 -> 2063.4328 | H61: =Premissas!$C$59*(1-Premissas!$C$32)^(4) -> 54122.63 | I61: =MIN(H61,Dimensionador!$C$7*Premissas!$C$13*(Premissas!$C$73+0.5833333333*(Premissas!$C$74-Premissas!$C$73))) -> 7191.8711 | J61: =MAX(0,H61-I61) -> 46930.759 | K61: =Premissas!$C$35*(1+Premissas!$C$27)^(4)/12 -> 1113.7848 | L61: =E61-F61+(I61+J61)*Premissas!$C$20*(1+Premissas!$C$26)^(4) -> 62583.691 | M61: =L61-G61-K61 -> 59406.474 | N61: =N60+M61 -> 552764.51 | O61: =O60+M61 -> 2840264.5 | P61: =IF(AND(N61>=0,N60<0),"✅ PAYBACK","") | Q61: =I61 -> 7191.8711
A62: 5 | B62: Set | C62: =Premissas!$C$73+0.6666666667*(Premissas!$C$74-Premissas!$C$73) -> 0.89433333 | D62: =(1+Premissas!$C$26)^(4) -> 1.360489 | E62: =Dimensionador!$C$22*(Premissas!$C$73+0.6666666667*(Premissas!$C$74-Premissas!$C$73))*Premissas!$C$21*(1+Premissas!$C$26)^(4) -> 22576.811 | F62: =Dimensionador!$C$7*Premissas!$C$13*(Premissas!$C$73+0.6666666667*(Premissas!$C$74-Premissas!$C$73))*Premissas!$C$20*(1+Premissas!$C$26)^(4) -> 6113.8769 | G62: =Dimensionador!$C$7*Premissas!$C$25*(1+Premissas!$C$27)^(4)/12 -> 2063.4328 | H62: =Premissas!$C$60*(1-Premissas!$C$32)^(4) -> 52376.739 | I62: =MIN(H62,Dimensionador!$C$7*Premissas!$C$13*(Premissas!$C$73+0.6666666667*(Premissas!$C$74-Premissas!$C$73))) -> 7179.1611 | J62: =MAX(0,H62-I62) -> 45197.578 | K62: =Premissas!$C$35*(1+Premissas!$C$27)^(4)/12 -> 1113.7848 | L62: =E62-F62+(I62+J62)*Premissas!$C$20*(1+Premissas!$C$26)^(4) -> 61067.719 | M62: =L62-G62-K62 -> 57890.502 | N62: =N61+M62 -> 610655.01 | O62: =O61+M62 -> 2898155 | P62: =IF(AND(N62>=0,N61<0),"✅ PAYBACK","") | Q62: =I62 -> 7179.1611
A63: 5 | B63: Out | C63: =Premissas!$C$73+0.75*(Premissas!$C$74-Premissas!$C$73) -> 0.89275 | D63: =(1+Premissas!$C$26)^(4) -> 1.360489 | E63: =Dimensionador!$C$22*(Premissas!$C$73+0.75*(Premissas!$C$74-Premissas!$C$73))*Premissas!$C$21*(1+Premissas!$C$26)^(4) -> 22536.841 | F63: =Dimensionador!$C$7*Premissas!$C$13*(Premissas!$C$73+0.75*(Premissas!$C$74-Premissas!$C$73))*Premissas!$C$20*(1+Premissas!$C$26)^(4) -> 6103.0528 | G63: =Dimensionador!$C$7*Premissas!$C$25*(1+Premissas!$C$27)^(4)/12 -> 2063.4328 | H63: =Premissas!$C$61*(1-Premissas!$C$32)^(4) -> 54122.63 | I63: =MIN(H63,Dimensionador!$C$7*Premissas!$C$13*(Premissas!$C$73+0.75*(Premissas!$C$74-Premissas!$C$73))) -> 7166.451 | J63: =MAX(0,H63-I63) -> 46956.179 | K63: =Premissas!$C$35*(1+Premissas!$C$27)^(4)/12 -> 1113.7848 | L63: =E63-F63+(I63+J63)*Premissas!$C$20*(1+Premissas!$C$26)^(4) -> 62525.399 | M63: =L63-G63-K63 -> 59348.182 | N63: =N62+M63 -> 670003.19 | O63: =O62+M63 -> 2957503.2 | P63: =IF(AND(N63>=0,N62<0),"✅ PAYBACK","") | Q63: =I63 -> 7166.451
A64: 5 | B64: Nov | C64: =Premissas!$C$73+0.8333333333*(Premissas!$C$74-Premissas!$C$73) -> 0.89116667 | D64: =(1+Premissas!$C$26)^(4) -> 1.360489 | E64: =Dimensionador!$C$22*(Premissas!$C$73+0.8333333333*(Premissas!$C$74-Premissas!$C$73))*Premissas!$C$21*(1+Premissas!$C$26)^(4) -> 22496.871 | F64: =Dimensionador!$C$7*Premissas!$C$13*(Premissas!$C$73+0.8333333333*(Premissas!$C$74-Premissas!$C$73))*Premissas!$C$20*(1+Premissas!$C$26)^(4) -> 6092.2288 | G64: =Dimensionador!$C$7*Premissas!$C$25*(1+Premissas!$C$27)^(4)/12 -> 2063.4328 | H64: =Premissas!$C$62*(1-Premissas!$C$32)^(4) -> 52376.739 | I64: =MIN(H64,Dimensionador!$C$7*Premissas!$C$13*(Premissas!$C$73+0.8333333333*(Premissas!$C$74-Premissas!$C$73))) -> 7153.741 | J64: =MAX(0,H64-I64) -> 45222.998 | K64: =Premissas!$C$35*(1+Premissas!$C$27)^(4)/12 -> 1113.7848 | L64: =E64-F64+(I64+J64)*Premissas!$C$20*(1+Premissas!$C$26)^(4) -> 61009.427 | M64: =L64-G64-K64 -> 57832.209 | N64: =N63+M64 -> 727835.4 | O64: =O63+M64 -> 3015335.4 | P64: =IF(AND(N64>=0,N63<0),"✅ PAYBACK","") | Q64: =I64 -> 7153.741
A65: 5 | B65: Dez | C65: =Premissas!$C$73+0.9166666667*(Premissas!$C$74-Premissas!$C$73) -> 0.88958333 | D65: =(1+Premissas!$C$26)^(4) -> 1.360489 | E65: =Dimensionador!$C$22*(Premissas!$C$73+0.9166666667*(Premissas!$C$74-Premissas!$C$73))*Premissas!$C$21*(1+Premissas!$C$26)^(4) -> 22456.901 | F65: =Dimensionador!$C$7*Premissas!$C$13*(Premissas!$C$73+0.9166666667*(Premissas!$C$74-Premissas!$C$73))*Premissas!$C$20*(1+Premissas!$C$26)^(4) -> 6081.4047 | G65: =Dimensionador!$C$7*Premissas!$C$25*(1+Premissas!$C$27)^(4)/12 -> 2063.4328 | H65: =Premissas!$C$63*(1-Premissas!$C$32)^(4) -> 54122.63 | I65: =MIN(H65,Dimensionador!$C$7*Premissas!$C$13*(Premissas!$C$73+0.9166666667*(Premissas!$C$74-Premissas!$C$73))) -> 7141.031 | J65: =MAX(0,H65-I65) -> 46981.599 | K65: =Premissas!$C$35*(1+Premissas!$C$27)^(4)/12 -> 1113.7848 | L65: =E65-F65+(I65+J65)*Premissas!$C$20*(1+Premissas!$C$26)^(4) -> 62467.107 | M65: =L65-G65-K65 -> 59289.89 | N65: =N64+M65 -> 787125.29 | O65: =O64+M65 -> 3074625.3 | P65: =IF(AND(N65>=0,N64<0),"✅ PAYBACK","") | Q65: =I65 -> 7141.031
A66: 6 | B66: Jan | C66: =Premissas!$C$74+0*(Premissas!$C$75-Premissas!$C$74) -> 0.888 | D66: =(1+Premissas!$C$26)^(5) -> 1.4693281 | E66: =Dimensionador!$C$22*(Premissas!$C$74+0*(Premissas!$C$75-Premissas!$C$74))*Premissas!$C$21*(1+Premissas!$C$26)^(5) -> 24210.285 | F66: =Dimensionador!$C$7*Premissas!$C$13*(Premissas!$C$74+0*(Premissas!$C$75-Premissas!$C$74))*Premissas!$C$20*(1+Premissas!$C$26)^(5) -> 6556.2271 | G66: =Dimensionador!$C$7*Premissas!$C$25*(1+Premissas!$C$27)^(5)/12 -> 2125.3358 | H66: =Premissas!$C$52*(1-Premissas!$C$32)^(5) -> 53852.017 | I66: =MIN(H66,Dimensionador!$C$7*Premissas!$C$13*(Premissas!$C$74+0*(Premissas!$C$75-Premissas!$C$74))) -> 7128.3209 | J66: =MAX(0,H66-I66) -> 46723.696 | K66: =Premissas!$C$35*(1+Premissas!$C$27)^(5)/12 -> 1147.1983 | L66: =E66-F66+(I66+J66)*Premissas!$C$20*(1+Premissas!$C$26)^(5) -> 67184.103 | M66: =L66-G66-K66 -> 63911.569 | N66: =N65+M66 -> 851036.86 | O66: =O65+M66 -> 3138536.9 | P66: =IF(AND(N66>=0,N65<0),"✅ PAYBACK","") | Q66: =I66 -> 7128.3209
A67: 6 | B67: Fev | C67: =Premissas!$C$74+0.0833333333*(Premissas!$C$75-Premissas!$C$74) -> 0.8865 | D67: =(1+Premissas!$C$26)^(5) -> 1.4693281 | E67: =Dimensionador!$C$22*(Premissas!$C$74+0.0833333333*(Premissas!$C$75-Premissas!$C$74))*Premissas!$C$21*(1+Premissas!$C$26)^(5) -> 24169.39 | F67: =Dimensionador!$C$7*Premissas!$C$13*(Premissas!$C$74+0.0833333333*(Premissas!$C$75-Premissas!$C$74))*Premissas!$C$20*(1+Premissas!$C$26)^(5) -> 6545.1524 | G67: =Dimensionador!$C$7*Premissas!$C$25*(1+Premissas!$C$27)^(5)/12 -> 2125.3358 | H67: =Premissas!$C$53*(1-Premissas!$C$32)^(5) -> 48640.532 | I67: =MIN(H67,Dimensionador!$C$7*Premissas!$C$13*(Premissas!$C$74+0.0833333333*(Premissas!$C$75-Premissas!$C$74))) -> 7116.2798 | J67: =MAX(0,H67-I67) -> 41524.252 | K67: =Premissas!$C$35*(1+Premissas!$C$27)^(5)/12 -> 1147.1983 | L67: =E67-F67+(I67+J67)*Premissas!$C$20*(1+Premissas!$C$26)^(5) -> 62361.052 | M67: =L67-G67-K67 -> 59088.518 | N67: =N66+M67 -> 910125.38 | O67: =O66+M67 -> 3197625.4 | P67: =IF(AND(N67>=0,N66<0),"✅ PAYBACK","") | Q67: =I67 -> 7116.2798
A68: 6 | B68: Mar | C68: =Premissas!$C$74+0.1666666667*(Premissas!$C$75-Premissas!$C$74) -> 0.885 | D68: =(1+Premissas!$C$26)^(5) -> 1.4693281 | E68: =Dimensionador!$C$22*(Premissas!$C$74+0.1666666667*(Premissas!$C$75-Premissas!$C$74))*Premissas!$C$21*(1+Premissas!$C$26)^(5) -> 24128.494 | F68: =Dimensionador!$C$7*Premissas!$C$13*(Premissas!$C$74+0.1666666667*(Premissas!$C$75-Premissas!$C$74))*Premissas!$C$20*(1+Premissas!$C$26)^(5) -> 6534.0777 | G68: =Dimensionador!$C$7*Premissas!$C$25*(1+Premissas!$C$27)^(5)/12 -> 2125.3358 | H68: =Premissas!$C$54*(1-Premissas!$C$32)^(5) -> 53852.017 | I68: =MIN(H68,Dimensionador!$C$7*Premissas!$C$13*(Premissas!$C$74+0.1666666667*(Premissas!$C$75-Premissas!$C$74))) -> 7104.2388 | J68: =MAX(0,H68-I68) -> 46747.778 | K68: =Premissas!$C$35*(1+Premissas!$C$27)^(5)/12 -> 1147.1983 | L68: =E68-F68+(I68+J68)*Premissas!$C$20*(1+Premissas!$C$26)^(5) -> 67124.461 | M68: =L68-G68-K68 -> 63851.927 | N68: =N67+M68 -> 973977.31 | O68: =O67+M68 -> 3261477.3 | P68: =IF(AND(N68>=0,N67<0),"✅ PAYBACK","") | Q68: =I68 -> 7104.2388
A69: 6 | B69: Abr | C69: =Premissas!$C$74+0.25*(Premissas!$C$75-Premissas!$C$74) -> 0.8835 | D69: =(1+Premissas!$C$26)^(5) -> 1.4693281 | E69: =Dimensionador!$C$22*(Premissas!$C$74+0.25*(Premissas!$C$75-Premissas!$C$74))*Premissas!$C$21*(1+Premissas!$C$26)^(5) -> 24087.598 | F69: =Dimensionador!$C$7*Premissas!$C$13*(Premissas!$C$74+0.25*(Premissas!$C$75-Premissas!$C$74))*Premissas!$C$20*(1+Premissas!$C$26)^(5) -> 6523.003 | G69: =Dimensionador!$C$7*Premissas!$C$25*(1+Premissas!$C$27)^(5)/12 -> 2125.3358 | H69: =Premissas!$C$55*(1-Premissas!$C$32)^(5) -> 52114.855 | I69: =MIN(H69,Dimensionador!$C$7*Premissas!$C$13*(Premissas!$C$74+0.25*(Premissas!$C$75-Premissas!$C$74))) -> 7092.1977 | J69: =MAX(0,H69-I69) -> 45022.658 | K69: =Premissas!$C$35*(1+Premissas!$C$27)^(5)/12 -> 1147.1983 | L69: =E69-F69+(I69+J69)*Premissas!$C$20*(1+Premissas!$C$26)^(5) -> 65496.897 | M69: =L69-G69-K69 -> 62224.363 | N69: =N68+M69 -> 1036201.7 | O69: =O68+M69 -> 3323701.7 | P69: =IF(AND(N69>=0,N68<0),"✅ PAYBACK","") | Q69: =I69 -> 7092.1977
A70: 6 | B70: Mai | C70: =Premissas!$C$74+0.3333333333*(Premissas!$C$75-Premissas!$C$74) -> 0.882 | D70: =(1+Premissas!$C$26)^(5) -> 1.4693281 | E70: =Dimensionador!$C$22*(Premissas!$C$74+0.3333333333*(Premissas!$C$75-Premissas!$C$74))*Premissas!$C$21*(1+Premissas!$C$26)^(5) -> 24046.702 | F70: =Dimensionador!$C$7*Premissas!$C$13*(Premissas!$C$74+0.3333333333*(Premissas!$C$75-Premissas!$C$74))*Premissas!$C$20*(1+Premissas!$C$26)^(5) -> 6511.9283 | G70: =Dimensionador!$C$7*Premissas!$C$25*(1+Premissas!$C$27)^(5)/12 -> 2125.3358 | H70: =Premissas!$C$56*(1-Premissas!$C$32)^(5) -> 53852.017 | I70: =MIN(H70,Dimensionador!$C$7*Premissas!$C$13*(Premissas!$C$74+0.3333333333*(Premissas!$C$75-Premissas!$C$74))) -> 7080.1566 | J70: =MAX(0,H70-I70) -> 46771.86 | K70: =Premissas!$C$35*(1+Premissas!$C$27)^(5)/12 -> 1147.1983 | L70: =E70-F70+(I70+J70)*Premissas!$C$20*(1+Premissas!$C$26)^(5) -> 67064.819 | M70: =L70-G70-K70 -> 63792.285 | N70: =N69+M70 -> 1099994 | O70: =O69+M70 -> 3387494 | P70: =IF(AND(N70>=0,N69<0),"✅ PAYBACK","") | Q70: =I70 -> 7080.1566
A71: 6 | B71: Jun | C71: =Premissas!$C$74+0.4166666667*(Premissas!$C$75-Premissas!$C$74) -> 0.8805 | D71: =(1+Premissas!$C$26)^(5) -> 1.4693281 | E71: =Dimensionador!$C$22*(Premissas!$C$74+0.4166666667*(Premissas!$C$75-Premissas!$C$74))*Premissas!$C$21*(1+Premissas!$C$26)^(5) -> 24005.807 | F71: =Dimensionador!$C$7*Premissas!$C$13*(Premissas!$C$74+0.4166666667*(Premissas!$C$75-Premissas!$C$74))*Premissas!$C$20*(1+Premissas!$C$26)^(5) -> 6500.8536 | G71: =Dimensionador!$C$7*Premissas!$C$25*(1+Premissas!$C$27)^(5)/12 -> 2125.3358 | H71: =Premissas!$C$57*(1-Premissas!$C$32)^(5) -> 52114.855 | I71: =MIN(H71,Dimensionador!$C$7*Premissas!$C$13*(Premissas!$C$74+0.4166666667*(Premissas!$C$75-Premissas!$C$74))) -> 7068.1155 | J71: =MAX(0,H71-I71) -> 45046.74 | K71: =Premissas!$C$35*(1+Premissas!$C$27)^(5)/12 -> 1147.1983 | L71: =E71-F71+(I71+J71)*Premissas!$C$20*(1+Premissas!$C$26)^(5) -> 65437.255 | M71: =L71-G71-K71 -> 62164.72 | N71: =N70+M71 -> 1162158.7 | O71: =O70+M71 -> 3449658.7 | P71: =IF(AND(N71>=0,N70<0),"✅ PAYBACK","") | Q71: =I71 -> 7068.1155
A72: 6 | B72: Jul | C72: =Premissas!$C$74+0.5*(Premissas!$C$75-Premissas!$C$74) -> 0.879 | D72: =(1+Premissas!$C$26)^(5) -> 1.4693281 | E72: =Dimensionador!$C$22*(Premissas!$C$74+0.5*(Premissas!$C$75-Premissas!$C$74))*Premissas!$C$21*(1+Premissas!$C$26)^(5) -> 23964.911 | F72: =Dimensionador!$C$7*Premissas!$C$13*(Premissas!$C$74+0.5*(Premissas!$C$75-Premissas!$C$74))*Premissas!$C$20*(1+Premissas!$C$26)^(5) -> 6489.7789 | G72: =Dimensionador!$C$7*Premissas!$C$25*(1+Premissas!$C$27)^(5)/12 -> 2125.3358 | H72: =Premissas!$C$58*(1-Premissas!$C$32)^(5) -> 53852.017 | I72: =MIN(H72,Dimensionador!$C$7*Premissas!$C$13*(Premissas!$C$74+0.5*(Premissas!$C$75-Premissas!$C$74))) -> 7056.0744 | J72: =MAX(0,H72-I72) -> 46795.943 | K72: =Premissas!$C$35*(1+Premissas!$C$27)^(5)/12 -> 1147.1983 | L72: =E72-F72+(I72+J72)*Premissas!$C$20*(1+Premissas!$C$26)^(5) -> 67005.177 | M72: =L72-G72-K72 -> 63732.643 | N72: =N71+M72 -> 1225891.3 | O72: =O71+M72 -> 3513391.3 | P72: =IF(AND(N72>=0,N71<0),"✅ PAYBACK","") | Q72: =I72 -> 7056.0744
A73: 6 | B73: Ago | C73: =Premissas!$C$74+0.5833333333*(Premissas!$C$75-Premissas!$C$74) -> 0.8775 | D73: =(1+Premissas!$C$26)^(5) -> 1.4693281 | E73: =Dimensionador!$C$22*(Premissas!$C$74+0.5833333333*(Premissas!$C$75-Premissas!$C$74))*Premissas!$C$21*(1+Premissas!$C$26)^(5) -> 23924.015 | F73: =Dimensionador!$C$7*Premissas!$C$13*(Premissas!$C$74+0.5833333333*(Premissas!$C$75-Premissas!$C$74))*Premissas!$C$20*(1+Premissas!$C$26)^(5) -> 6478.7042 | G73: =Dimensionador!$C$7*Premissas!$C$25*(1+Premissas!$C$27)^(5)/12 -> 2125.3358 | H73: =Premissas!$C$59*(1-Premissas!$C$32)^(5) -> 53852.017 | I73: =MIN(H73,Dimensionador!$C$7*Premissas!$C$13*(Premissas!$C$74+0.5833333333*(Premissas!$C$75-Premissas!$C$74))) -> 7044.0333 | J73: =MAX(0,H73-I73) -> 46807.984 | K73: =Premissas!$C$35*(1+Premissas!$C$27)^(5)/12 -> 1147.1983 | L73: =E73-F73+(I73+J73)*Premissas!$C$20*(1+Premissas!$C$26)^(5) -> 66975.356 | M73: =L73-G73-K73 -> 63702.822 | N73: =N72+M73 -> 1289594.1 | O73: =O72+M73 -> 3577094.1 | P73: =IF(AND(N73>=0,N72<0),"✅ PAYBACK","") | Q73: =I73 -> 7044.0333
A74: 6 | B74: Set | C74: =Premissas!$C$74+0.6666666667*(Premissas!$C$75-Premissas!$C$74) -> 0.876 | D74: =(1+Premissas!$C$26)^(5) -> 1.4693281 | E74: =Dimensionador!$C$22*(Premissas!$C$74+0.6666666667*(Premissas!$C$75-Premissas!$C$74))*Premissas!$C$21*(1+Premissas!$C$26)^(5) -> 23883.119 | F74: =Dimensionador!$C$7*Premissas!$C$13*(Premissas!$C$74+0.6666666667*(Premissas!$C$75-Premissas!$C$74))*Premissas!$C$20*(1+Premissas!$C$26)^(5) -> 6467.6295 | G74: =Dimensionador!$C$7*Premissas!$C$25*(1+Premissas!$C$27)^(5)/12 -> 2125.3358 | H74: =Premissas!$C$60*(1-Premissas!$C$32)^(5) -> 52114.855 | I74: =MIN(H74,Dimensionador!$C$7*Premissas!$C$13*(Premissas!$C$74+0.6666666667*(Premissas!$C$75-Premissas!$C$74))) -> 7031.9923 | J74: =MAX(0,H74-I74) -> 45082.863 | K74: =Premissas!$C$35*(1+Premissas!$C$27)^(5)/12 -> 1147.1983 | L74: =E74-F74+(I74+J74)*Premissas!$C$20*(1+Premissas!$C$26)^(5) -> 65347.791 | M74: =L74-G74-K74 -> 62075.257 | N74: =N73+M74 -> 1351669.4 | O74: =O73+M74 -> 3639169.4 | P74: =IF(AND(N74>=0,N73<0),"✅ PAYBACK","") | Q74: =I74 -> 7031.9923
A75: 6 | B75: Out | C75: =Premissas!$C$74+0.75*(Premissas!$C$75-Premissas!$C$74) -> 0.8745 | D75: =(1+Premissas!$C$26)^(5) -> 1.4693281 | E75: =Dimensionador!$C$22*(Premissas!$C$74+0.75*(Premissas!$C$75-Premissas!$C$74))*Premissas!$C$21*(1+Premissas!$C$26)^(5) -> 23842.224 | F75: =Dimensionador!$C$7*Premissas!$C$13*(Premissas!$C$74+0.75*(Premissas!$C$75-Premissas!$C$74))*Premissas!$C$20*(1+Premissas!$C$26)^(5) -> 6456.5548 | G75: =Dimensionador!$C$7*Premissas!$C$25*(1+Premissas!$C$27)^(5)/12 -> 2125.3358 | H75: =Premissas!$C$61*(1-Premissas!$C$32)^(5) -> 53852.017 | I75: =MIN(H75,Dimensionador!$C$7*Premissas!$C$13*(Premissas!$C$74+0.75*(Premissas!$C$75-Premissas!$C$74))) -> 7019.9512 | J75: =MAX(0,H75-I75) -> 46832.066 | K75: =Premissas!$C$35*(1+Premissas!$C$27)^(5)/12 -> 1147.1983 | L75: =E75-F75+(I75+J75)*Premissas!$C$20*(1+Premissas!$C$26)^(5) -> 66915.714 | M75: =L75-G75-K75 -> 63643.18 | N75: =N74+M75 -> 1415312.6 | O75: =O74+M75 -> 3702812.6 | P75: =IF(AND(N75>=0,N74<0),"✅ PAYBACK","") | Q75: =I75 -> 7019.9512
A76: 6 | B76: Nov | C76: =Premissas!$C$74+0.8333333333*(Premissas!$C$75-Premissas!$C$74) -> 0.873 | D76: =(1+Premissas!$C$26)^(5) -> 1.4693281 | E76: =Dimensionador!$C$22*(Premissas!$C$74+0.8333333333*(Premissas!$C$75-Premissas!$C$74))*Premissas!$C$21*(1+Premissas!$C$26)^(5) -> 23801.328 | F76: =Dimensionador!$C$7*Premissas!$C$13*(Premissas!$C$74+0.8333333333*(Premissas!$C$75-Premissas!$C$74))*Premissas!$C$20*(1+Premissas!$C$26)^(5) -> 6445.4801 | G76: =Dimensionador!$C$7*Premissas!$C$25*(1+Premissas!$C$27)^(5)/12 -> 2125.3358 | H76: =Premissas!$C$62*(1-Premissas!$C$32)^(5) -> 52114.855 | I76: =MIN(H76,Dimensionador!$C$7*Premissas!$C$13*(Premissas!$C$74+0.8333333333*(Premissas!$C$75-Premissas!$C$74))) -> 7007.9101 | J76: =MAX(0,H76-I76) -> 45106.945 | K76: =Premissas!$C$35*(1+Premissas!$C$27)^(5)/12 -> 1147.1983 | L76: =E76-F76+(I76+J76)*Premissas!$C$20*(1+Premissas!$C$26)^(5) -> 65288.149 | M76: =L76-G76-K76 -> 62015.615 | N76: =N75+M76 -> 1477328.2 | O76: =O75+M76 -> 3764828.2 | P76: =IF(AND(N76>=0,N75<0),"✅ PAYBACK","") | Q76: =I76 -> 7007.9101
A77: 6 | B77: Dez | C77: =Premissas!$C$74+0.9166666667*(Premissas!$C$75-Premissas!$C$74) -> 0.8715 | D77: =(1+Premissas!$C$26)^(5) -> 1.4693281 | E77: =Dimensionador!$C$22*(Premissas!$C$74+0.9166666667*(Premissas!$C$75-Premissas!$C$74))*Premissas!$C$21*(1+Premissas!$C$26)^(5) -> 23760.432 | F77: =Dimensionador!$C$7*Premissas!$C$13*(Premissas!$C$74+0.9166666667*(Premissas!$C$75-Premissas!$C$74))*Premissas!$C$20*(1+Premissas!$C$26)^(5) -> 6434.4053 | G77: =Dimensionador!$C$7*Premissas!$C$25*(1+Premissas!$C$27)^(5)/12 -> 2125.3358 | H77: =Premissas!$C$63*(1-Premissas!$C$32)^(5) -> 53852.017 | I77: =MIN(H77,Dimensionador!$C$7*Premissas!$C$13*(Premissas!$C$74+0.9166666667*(Premissas!$C$75-Premissas!$C$74))) -> 6995.869 | J77: =MAX(0,H77-I77) -> 46856.148 | K77: =Premissas!$C$35*(1+Premissas!$C$27)^(5)/12 -> 1147.1983 | L77: =E77-F77+(I77+J77)*Premissas!$C$20*(1+Premissas!$C$26)^(5) -> 66856.072 | M77: =L77-G77-K77 -> 63583.538 | N77: =N76+M77 -> 1540911.7 | O77: =O76+M77 -> 3828411.7 | P77: =IF(AND(N77>=0,N76<0),"✅ PAYBACK","") | Q77: =I77 -> 6995.869
A78: 7 | B78: Jan | C78: =Premissas!$C$75+0*(Premissas!$C$76-Premissas!$C$75) -> 0.87 | D78: =(1+Premissas!$C$26)^(6) -> 1.5868743 | E78: =Dimensionador!$C$22*(Premissas!$C$75+0*(Premissas!$C$76-Premissas!$C$75))*Premissas!$C$21*(1+Premissas!$C$26)^(6) -> 25617.099 | F78: =Dimensionador!$C$7*Premissas!$C$13*(Premissas!$C$75+0*(Premissas!$C$76-Premissas!$C$75))*Premissas!$C$20*(1+Premissas!$C$26)^(6) -> 6937.1971 | G78: =Dimensionador!$C$7*Premissas!$C$25*(1+Premissas!$C$27)^(6)/12 -> 2189.0959 | H78: =Premissas!$C$52*(1-Premissas!$C$32)^(6) -> 53582.757 | I78: =MIN(H78,Dimensionador!$C$7*Premissas!$C$13*(Premissas!$C$75+0*(Premissas!$C$76-Premissas!$C$75))) -> 6983.8279 | J78: =MAX(0,H78-I78) -> 46598.929 | K78: =Premissas!$C$35*(1+Premissas!$C$27)^(6)/12 -> 1181.6143 | L78: =E78-F78+(I78+J78)*Premissas!$C$20*(1+Premissas!$C$26)^(6) -> 71904.888 | M78: =L78-G78-K78 -> 68534.178 | N78: =N77+M78 -> 1609445.9 | O78: =O77+M78 -> 3896945.9 | P78: =IF(AND(N78>=0,N77<0),"✅ PAYBACK","") | Q78: =I78 -> 6983.8279
A79: 7 | B79: Fev | C79: =Premissas!$C$75+0.0833333333*(Premissas!$C$76-Premissas!$C$75) -> 0.8685 | D79: =(1+Premissas!$C$26)^(6) -> 1.5868743 | E79: =Dimensionador!$C$22*(Premissas!$C$75+0.0833333333*(Premissas!$C$76-Premissas!$C$75))*Premissas!$C$21*(1+Premissas!$C$26)^(6) -> 25572.932 | F79: =Dimensionador!$C$7*Premissas!$C$13*(Premissas!$C$75+0.0833333333*(Premissas!$C$76-Premissas!$C$75))*Premissas!$C$20*(1+Premissas!$C$26)^(6) -> 6925.2364 | G79: =Dimensionador!$C$7*Premissas!$C$25*(1+Premissas!$C$27)^(6)/12 -> 2189.0959 | H79: =Premissas!$C$53*(1-Premissas!$C$32)^(6) -> 48397.329 | I79: =MIN(H79,Dimensionador!$C$7*Premissas!$C$13*(Premissas!$C$75+0.0833333333*(Premissas!$C$76-Premissas!$C$75))) -> 6971.7869 | J79: =MAX(0,H79-I79) -> 41425.542 | K79: =Premissas!$C$35*(1+Premissas!$C$27)^(6)/12 -> 1181.6143 | L79: =E79-F79+(I79+J79)*Premissas!$C$20*(1+Premissas!$C$26)^(6) -> 66721.877 | M79: =L79-G79-K79 -> 63351.166 | N79: =N78+M79 -> 1672797.1 | O79: =O78+M79 -> 3960297.1 | P79: =IF(AND(N79>=0,N78<0),"✅ PAYBACK","") | Q79: =I79 -> 6971.7869
A80: 7 | B80: Mar | C80: =Premissas!$C$75+0.1666666667*(Premissas!$C$76-Premissas!$C$75) -> 0.867 | D80: =(1+Premissas!$C$26)^(6) -> 1.5868743 | E80: =Dimensionador!$C$22*(Premissas!$C$75+0.1666666667*(Premissas!$C$76-Premissas!$C$75))*Premissas!$C$21*(1+Premissas!$C$26)^(6) -> 25528.764 | F80: =Dimensionador!$C$7*Premissas!$C$13*(Premissas!$C$75+0.1666666667*(Premissas!$C$76-Premissas!$C$75))*Premissas!$C$20*(1+Premissas!$C$26)^(6) -> 6913.2757 | G80: =Dimensionador!$C$7*Premissas!$C$25*(1+Premissas!$C$27)^(6)/12 -> 2189.0959 | H80: =Premissas!$C$54*(1-Premissas!$C$32)^(6) -> 53582.757 | I80: =MIN(H80,Dimensionador!$C$7*Premissas!$C$13*(Premissas!$C$75+0.1666666667*(Premissas!$C$76-Premissas!$C$75))) -> 6959.7458 | J80: =MAX(0,H80-I80) -> 46623.011 | K80: =Premissas!$C$35*(1+Premissas!$C$27)^(6)/12 -> 1181.6143 | L80: =E80-F80+(I80+J80)*Premissas!$C$20*(1+Premissas!$C$26)^(6) -> 71840.475 | M80: =L80-G80-K80 -> 68469.765 | N80: =N79+M80 -> 1741266.8 | O80: =O79+M80 -> 4028766.8 | P80: =IF(AND(N80>=0,N79<0),"✅ PAYBACK","") | Q80: =I80 -> 6959.7458
A81: 7 | B81: Abr | C81: =Premissas!$C$75+0.25*(Premissas!$C$76-Premissas!$C$75) -> 0.8655 | D81: =(1+Premissas!$C$26)^(6) -> 1.5868743 | E81: =Dimensionador!$C$22*(Premissas!$C$75+0.25*(Premissas!$C$76-Premissas!$C$75))*Premissas!$C$21*(1+Premissas!$C$26)^(6) -> 25484.597 | F81: =Dimensionador!$C$7*Premissas!$C$13*(Premissas!$C$75+0.25*(Premissas!$C$76-Premissas!$C$75))*Premissas!$C$20*(1+Premissas!$C$26)^(6) -> 6901.315 | G81: =Dimensionador!$C$7*Premissas!$C$25*(1+Premissas!$C$27)^(6)/12 -> 2189.0959 | H81: =Premissas!$C$55*(1-Premissas!$C$32)^(6) -> 51854.281 | I81: =MIN(H81,Dimensionador!$C$7*Premissas!$C$13*(Premissas!$C$75+0.25*(Premissas!$C$76-Premissas!$C$75))) -> 6947.7047 | J81: =MAX(0,H81-I81) -> 44906.576 | K81: =Premissas!$C$35*(1+Premissas!$C$27)^(6)/12 -> 1181.6143 | L81: =E81-F81+(I81+J81)*Premissas!$C$20*(1+Premissas!$C$26)^(6) -> 70091.333 | M81: =L81-G81-K81 -> 66720.623 | N81: =N80+M81 -> 1807987.5 | O81: =O80+M81 -> 4095487.5 | P81: =IF(AND(N81>=0,N80<0),"✅ PAYBACK","") | Q81: =I81 -> 6947.7047
A82: 7 | B82: Mai | C82: =Premissas!$C$75+0.3333333333*(Premissas!$C$76-Premissas!$C$75) -> 0.864 | D82: =(1+Premissas!$C$26)^(6) -> 1.5868743 | E82: =Dimensionador!$C$22*(Premissas!$C$75+0.3333333333*(Premissas!$C$76-Premissas!$C$75))*Premissas!$C$21*(1+Premissas!$C$26)^(6) -> 25440.43 | F82: =Dimensionador!$C$7*Premissas!$C$13*(Premissas!$C$75+0.3333333333*(Premissas!$C$76-Premissas!$C$75))*Premissas!$C$20*(1+Premissas!$C$26)^(6) -> 6889.3544 | G82: =Dimensionador!$C$7*Premissas!$C$25*(1+Premissas!$C$27)^(6)/12 -> 2189.0959 | H82: =Premissas!$C$56*(1-Premissas!$C$32)^(6) -> 53582.757 | I82: =MIN(H82,Dimensionador!$C$7*Premissas!$C$13*(Premissas!$C$75+0.3333333333*(Premissas!$C$76-Premissas!$C$75))) -> 6935.6636 | J82: =MAX(0,H82-I82) -> 46647.093 | K82: =Premissas!$C$35*(1+Premissas!$C$27)^(6)/12 -> 1181.6143 | L82: =E82-F82+(I82+J82)*Premissas!$C$20*(1+Premissas!$C$26)^(6) -> 71776.062 | M82: =L82-G82-K82 -> 68405.351 | N82: =N81+M82 -> 1876392.8 | O82: =O81+M82 -> 4163892.8 | P82: =IF(AND(N82>=0,N81<0),"✅ PAYBACK","") | Q82: =I82 -> 6935.6636
A83: 7 | B83: Jun | C83: =Premissas!$C$75+0.4166666667*(Premissas!$C$76-Premissas!$C$75) -> 0.8625 | D83: =(1+Premissas!$C$26)^(6) -> 1.5868743 | E83: =Dimensionador!$C$22*(Premissas!$C$75+0.4166666667*(Premissas!$C$76-Premissas!$C$75))*Premissas!$C$21*(1+Premissas!$C$26)^(6) -> 25396.262 | F83: =Dimensionador!$C$7*Premissas!$C$13*(Premissas!$C$75+0.4166666667*(Premissas!$C$76-Premissas!$C$75))*Premissas!$C$20*(1+Premissas!$C$26)^(6) -> 6877.3937 | G83: =Dimensionador!$C$7*Premissas!$C$25*(1+Premissas!$C$27)^(6)/12 -> 2189.0959 | H83: =Premissas!$C$57*(1-Premissas!$C$32)^(6) -> 51854.281 | I83: =MIN(H83,Dimensionador!$C$7*Premissas!$C$13*(Premissas!$C$75+0.4166666667*(Premissas!$C$76-Premissas!$C$75))) -> 6923.6225 | J83: =MAX(0,H83-I83) -> 44930.658 | K83: =Premissas!$C$35*(1+Premissas!$C$27)^(6)/12 -> 1181.6143 | L83: =E83-F83+(I83+J83)*Premissas!$C$20*(1+Premissas!$C$26)^(6) -> 70026.92 | M83: =L83-G83-K83 -> 66656.21 | N83: =N82+M83 -> 1943049 | O83: =O82+M83 -> 4230549 | P83: =IF(AND(N83>=0,N82<0),"✅ PAYBACK","") | Q83: =I83 -> 6923.6225
A84: 7 | B84: Jul | C84: =Premissas!$C$75+0.5*(Premissas!$C$76-Premissas!$C$75) -> 0.861 | D84: =(1+Premissas!$C$26)^(6) -> 1.5868743 | E84: =Dimensionador!$C$22*(Premissas!$C$75+0.5*(Premissas!$C$76-Premissas!$C$75))*Premissas!$C$21*(1+Premissas!$C$26)^(6) -> 25352.095 | F84: =Dimensionador!$C$7*Premissas!$C$13*(Premissas!$C$75+0.5*(Premissas!$C$76-Premissas!$C$75))*Premissas!$C$20*(1+Premissas!$C$26)^(6) -> 6865.433 | G84: =Dimensionador!$C$7*Premissas!$C$25*(1+Premissas!$C$27)^(6)/12 -> 2189.0959 | H84: =Premissas!$C$58*(1-Premissas!$C$32)^(6) -> 53582.757 | I84: =MIN(H84,Dimensionador!$C$7*Premissas!$C$13*(Premissas!$C$75+0.5*(Premissas!$C$76-Premissas!$C$75))) -> 6911.5814 | J84: =MAX(0,H84-I84) -> 46671.176 | K84: =Premissas!$C$35*(1+Premissas!$C$27)^(6)/12 -> 1181.6143 | L84: =E84-F84+(I84+J84)*Premissas!$C$20*(1+Premissas!$C$26)^(6) -> 71711.648 | M84: =L84-G84-K84 -> 68340.938 | N84: =N83+M84 -> 2011390 | O84: =O83+M84 -> 4298890 | P84: =IF(AND(N84>=0,N83<0),"✅ PAYBACK","") | Q84: =I84 -> 6911.5814
A85: 7 | B85: Ago | C85: =Premissas!$C$75+0.5833333333*(Premissas!$C$76-Premissas!$C$75) -> 0.8595 | D85: =(1+Premissas!$C$26)^(6) -> 1.5868743 | E85: =Dimensionador!$C$22*(Premissas!$C$75+0.5833333333*(Premissas!$C$76-Premissas!$C$75))*Premissas!$C$21*(1+Premissas!$C$26)^(6) -> 25307.927 | F85: =Dimensionador!$C$7*Premissas!$C$13*(Premissas!$C$75+0.5833333333*(Premissas!$C$76-Premissas!$C$75))*Premissas!$C$20*(1+Premissas!$C$26)^(6) -> 6853.4723 | G85: =Dimensionador!$C$7*Premissas!$C$25*(1+Premissas!$C$27)^(6)/12 -> 2189.0959 | H85: =Premissas!$C$59*(1-Premissas!$C$32)^(6) -> 53582.757 | I85: =MIN(H85,Dimensionador!$C$7*Premissas!$C$13*(Premissas!$C$75+0.5833333333*(Premissas!$C$76-Premissas!$C$75))) -> 6899.5404 | J85: =MAX(0,H85-I85) -> 46683.217 | K85: =Premissas!$C$35*(1+Premissas!$C$27)^(6)/12 -> 1181.6143 | L85: =E85-F85+(I85+J85)*Premissas!$C$20*(1+Premissas!$C$26)^(6) -> 71679.441 | M85: =L85-G85-K85 -> 68308.731 | N85: =N84+M85 -> 2079698.7 | O85: =O84+M85 -> 4367198.7 | P85: =IF(AND(N85>=0,N84<0),"✅ PAYBACK","") | Q85: =I85 -> 6899.5404
A86: 7 | B86: Set | C86: =Premissas!$C$75+0.6666666667*(Premissas!$C$76-Premissas!$C$75) -> 0.858 | D86: =(1+Premissas!$C$26)^(6) -> 1.5868743 | E86: =Dimensionador!$C$22*(Premissas!$C$75+0.6666666667*(Premissas!$C$76-Premissas!$C$75))*Premissas!$C$21*(1+Premissas!$C$26)^(6) -> 25263.76 | F86: =Dimensionador!$C$7*Premissas!$C$13*(Premissas!$C$75+0.6666666667*(Premissas!$C$76-Premissas!$C$75))*Premissas!$C$20*(1+Premissas!$C$26)^(6) -> 6841.5116 | G86: =Dimensionador!$C$7*Premissas!$C$25*(1+Premissas!$C$27)^(6)/12 -> 2189.0959 | H86: =Premissas!$C$60*(1-Premissas!$C$32)^(6) -> 51854.281 | I86: =MIN(H86,Dimensionador!$C$7*Premissas!$C$13*(Premissas!$C$75+0.6666666667*(Premissas!$C$76-Premissas!$C$75))) -> 6887.4993 | J86: =MAX(0,H86-I86) -> 44966.782 | K86: =Premissas!$C$35*(1+Premissas!$C$27)^(6)/12 -> 1181.6143 | L86: =E86-F86+(I86+J86)*Premissas!$C$20*(1+Premissas!$C$26)^(6) -> 69930.3 | M86: =L86-G86-K86 -> 66559.589 | N86: =N85+M86 -> 2146258.3 | O86: =O85+M86 -> 4433758.3 | P86: =IF(AND(N86>=0,N85<0),"✅ PAYBACK","") | Q86: =I86 -> 6887.4993
A87: 7 | B87: Out | C87: =Premissas!$C$75+0.75*(Premissas!$C$76-Premissas!$C$75) -> 0.8565 | D87: =(1+Premissas!$C$26)^(6) -> 1.5868743 | E87: =Dimensionador!$C$22*(Premissas!$C$75+0.75*(Premissas!$C$76-Premissas!$C$75))*Premissas!$C$21*(1+Premissas!$C$26)^(6) -> 25219.593 | F87: =Dimensionador!$C$7*Premissas!$C$13*(Premissas!$C$75+0.75*(Premissas!$C$76-Premissas!$C$75))*Premissas!$C$20*(1+Premissas!$C$26)^(6) -> 6829.5509 | G87: =Dimensionador!$C$7*Premissas!$C$25*(1+Premissas!$C$27)^(6)/12 -> 2189.0959 | H87: =Premissas!$C$61*(1-Premissas!$C$32)^(6) -> 53582.757 | I87: =MIN(H87,Dimensionador!$C$7*Premissas!$C$13*(Premissas!$C$75+0.75*(Premissas!$C$76-Premissas!$C$75))) -> 6875.4582 | J87: =MAX(0,H87-I87) -> 46707.299 | K87: =Premissas!$C$35*(1+Premissas!$C$27)^(6)/12 -> 1181.6143 | L87: =E87-F87+(I87+J87)*Premissas!$C$20*(1+Premissas!$C$26)^(6) -> 71615.028 | M87: =L87-G87-K87 -> 68244.318 | N87: =N86+M87 -> 2214502.6 | O87: =O86+M87 -> 4502002.6 | P87: =IF(AND(N87>=0,N86<0),"✅ PAYBACK","") | Q87: =I87 -> 6875.4582
A88: 7 | B88: Nov | C88: =Premissas!$C$75+0.8333333333*(Premissas!$C$76-Premissas!$C$75) -> 0.855 | D88: =(1+Premissas!$C$26)^(6) -> 1.5868743 | E88: =Dimensionador!$C$22*(Premissas!$C$75+0.8333333333*(Premissas!$C$76-Premissas!$C$75))*Premissas!$C$21*(1+Premissas!$C$26)^(6) -> 25175.425 | F88: =Dimensionador!$C$7*Premissas!$C$13*(Premissas!$C$75+0.8333333333*(Premissas!$C$76-Premissas!$C$75))*Premissas!$C$20*(1+Premissas!$C$26)^(6) -> 6817.5902 | G88: =Dimensionador!$C$7*Premissas!$C$25*(1+Premissas!$C$27)^(6)/12 -> 2189.0959 | H88: =Premissas!$C$62*(1-Premissas!$C$32)^(6) -> 51854.281 | I88: =MIN(H88,Dimensionador!$C$7*Premissas!$C$13*(Premissas!$C$75+0.8333333333*(Premissas!$C$76-Premissas!$C$75))) -> 6863.4171 | J88: =MAX(0,H88-I88) -> 44990.864 | K88: =Premissas!$C$35*(1+Premissas!$C$27)^(6)/12 -> 1181.6143 | L88: =E88-F88+(I88+J88)*Premissas!$C$20*(1+Premissas!$C$26)^(6) -> 69865.886 | M88: =L88-G88-K88 -> 66495.176 | N88: =N87+M88 -> 2280997.8 | O88: =O87+M88 -> 4568497.8 | P88: =IF(AND(N88>=0,N87<0),"✅ PAYBACK","") | Q88: =I88 -> 6863.4171
A89: 7 | B89: Dez | C89: =Premissas!$C$75+0.9166666667*(Premissas!$C$76-Premissas!$C$75) -> 0.8535 | D89: =(1+Premissas!$C$26)^(6) -> 1.5868743 | E89: =Dimensionador!$C$22*(Premissas!$C$75+0.9166666667*(Premissas!$C$76-Premissas!$C$75))*Premissas!$C$21*(1+Premissas!$C$26)^(6) -> 25131.258 | F89: =Dimensionador!$C$7*Premissas!$C$13*(Premissas!$C$75+0.9166666667*(Premissas!$C$76-Premissas!$C$75))*Premissas!$C$20*(1+Premissas!$C$26)^(6) -> 6805.6296 | G89: =Dimensionador!$C$7*Premissas!$C$25*(1+Premissas!$C$27)^(6)/12 -> 2189.0959 | H89: =Premissas!$C$63*(1-Premissas!$C$32)^(6) -> 53582.757 | I89: =MIN(H89,Dimensionador!$C$7*Premissas!$C$13*(Premissas!$C$75+0.9166666667*(Premissas!$C$76-Premissas!$C$75))) -> 6851.376 | J89: =MAX(0,H89-I89) -> 46731.381 | K89: =Premissas!$C$35*(1+Premissas!$C$27)^(6)/12 -> 1181.6143 | L89: =E89-F89+(I89+J89)*Premissas!$C$20*(1+Premissas!$C$26)^(6) -> 71550.614 | M89: =L89-G89-K89 -> 68179.904 | N89: =N88+M89 -> 2349177.7 | O89: =O88+M89 -> 4636677.7 | P89: =IF(AND(N89>=0,N88<0),"✅ PAYBACK","") | Q89: =I89 -> 6851.376
A90: 8 | B90: Jan | C90: =Premissas!$C$76+0*(Premissas!$C$77-Premissas!$C$76) -> 0.852 | D90: =(1+Premissas!$C$26)^(7) -> 1.7138243 | E90: =Dimensionador!$C$22*(Premissas!$C$76+0*(Premissas!$C$77-Premissas!$C$76))*Premissas!$C$21*(1+Premissas!$C$26)^(7) -> 27094.058 | F90: =Dimensionador!$C$7*Premissas!$C$13*(Premissas!$C$76+0*(Premissas!$C$77-Premissas!$C$76))*Premissas!$C$20*(1+Premissas!$C$26)^(7) -> 7337.1624 | G90: =Dimensionador!$C$7*Premissas!$C$25*(1+Premissas!$C$27)^(7)/12 -> 2254.7688 | H90: =Premissas!$C$52*(1-Premissas!$C$32)^(7) -> 53314.843 | I90: =MIN(H90,Dimensionador!$C$7*Premissas!$C$13*(Premissas!$C$76+0*(Premissas!$C$77-Premissas!$C$76))) -> 6839.3349 | J90: =MAX(0,H90-I90) -> 46475.508 | K90: =Premissas!$C$35*(1+Premissas!$C$27)^(7)/12 -> 1217.0627 | L90: =E90-F90+(I90+J90)*Premissas!$C$20*(1+Premissas!$C$26)^(7) -> 76952.465 | M90: =L90-G90-K90 -> 73480.634 | N90: =N89+M90 -> 2422658.3 | O90: =O89+M90 -> 4710158.3 | P90: =IF(AND(N90>=0,N89<0),"✅ PAYBACK","") | Q90: =I90 -> 6839.3349
A91: 8 | B91: Fev | C91: =Premissas!$C$76+0.0833333333*(Premissas!$C$77-Premissas!$C$76) -> 0.8505 | D91: =(1+Premissas!$C$26)^(7) -> 1.7138243 | E91: =Dimensionador!$C$22*(Premissas!$C$76+0.0833333333*(Premissas!$C$77-Premissas!$C$76))*Premissas!$C$21*(1+Premissas!$C$26)^(7) -> 27046.357 | F91: =Dimensionador!$C$7*Premissas!$C$13*(Premissas!$C$76+0.0833333333*(Premissas!$C$77-Premissas!$C$76))*Premissas!$C$20*(1+Premissas!$C$26)^(7) -> 7324.2448 | G91: =Dimensionador!$C$7*Premissas!$C$25*(1+Premissas!$C$27)^(7)/12 -> 2254.7688 | H91: =Premissas!$C$53*(1-Premissas!$C$32)^(7) -> 48155.342 | I91: =MIN(H91,Dimensionador!$C$7*Premissas!$C$13*(Premissas!$C$76+0.0833333333*(Premissas!$C$77-Premissas!$C$76))) -> 6827.2939 | J91: =MAX(0,H91-I91) -> 41328.048 | K91: =Premissas!$C$35*(1+Premissas!$C$27)^(7)/12 -> 1217.0627 | L91: =E91-F91+(I91+J91)*Premissas!$C$20*(1+Premissas!$C$26)^(7) -> 71382.627 | M91: =L91-G91-K91 -> 67910.796 | N91: =N90+M91 -> 2490569.1 | O91: =O90+M91 -> 4778069.1 | P91: =IF(AND(N91>=0,N90<0),"✅ PAYBACK","") | Q91: =I91 -> 6827.2939
A92: 8 | B92: Mar | C92: =Premissas!$C$76+0.1666666667*(Premissas!$C$77-Premissas!$C$76) -> 0.849 | D92: =(1+Premissas!$C$26)^(7) -> 1.7138243 | E92: =Dimensionador!$C$22*(Premissas!$C$76+0.1666666667*(Premissas!$C$77-Premissas!$C$76))*Premissas!$C$21*(1+Premissas!$C$26)^(7) -> 26998.656 | F92: =Dimensionador!$C$7*Premissas!$C$13*(Premissas!$C$76+0.1666666667*(Premissas!$C$77-Premissas!$C$76))*Premissas!$C$20*(1+Premissas!$C$26)^(7) -> 7311.3273 | G92: =Dimensionador!$C$7*Premissas!$C$25*(1+Premissas!$C$27)^(7)/12 -> 2254.7688 | H92: =Premissas!$C$54*(1-Premissas!$C$32)^(7) -> 53314.843 | I92: =MIN(H92,Dimensionador!$C$7*Premissas!$C$13*(Premissas!$C$76+0.1666666667*(Premissas!$C$77-Premissas!$C$76))) -> 6815.2528 | J92: =MAX(0,H92-I92) -> 46499.59 | K92: =Premissas!$C$35*(1+Premissas!$C$27)^(7)/12 -> 1217.0627 | L92: =E92-F92+(I92+J92)*Premissas!$C$20*(1+Premissas!$C$26)^(7) -> 76882.899 | M92: =L92-G92-K92 -> 73411.067 | N92: =N91+M92 -> 2563980.2 | O92: =O91+M92 -> 4851480.2 | P92: =IF(AND(N92>=0,N91<0),"✅ PAYBACK","") | Q92: =I92 -> 6815.2528
A93: 8 | B93: Abr | C93: =Premissas!$C$76+0.25*(Premissas!$C$77-Premissas!$C$76) -> 0.8475 | D93: =(1+Premissas!$C$26)^(7) -> 1.7138243 | E93: =Dimensionador!$C$22*(Premissas!$C$76+0.25*(Premissas!$C$77-Premissas!$C$76))*Premissas!$C$21*(1+Premissas!$C$26)^(7) -> 26950.955 | F93: =Dimensionador!$C$7*Premissas!$C$13*(Premissas!$C$76+0.25*(Premissas!$C$77-Premissas!$C$76))*Premissas!$C$20*(1+Premissas!$C$26)^(7) -> 7298.4098 | G93: =Dimensionador!$C$7*Premissas!$C$25*(1+Premissas!$C$27)^(7)/12 -> 2254.7688 | H93: =Premissas!$C$55*(1-Premissas!$C$32)^(7) -> 51595.01 | I93: =MIN(H93,Dimensionador!$C$7*Premissas!$C$13*(Premissas!$C$76+0.25*(Premissas!$C$77-Premissas!$C$76))) -> 6803.2117 | J93: =MAX(0,H93-I93) -> 44791.798 | K93: =Premissas!$C$35*(1+Premissas!$C$27)^(7)/12 -> 1217.0627 | L93: =E93-F93+(I93+J93)*Premissas!$C$20*(1+Premissas!$C$26)^(7) -> 75003.097 | M93: =L93-G93-K93 -> 71531.266 | N93: =N92+M93 -> 2635511.4 | O93: =O92+M93 -> 4923011.4 | P93: =IF(AND(N93>=0,N92<0),"✅ PAYBACK","") | Q93: =I93 -> 6803.2117
A94: 8 | B94: Mai | C94: =Premissas!$C$76+0.3333333333*(Premissas!$C$77-Premissas!$C$76) -> 0.846 | D94: =(1+Premissas!$C$26)^(7) -> 1.7138243 | E94: =Dimensionador!$C$22*(Premissas!$C$76+0.3333333333*(Premissas!$C$77-Premissas!$C$76))*Premissas!$C$21*(1+Premissas!$C$26)^(7) -> 26903.254 | F94: =Dimensionador!$C$7*Premissas!$C$13*(Premissas!$C$76+0.3333333333*(Premissas!$C$77-Premissas!$C$76))*Premissas!$C$20*(1+Premissas!$C$26)^(7) -> 7285.4922 | G94: =Dimensionador!$C$7*Premissas!$C$25*(1+Premissas!$C$27)^(7)/12 -> 2254.7688 | H94: =Premissas!$C$56*(1-Premissas!$C$32)^(7) -> 53314.843 | I94: =MIN(H94,Dimensionador!$C$7*Premissas!$C$13*(Premissas!$C$76+0.3333333333*(Premissas!$C$77-Premissas!$C$76))) -> 6791.1706 | J94: =MAX(0,H94-I94) -> 46523.673 | K94: =Premissas!$C$35*(1+Premissas!$C$27)^(7)/12 -> 1217.0627 | L94: =E94-F94+(I94+J94)*Premissas!$C$20*(1+Premissas!$C$26)^(7) -> 76813.332 | M94: =L94-G94-K94 -> 73341.501 | N94: =N93+M94 -> 2708852.9 | O94: =O93+M94 -> 4996352.9 | P94: =IF(AND(N94>=0,N93<0),"✅ PAYBACK","") | Q94: =I94 -> 6791.1706
A95: 8 | B95: Jun | C95: =Premissas!$C$76+0.4166666667*(Premissas!$C$77-Premissas!$C$76) -> 0.8445 | D95: =(1+Premissas!$C$26)^(7) -> 1.7138243 | E95: =Dimensionador!$C$22*(Premissas!$C$76+0.4166666667*(Premissas!$C$77-Premissas!$C$76))*Premissas!$C$21*(1+Premissas!$C$26)^(7) -> 26855.554 | F95: =Dimensionador!$C$7*Premissas!$C$13*(Premissas!$C$76+0.4166666667*(Premissas!$C$77-Premissas!$C$76))*Premissas!$C$20*(1+Premissas!$C$26)^(7) -> 7272.5747 | G95: =Dimensionador!$C$7*Premissas!$C$25*(1+Premissas!$C$27)^(7)/12 -> 2254.7688 | H95: =Premissas!$C$57*(1-Premissas!$C$32)^(7) -> 51595.01 | I95: =MIN(H95,Dimensionador!$C$7*Premissas!$C$13*(Premissas!$C$76+0.4166666667*(Premissas!$C$77-Premissas!$C$76))) -> 6779.1295 | J95: =MAX(0,H95-I95) -> 44815.88 | K95: =Premissas!$C$35*(1+Premissas!$C$27)^(7)/12 -> 1217.0627 | L95: =E95-F95+(I95+J95)*Premissas!$C$20*(1+Premissas!$C$26)^(7) -> 74933.531 | M95: =L95-G95-K95 -> 71461.699 | N95: =N94+M95 -> 2780314.6 | O95: =O94+M95 -> 5067814.6 | P95: =IF(AND(N95>=0,N94<0),"✅ PAYBACK","") | Q95: =I95 -> 6779.1295
A96: 8 | B96: Jul | C96: =Premissas!$C$76+0.5*(Premissas!$C$77-Premissas!$C$76) -> 0.843 | D96: =(1+Premissas!$C$26)^(7) -> 1.7138243 | E96: =Dimensionador!$C$22*(Premissas!$C$76+0.5*(Premissas!$C$77-Premissas!$C$76))*Premissas!$C$21*(1+Premissas!$C$26)^(7) -> 26807.853 | F96: =Dimensionador!$C$7*Premissas!$C$13*(Premissas!$C$76+0.5*(Premissas!$C$77-Premissas!$C$76))*Premissas!$C$20*(1+Premissas!$C$26)^(7) -> 7259.6571 | G96: =Dimensionador!$C$7*Premissas!$C$25*(1+Premissas!$C$27)^(7)/12 -> 2254.7688 | H96: =Premissas!$C$58*(1-Premissas!$C$32)^(7) -> 53314.843 | I96: =MIN(H96,Dimensionador!$C$7*Premissas!$C$13*(Premissas!$C$76+0.5*(Premissas!$C$77-Premissas!$C$76))) -> 6767.0884 | J96: =MAX(0,H96-I96) -> 46547.755 | K96: =Premissas!$C$35*(1+Premissas!$C$27)^(7)/12 -> 1217.0627 | L96: =E96-F96+(I96+J96)*Premissas!$C$20*(1+Premissas!$C$26)^(7) -> 76743.766 | M96: =L96-G96-K96 -> 73271.934 | N96: =N95+M96 -> 2853586.6 | O96: =O95+M96 -> 5141086.6 | P96: =IF(AND(N96>=0,N95<0),"✅ PAYBACK","") | Q96: =I96 -> 6767.0884
A97: 8 | B97: Ago | C97: =Premissas!$C$76+0.5833333333*(Premissas!$C$77-Premissas!$C$76) -> 0.8415 | D97: =(1+Premissas!$C$26)^(7) -> 1.7138243 | E97: =Dimensionador!$C$22*(Premissas!$C$76+0.5833333333*(Premissas!$C$77-Premissas!$C$76))*Premissas!$C$21*(1+Premissas!$C$26)^(7) -> 26760.152 | F97: =Dimensionador!$C$7*Premissas!$C$13*(Premissas!$C$76+0.5833333333*(Premissas!$C$77-Premissas!$C$76))*Premissas!$C$20*(1+Premissas!$C$26)^(7) -> 7246.7396 | G97: =Dimensionador!$C$7*Premissas!$C$25*(1+Premissas!$C$27)^(7)/12 -> 2254.7688 | H97: =Premissas!$C$59*(1-Premissas!$C$32)^(7) -> 53314.843 | I97: =MIN(H97,Dimensionador!$C$7*Premissas!$C$13*(Premissas!$C$76+0.5833333333*(Premissas!$C$77-Premissas!$C$76))) -> 6755.0474 | J97: =MAX(0,H97-I97) -> 46559.796 | K97: =Premissas!$C$35*(1+Premissas!$C$27)^(7)/12 -> 1217.0627 | L97: =E97-F97+(I97+J97)*Premissas!$C$20*(1+Premissas!$C$26)^(7) -> 76708.983 | M97: =L97-G97-K97 -> 73237.151 | N97: =N96+M97 -> 2926823.7 | O97: =O96+M97 -> 5214323.7 | P97: =IF(AND(N97>=0,N96<0),"✅ PAYBACK","") | Q97: =I97 -> 6755.0474
A98: 8 | B98: Set | C98: =Premissas!$C$76+0.6666666667*(Premissas!$C$77-Premissas!$C$76) -> 0.84 | D98: =(1+Premissas!$C$26)^(7) -> 1.7138243 | E98: =Dimensionador!$C$22*(Premissas!$C$76+0.6666666667*(Premissas!$C$77-Premissas!$C$76))*Premissas!$C$21*(1+Premissas!$C$26)^(7) -> 26712.451 | F98: =Dimensionador!$C$7*Premissas!$C$13*(Premissas!$C$76+0.6666666667*(Premissas!$C$77-Premissas!$C$76))*Premissas!$C$20*(1+Premissas!$C$26)^(7) -> 7233.8221 | G98: =Dimensionador!$C$7*Premissas!$C$25*(1+Premissas!$C$27)^(7)/12 -> 2254.7688 | H98: =Premissas!$C$60*(1-Premissas!$C$32)^(7) -> 51595.01 | I98: =MIN(H98,Dimensionador!$C$7*Premissas!$C$13*(Premissas!$C$76+0.6666666667*(Premissas!$C$77-Premissas!$C$76))) -> 6743.0063 | J98: =MAX(0,H98-I98) -> 44852.003 | K98: =Premissas!$C$35*(1+Premissas!$C$27)^(7)/12 -> 1217.0627 | L98: =E98-F98+(I98+J98)*Premissas!$C$20*(1+Premissas!$C$26)^(7) -> 74829.181 | M98: =L98-G98-K98 -> 71357.349 | N98: =N97+M98 -> 2998181.1 | O98: =O97+M98 -> 5285681.1 | P98: =IF(AND(N98>=0,N97<0),"✅ PAYBACK","") | Q98: =I98 -> 6743.0063
A99: 8 | B99: Out | C99: =Premissas!$C$76+0.75*(Premissas!$C$77-Premissas!$C$76) -> 0.8385 | D99: =(1+Premissas!$C$26)^(7) -> 1.7138243 | E99: =Dimensionador!$C$22*(Premissas!$C$76+0.75*(Premissas!$C$77-Premissas!$C$76))*Premissas!$C$21*(1+Premissas!$C$26)^(7) -> 26664.75 | F99: =Dimensionador!$C$7*Premissas!$C$13*(Premissas!$C$76+0.75*(Premissas!$C$77-Premissas!$C$76))*Premissas!$C$20*(1+Premissas!$C$26)^(7) -> 7220.9045 | G99: =Dimensionador!$C$7*Premissas!$C$25*(1+Premissas!$C$27)^(7)/12 -> 2254.7688 | H99: =Premissas!$C$61*(1-Premissas!$C$32)^(7) -> 53314.843 | I99: =MIN(H99,Dimensionador!$C$7*Premissas!$C$13*(Premissas!$C$76+0.75*(Premissas!$C$77-Premissas!$C$76))) -> 6730.9652 | J99: =MAX(0,H99-I99) -> 46583.878 | K99: =Premissas!$C$35*(1+Premissas!$C$27)^(7)/12 -> 1217.0627 | L99: =E99-F99+(I99+J99)*Premissas!$C$20*(1+Premissas!$C$26)^(7) -> 76639.416 | M99: =L99-G99-K99 -> 73167.585 | N99: =N98+M99 -> 3071348.7 | O99: =O98+M99 -> 5358848.7 | P99: =IF(AND(N99>=0,N98<0),"✅ PAYBACK","") | Q99: =I99 -> 6730.9652
A100: 8 | B100: Nov | C100: =Premissas!$C$76+0.8333333333*(Premissas!$C$77-Premissas!$C$76) -> 0.837 | D100: =(1+Premissas!$C$26)^(7) -> 1.7138243 | E100: =Dimensionador!$C$22*(Premissas!$C$76+0.8333333333*(Premissas!$C$77-Premissas!$C$76))*Premissas!$C$21*(1+Premissas!$C$26)^(7) -> 26617.05 | F100: =Dimensionador!$C$7*Premissas!$C$13*(Premissas!$C$76+0.8333333333*(Premissas!$C$77-Premissas!$C$76))*Premissas!$C$20*(1+Premissas!$C$26)^(7) -> 7207.987 | G100: =Dimensionador!$C$7*Premissas!$C$25*(1+Premissas!$C$27)^(7)/12 -> 2254.7688 | H100: =Premissas!$C$62*(1-Premissas!$C$32)^(7) -> 51595.01 | I100: =MIN(H100,Dimensionador!$C$7*Premissas!$C$13*(Premissas!$C$76+0.8333333333*(Premissas!$C$77-Premissas!$C$76))) -> 6718.9241 | J100: =MAX(0,H100-I100) -> 44876.085 | K100: =Premissas!$C$35*(1+Premissas!$C$27)^(7)/12 -> 1217.0627 | L100: =E100-F100+(I100+J100)*Premissas!$C$20*(1+Premissas!$C$26)^(7) -> 74759.614 | M100: =L100-G100-K100 -> 71287.783 | N100: =N99+M100 -> 3142636.4 | O100: =O99+M100 -> 5430136.4 | P100: =IF(AND(N100>=0,N99<0),"✅ PAYBACK","") | Q100: =I100 -> 6718.9241
A101: 8 | B101: Dez | C101: =Premissas!$C$76+0.9166666667*(Premissas!$C$77-Premissas!$C$76) -> 0.8355 | D101: =(1+Premissas!$C$26)^(7) -> 1.7138243 | E101: =Dimensionador!$C$22*(Premissas!$C$76+0.9166666667*(Premissas!$C$77-Premissas!$C$76))*Premissas!$C$21*(1+Premissas!$C$26)^(7) -> 26569.349 | F101: =Dimensionador!$C$7*Premissas!$C$13*(Premissas!$C$76+0.9166666667*(Premissas!$C$77-Premissas!$C$76))*Premissas!$C$20*(1+Premissas!$C$26)^(7) -> 7195.0695 | G101: =Dimensionador!$C$7*Premissas!$C$25*(1+Premissas!$C$27)^(7)/12 -> 2254.7688 | H101: =Premissas!$C$63*(1-Premissas!$C$32)^(7) -> 53314.843 | I101: =MIN(H101,Dimensionador!$C$7*Premissas!$C$13*(Premissas!$C$76+0.9166666667*(Premissas!$C$77-Premissas!$C$76))) -> 6706.883 | J101: =MAX(0,H101-I101) -> 46607.96 | K101: =Premissas!$C$35*(1+Premissas!$C$27)^(7)/12 -> 1217.0627 | L101: =E101-F101+(I101+J101)*Premissas!$C$20*(1+Premissas!$C$26)^(7) -> 76569.85 | M101: =L101-G101-K101 -> 73098.018 | N101: =N100+M101 -> 3215734.5 | O101: =O100+M101 -> 5503234.5 | P101: =IF(AND(N101>=0,N100<0),"✅ PAYBACK","") | Q101: =I101 -> 6706.883
...

Sheet Premissas
A1: PREMISSAS — BESS LOAD SHIFTING
A2: Azul = input editável | Verde = calculado | Vinculado ao Dimensionador
B4: EQUIPAMENTO BESS | C4: VALOR | D4: UNIDADE
B5: Potência BESS | C5: 241 | D5: kW
B6: DoD | C6: 1 | D6: p.u.
B7: η BESS round-trip | C7: 0.9556 | D7: p.u.
B8: η Elétrica | C8: 0.98 | D8: p.u.
B9: η Operacional | C9: 0.99 | D9: p.u.
B10: Dias úteis/mês | C10: 21 | D10: dias
B11: Energia útil/ciclo [calc] | C11: =C5*C6*C7*C8*C9 -> 223.43667 | D11: kWh
B12: Energia útil/mês 1 BESS [calc] | C12: =C11*C10*J12 -> 3450.0001 | D12: kWh | G12: 4692.17 | H12: =Dimensionador!C5/2 -> 3450 | J12: =H12/G12 -> 0.73526748
B13: Energia carga/mês 1 BESS [calc] | C13: =(C5*C10*C6)/(C7*C8*C9)*J12 -> 4013.6942 | D13: kWh | G13: =C13*2 -> 8027.3884
B15: TARIFAS — MERCADO LIVRE | C15: VALOR | D15: UNIDADE
B16: TUSD Fora Ponta | C16: 0.625962 | D16: R$/kWh
B17: TE Fora Ponta ML | C17: 0 | D17: R$/kWh
B18: TUSD Na Ponta | C18: 2.689175 | D18: R$/kWh
B19: TE Na Ponta ML | C19: 0 | D19: R$/kWh
B20: HFP Total [calc] | C20: =C16+C17 -> 0.625962 | D20: R$/kWh
B21: HP Total [calc] | C21: =C18+C19 -> 2.689175 | D21: R$/kWh
B22: Delta HP-HFP [calc] | C22: =C21-C20 -> 2.063213 | D22: R$/kWh
B24: PARÂMETROS FINANCEIROS | C24: VALOR | D24: UNIDADE
B25: O&M por BESS/ano | C25: =Dimensionador!C8*1% -> 11000 | D25: R$/ano
B26: Reajuste energia | C26: 0.08 | D26: % a.a.
B27: Reajuste O&M | C27: 0.03 | D27: % a.a.
B28: TMA | C28: 0.12 | D28: % a.a.
A29: ⑤ SISTEMA SOLAR FOTOVOLTAICO
B30: Potência instalada (kWp) | C30: 475 | D30: kWp | E30: Input: tamanho do sistema solar
B31: Performance Ratio (PR) | C31: 0.75 | D31: p.u. | E31: Tipicamente 75-82% para sistemas C&I
B32: Degradação painéis (a.a.) | C32: 0.005 | D32: % a.a. | E32: Tipicamente 0,5% a.a.
B33: CAPEX solar total | C33: 1187500 | D33: R$ | E33: Equipamentos + instalação + comissionamento
B34: O&M solar (% CAPEX/ano) | C34: 0.01 | D34: % a.a. | E34: Tipicamente 0,5–1,5% do CAPEX solar/ano
B35: O&M solar ano 1 (R$) | C35: =C33*C34 -> 11875 | E35: CAPEX solar × % O&M
B36: Energia solar base/dia | C36: =C30*C31 -> 356.25 | E36: kWp × PR (sem HSP)
A37: IRRADIÂNCIA — HSP MENSAL (h/dia) — preencher com dados CRESESB
B38: Janeiro | C38: 5 | D38: h/dia | E38: HSP médio de Janeiro — fonte: CRESESB / PVGIS
B39: Fevereiro | C39: 5 | D39: h/dia | E39: HSP médio de Fevereiro — fonte: CRESESB / PVGIS
B40: Março | C40: 5 | D40: h/dia | E40: HSP médio de Março — fonte: CRESESB / PVGIS
B41: Abril | C41: 5 | D41: h/dia | E41: HSP médio de Abril — fonte: CRESESB / PVGIS
B42: Maio | C42: 5 | D42: h/dia | E42: HSP médio de Maio — fonte: CRESESB / PVGIS
B43: Junho | C43: 5 | D43: h/dia | E43: HSP médio de Junho — fonte: CRESESB / PVGIS
B44: Julho | C44: 5 | D44: h/dia | E44: HSP médio de Julho — fonte: CRESESB / PVGIS
B45: Agosto | C45: 5 | D45: h/dia | E45: HSP médio de Agosto — fonte: CRESESB / PVGIS
B46: Setembro | C46: 5 | D46: h/dia | E46: HSP médio de Setembro — fonte: CRESESB / PVGIS
B47: Outubro | C47: 5 | D47: h/dia | E47: HSP médio de Outubro — fonte: CRESESB / PVGIS
B48: Novembro | C48: 5 | D48: h/dia | E48: HSP médio de Novembro — fonte: CRESESB / PVGIS
B49: Dezembro | C49: 5 | D49: h/dia | E49: HSP médio de Dezembro — fonte: CRESESB / PVGIS
B50: HSP médio anual [calc] | C50: =AVERAGE(C38:C49) -> 5 | D50: h/dia
A51: GERAÇÃO SOLAR ESTIMADA (kWh/mês) — calculada automaticamente
B52: Janeiro | C52: =C30*C38*C31*31 -> 55218.75 | D52: kWh/mês
B53: Fevereiro | C53: =C30*C39*C31*28 -> 49875 | D53: kWh/mês
B54: Março | C54: =C30*C40*C31*31 -> 55218.75 | D54: kWh/mês
B55: Abril | C55: =C30*C41*C31*30 -> 53437.5 | D55: kWh/mês
B56: Maio | C56: =C30*C42*C31*31 -> 55218.75 | D56: kWh/mês
B57: Junho | C57: =C30*C43*C31*30 -> 53437.5 | D57: kWh/mês
B58: Julho | C58: =C30*C44*C31*31 -> 55218.75 | D58: kWh/mês
B59: Agosto | C59: =C30*C45*C31*31 -> 55218.75 | D59: kWh/mês
B60: Setembro | C60: =C30*C46*C31*30 -> 53437.5 | D60: kWh/mês
B61: Outubro | C61: =C30*C47*C31*31 -> 55218.75 | D61: kWh/mês
B62: Novembro | C62: =C30*C48*C31*30 -> 53437.5 | D62: kWh/mês
B63: Dezembro | C63: =C30*C49*C31*31 -> 55218.75 | D63: kWh/mês
B64: Geração total anual [calc] | C64: =SUM(C52:C63) -> 650156.25 | D64: kWh/ano
B65: Geração média mensal [calc] | C65: =C64/12 -> 54179.688 | D65: kWh/mês
B68: CURVA SOH HUAWEI (1 ciclo/dia, DoD 100%) | C68: SOH | D68: Ano
B69: Ano 0 | C69: 1 | D69: 0
B70: Ano 1 | C70: 0.971 | D70: 1
B71: Ano 2 | C71: 0.948 | D71: 2
B72: Ano 3 | C72: 0.927 | D72: 3
B73: Ano 4 | C73: 0.907 | D73: 4
B74: Ano 5 | C74: 0.888 | D74: 5
B75: Ano 6 | C75: 0.87 | D75: 6
B76: Ano 7 | C76: 0.852 | D76: 7
B77: Ano 8 | C77: 0.834 | D77: 8
B78: Ano 9 | C78: 0.817 | D78: 9
B79: Ano 10 | C79: 0.799 | D79: 10
B80: Ano 11 | C80: 0.783 | D80: 11
... B89: Ano 20 | C89: 0.645 | D89: 20
