Workbook

Sheet Dimensionador
A1: DIMENSIONADOR DE BESS | SECRETARIA DE INFRA ESTRUTURA | LOAD SHIFTING
A2: Preencha as células em AZUL. A planilha calcula o número sugerido e todos os indicadores.
A4: ① ENTRADA: CONSUMO E DIMENSIONAMENTO
B5: Consumo médio de ponta desejado | C5: 2350 | D5: kWh/mês | E5: Média mensal de energia a deslocar do HP para HFP
B6: ⟹ Nº sugerido de BESS (calculado) | C6: =CEILING(C5/(Premissas!$C$12),1) -> 1 | D6: unidades | E6: Arredondamento para cima (energia útil 1 BESS = C12 da aba Premissas)
B7: ✏️ Nº de BESS adotado (você define) | C7: 1 | D7: unidades | E7: ⬅ EDITE AQUI: confirme ou altere o número sugerido acima
B8: CAPEX total negociado (todos os BESS) | C8: 520000 | D8: R$ | E8: Valor total com instalação, frete e comissionamento
A10: ② PARÂMETROS DO EQUIPAMENTO (vinculados à aba Premissas)
B11: Potência nominal | C11: =Premissas!C5 -> 241 | D11: kW
B12: DoD | C12: =Premissas!C6 -> 1 | D12: p.u.
B13: η BESS round-trip | C13: =Premissas!C7 -> 0.9556 | D13: p.u.
B14: η Elétrica | C14: =Premissas!C8 -> 0.98 | D14: p.u.
B15: η Operacional | C15: =Premissas!C9 -> 0.99 | D15: p.u.
B16: Dias úteis/mês | C16: =Premissas!C10 -> 21 | D16: dias
B17: Energia útil/ciclo | C17: =Premissas!C11 -> 223.43667 | D17: kWh/ciclo
B18: Energia útil/mês 1 BESS | C18: =Premissas!C12 -> 4692.1701 | D18: kWh/mês
B19: Energia carga/mês 1 BESS | C19: =Premissas!C13 -> 5458.8219 | D19: kWh/mês
A21: ③ ENERGIA CALCULADA COM O Nº DE BESS ADOTADO
B22: Energia útil/mês (N BESS) | C22: =$C$7*Premissas!$C$12 -> 4692.1701 | E22: N BESS × energia útil 1 BESS
B23: Energia carga/mês (N BESS) | C23: =$C$7*Premissas!$C$13 -> 5458.8219 | E23: N BESS × energia de carga 1 BESS
B24: Cobertura do consumo desejado | C24: =C22/C5 -> 1.9966681 | E24: Energia disponível ÷ consumo de ponta médio
B25: Receita HP ano 1 (base) | C25: =C22*Premissas!$C$21*12 -> 165154.91 | E25: Energia útil × tarifa HP × 12 meses
B26: Custo HFP ano 1 (base) | C26: =C23*Premissas!$C$20*12 -> 8020.0747 | E26: Energia de carga × tarifa HFP × 12 meses
B27: Economia bruta ano 1 (base) | C27: =C25-C26 -> 157134.83 | E27: Receita HP − Custo HFP (sem degradação)
B28: O&M ano 1 (N BESS) | C28: =Premissas!$C$25 -> 7800 | E28: N BESS × O&M unitário
B29: Economia líquida ano 1 (base) | C29: =C27-C28 -> 149334.83 | E29: Após O&M, sem degradação ainda
A31: ④ TARIFAS (vinculadas à aba Premissas)
B32: Tarifa HFP total | C32: =Premissas!$C$20 -> 0.12243293
B33: Tarifa HP total | C33: =Premissas!$C$21 -> 2.933165
B34: Delta HP − HFP | C34: =Premissas!$C$22 -> 2.810732
B35: Reajuste tarifário anual | C35: =Premissas!$C$26 -> 0.08
A37: ⑤ INDICADORES FINANCEIROS — RESULTADO FINAL
B38: VPL (TMA Premissas) | C38: ='Fluxo 20 Anos'!C249 -> 1088598.1
B39: TIR (a.a.) | C39: ='Fluxo 20 Anos'!C250 -> 0.33737693
B40: Payback (anos) | C40: ='Fluxo 20 Anos'!C252 -> 3.3098908
B41: Payback (meses) | C41: ='Fluxo 20 Anos'!C251 -> 39.71869
B42: Acumulado Ano 20 | C42: ='Fluxo 20 Anos'!C253 -> 4765590.3
B43: Economia Total 20 anos (líq.) | C43: ='Fluxo 20 Anos'!C254 -> 5285590.3
B45: TMA utilizada no VPL: ver Premissas (célula C31) | Reajuste O&M: C30 | Horizonte: 20 anos

Sheet Fluxo 20 Anos
A1: FLUXO DE CAIXA — MÊS A MÊS — 20 ANOS | N BESS DINÂMICO
A2: SOH interpolado mensalmente | Reajuste tarifário anual | Degradação contínua ao longo dos 240 meses
A4: Ano | B4: Mês | C4: SOH Mês | D4: Reajuste Tarifário | E4: Receita HP (R$) | F4: Custo HFP (R$) | G4: O&M (R$/mês) | H4: Eco. Bruta (R$/mês) | I4: Eco. Líq. (R$/mês) | J4: Acumulado (R$) | K4: Eco. Acum. (sem CAPEX) | L4: Ref. Ponto Equilíbrio
A5: 0 | B5: Invest. | I5: =-Dimensionador!$C$8 -> -520000 | J5: =-Dimensionador!$C$8 -> -520000 | K5: =0 -> 0 | M5: =-Dimensionador!$C$8 -> -520000 | N5: =-Dimensionador!$C$8 -> -520000
A6: 1 | B6: Jan | C6: =Premissas!$C$31+0*(Premissas!$C$32-Premissas!$C$31) -> 1 | D6: =(1+Premissas!$C$26)^(0) -> 1 | E6: =Dimensionador!$C$22*(Premissas!$C$31+0*(Premissas!$C$32-Premissas!$C$31))*Premissas!$C$21*(1+Premissas!$C$26)^(0) -> 13762.909 | F6: =Dimensionador!$C$23*(Premissas!$C$31+0*(Premissas!$C$32-Premissas!$C$31))*Premissas!$C$20*(1+Premissas!$C$26)^(0) -> 668.33956 | G6: =Premissas!$C$25*(1+Premissas!$C$27)^(0)/12 -> 650 | H6: =E6-F6 -> 13094.569 | I6: =H6-G6 -> 12444.569 | J6: =J5+I6 -> -507555.43 | K6: =I6 -> 12444.569 | L6: "" | M6: =I6 -> 12444.569 | N6: =SUM(I6:I17) -> 147246.25
A7: 1 | B7: Fev | C7: =Premissas!$C$31+0.0833333333*(Premissas!$C$32-Premissas!$C$31) -> 0.99758333 | D7: =(1+Premissas!$C$26)^(0) -> 1 | E7: =Dimensionador!$C$22*(Premissas!$C$31+0.0833333333*(Premissas!$C$32-Premissas!$C$31))*Premissas!$C$21*(1+Premissas!$C$26)^(0) -> 13729.649 | F7: =Dimensionador!$C$23*(Premissas!$C$31+0.0833333333*(Premissas!$C$32-Premissas!$C$31))*Premissas!$C$20*(1+Premissas!$C$26)^(0) -> 666.72441 | G7: =Premissas!$C$25*(1+Premissas!$C$27)^(0)/12 -> 650 | H7: =E7-F7 -> 13062.924 | I7: =H7-G7 -> 12412.924 | J7: =J6+I7 -> -495142.51 | K7: =K6+I7 -> 24857.494 | L7: =IF(AND(J7>=0,J6<0),"✅ PAYBACK","") | M7: =I7 -> 12412.924 | N7: =SUM(I18:I29) -> 154961.18
A8: 1 | B8: Mar | C8: =Premissas!$C$31+0.1666666667*(Premissas!$C$32-Premissas!$C$31) -> 0.99516667 | D8: =(1+Premissas!$C$26)^(0) -> 1 | E8: =Dimensionador!$C$22*(Premissas!$C$31+0.1666666667*(Premissas!$C$32-Premissas!$C$31))*Premissas!$C$21*(1+Premissas!$C$26)^(0) -> 13696.388 | F8: =Dimensionador!$C$23*(Premissas!$C$31+0.1666666667*(Premissas!$C$32-Premissas!$C$31))*Premissas!$C$20*(1+Premissas!$C$26)^(0) -> 665.10925 | G8: =Premissas!$C$25*(1+Premissas!$C$27)^(0)/12 -> 650 | H8: =E8-F8 -> 13031.279 | I8: =H8-G8 -> 12381.279 | J8: =J7+I8 -> -482761.23 | K8: =K7+I8 -> 37238.773 | L8: =IF(AND(J8>=0,J7<0),"✅ PAYBACK","") | M8: =I8 -> 12381.279 | N8: =SUM(I30:I41) -> 163712.29
A9: 1 | B9: Abr | C9: =Premissas!$C$31+0.25*(Premissas!$C$32-Premissas!$C$31) -> 0.99275 | D9: =(1+Premissas!$C$26)^(0) -> 1 | E9: =Dimensionador!$C$22*(Premissas!$C$31+0.25*(Premissas!$C$32-Premissas!$C$31))*Premissas!$C$21*(1+Premissas!$C$26)^(0) -> 13663.128 | F9: =Dimensionador!$C$23*(Premissas!$C$31+0.25*(Premissas!$C$32-Premissas!$C$31))*Premissas!$C$20*(1+Premissas!$C$26)^(0) -> 663.4941 | G9: =Premissas!$C$25*(1+Premissas!$C$27)^(0)/12 -> 650 | H9: =E9-F9 -> 12999.634 | I9: =H9-G9 -> 12349.634 | J9: =J8+I9 -> -470411.59 | K9: =K8+I9 -> 49588.407 | L9: =IF(AND(J9>=0,J8<0),"✅ PAYBACK","") | M9: =I9 -> 12349.634 | N9: =SUM(I42:I53) -> 173156.91
A10: 1 | B10: Mai | C10: =Premissas!$C$31+0.3333333333*(Premissas!$C$32-Premissas!$C$31) -> 0.99033333 | D10: =(1+Premissas!$C$26)^(0) -> 1 | E10: =Dimensionador!$C$22*(Premissas!$C$31+0.3333333333*(Premissas!$C$32-Premissas!$C$31))*Premissas!$C$21*(1+Premissas!$C$26)^(0) -> 13629.868 | F10: =Dimensionador!$C$23*(Premissas!$C$31+0.3333333333*(Premissas!$C$32-Premissas!$C$31))*Premissas!$C$20*(1+Premissas!$C$26)^(0) -> 661.87894 | G10: =Premissas!$C$25*(1+Premissas!$C$27)^(0)/12 -> 650 | H10: =E10-F10 -> 12967.989 | I10: =H10-G10 -> 12317.989 | J10: =J9+I10 -> -458093.6 | K10: =K9+I10 -> 61906.395 | L10: =IF(AND(J10>=0,J9<0),"✅ PAYBACK","") | M10: =I10 -> 12317.989 | N10: =SUM(I54:I65) -> 183258.01
A11: 1 | B11: Jun | C11: =Premissas!$C$31+0.4166666667*(Premissas!$C$32-Premissas!$C$31) -> 0.98791667 | D11: =(1+Premissas!$C$26)^(0) -> 1 | E11: =Dimensionador!$C$22*(Premissas!$C$31+0.4166666667*(Premissas!$C$32-Premissas!$C$31))*Premissas!$C$21*(1+Premissas!$C$26)^(0) -> 13596.607 | F11: =Dimensionador!$C$23*(Premissas!$C$31+0.4166666667*(Premissas!$C$32-Premissas!$C$31))*Premissas!$C$20*(1+Premissas!$C$26)^(0) -> 660.26379 | G11: =Premissas!$C$25*(1+Premissas!$C$27)^(0)/12 -> 650 | H11: =E11-F11 -> 12936.343 | I11: =H11-G11 -> 12286.343 | J11: =J10+I11 -> -445807.26 | K11: =K10+I11 -> 74192.739 | L11: =IF(AND(J11>=0,J10<0),"✅ PAYBACK","") | M11: =I11 -> 12286.343 | N11: =SUM(I66:I77) -> 194076.65
A12: 1 | B12: Jul | C12: =Premissas!$C$31+0.5*(Premissas!$C$32-Premissas!$C$31) -> 0.9855 | D12: =(1+Premissas!$C$26)^(0) -> 1 | E12: =Dimensionador!$C$22*(Premissas!$C$31+0.5*(Premissas!$C$32-Premissas!$C$31))*Premissas!$C$21*(1+Premissas!$C$26)^(0) -> 13563.347 | F12: =Dimensionador!$C$23*(Premissas!$C$31+0.5*(Premissas!$C$32-Premissas!$C$31))*Premissas!$C$20*(1+Premissas!$C$26)^(0) -> 658.64864 | G12: =Premissas!$C$25*(1+Premissas!$C$27)^(0)/12 -> 650 | H12: =E12-F12 -> 12904.698 | I12: =H12-G12 -> 12254.698 | J12: =J11+I12 -> -433552.56 | K12: =K11+I12 -> 86447.437 | L12: =IF(AND(J12>=0,J11<0),"✅ PAYBACK","") | M12: =I12 -> 12254.698 | N12: =SUM(I78:I89) -> 205566.54
A13: 1 | B13: Ago | C13: =Premissas!$C$31+0.5833333333*(Premissas!$C$32-Premissas!$C$31) -> 0.98308333 | D13: =(1+Premissas!$C$26)^(0) -> 1 | E13: =Dimensionador!$C$22*(Premissas!$C$31+0.5833333333*(Premissas!$C$32-Premissas!$C$31))*Premissas!$C$21*(1+Premissas!$C$26)^(0) -> 13530.087 | F13: =Dimensionador!$C$23*(Premissas!$C$31+0.5833333333*(Premissas!$C$32-Premissas!$C$31))*Premissas!$C$20*(1+Premissas!$C$26)^(0) -> 657.03348 | G13: =Premissas!$C$25*(1+Premissas!$C$27)^(0)/12 -> 650 | H13: =E13-F13 -> 12873.053 | I13: =H13-G13 -> 12223.053 | J13: =J12+I13 -> -421329.51 | K13: =K12+I13 -> 98670.49 | L13: =IF(AND(J13>=0,J12<0),"✅ PAYBACK","") | M13: =I13 -> 12223.053 | N13: =SUM(I90:I101) -> 217630.12
A14: 1 | B14: Set | C14: =Premissas!$C$31+0.6666666667*(Premissas!$C$32-Premissas!$C$31) -> 0.98066667 | D14: =(1+Premissas!$C$26)^(0) -> 1 | E14: =Dimensionador!$C$22*(Premissas!$C$31+0.6666666667*(Premissas!$C$32-Premissas!$C$31))*Premissas!$C$21*(1+Premissas!$C$26)^(0) -> 13496.826 | F14: =Dimensionador!$C$23*(Premissas!$C$31+0.6666666667*(Premissas!$C$32-Premissas!$C$31))*Premissas!$C$20*(1+Premissas!$C$26)^(0) -> 655.41833 | G14: =Premissas!$C$25*(1+Premissas!$C$27)^(0)/12 -> 650 | H14: =E14-F14 -> 12841.408 | I14: =H14-G14 -> 12191.408 | J14: =J13+I14 -> -409138.1 | K14: =K13+I14 -> 110861.9 | L14: =IF(AND(J14>=0,J13<0),"✅ PAYBACK","") | M14: =I14 -> 12191.408 | N14: =SUM(I102:I113) -> 230418.26
A15: 1 | B15: Out | C15: =Premissas!$C$31+0.75*(Premissas!$C$32-Premissas!$C$31) -> 0.97825 | D15: =(1+Premissas!$C$26)^(0) -> 1 | E15: =Dimensionador!$C$22*(Premissas!$C$31+0.75*(Premissas!$C$32-Premissas!$C$31))*Premissas!$C$21*(1+Premissas!$C$26)^(0) -> 13463.566 | F15: =Dimensionador!$C$23*(Premissas!$C$31+0.75*(Premissas!$C$32-Premissas!$C$31))*Premissas!$C$20*(1+Premissas!$C$26)^(0) -> 653.80318 | G15: =Premissas!$C$25*(1+Premissas!$C$27)^(0)/12 -> 650 | H15: =E15-F15 -> 12809.763 | I15: =H15-G15 -> 12159.763 | J15: =J14+I15 -> -396978.34 | K15: =K14+I15 -> 123021.66 | L15: =IF(AND(J15>=0,J14<0),"✅ PAYBACK","") | M15: =I15 -> 12159.763 | N15: =SUM(I114:I125) -> 243861.87
A16: 1 | B16: Nov | C16: =Premissas!$C$31+0.8333333333*(Premissas!$C$32-Premissas!$C$31) -> 0.97583333 | D16: =(1+Premissas!$C$26)^(0) -> 1 | E16: =Dimensionador!$C$22*(Premissas!$C$31+0.8333333333*(Premissas!$C$32-Premissas!$C$31))*Premissas!$C$21*(1+Premissas!$C$26)^(0) -> 13430.305 | F16: =Dimensionador!$C$23*(Premissas!$C$31+0.8333333333*(Premissas!$C$32-Premissas!$C$31))*Premissas!$C$20*(1+Premissas!$C$26)^(0) -> 652.18802 | G16: =Premissas!$C$25*(1+Premissas!$C$27)^(0)/12 -> 650 | H16: =E16-F16 -> 12778.117 | I16: =H16-G16 -> 12128.117 | J16: =J15+I16 -> -384850.22 | K16: =K15+I16 -> 135149.78 | L16: =IF(AND(J16>=0,J15<0),"✅ PAYBACK","") | M16: =I16 -> 12128.117 | N16: =SUM(I126:I137) -> 258084.29
A17: 1 | B17: Dez | C17: =Premissas!$C$31+0.9166666667*(Premissas!$C$32-Premissas!$C$31) -> 0.97341667 | D17: =(1+Premissas!$C$26)^(0) -> 1 | E17: =Dimensionador!$C$22*(Premissas!$C$31+0.9166666667*(Premissas!$C$32-Premissas!$C$31))*Premissas!$C$21*(1+Premissas!$C$26)^(0) -> 13397.045 | F17: =Dimensionador!$C$23*(Premissas!$C$31+0.9166666667*(Premissas!$C$32-Premissas!$C$31))*Premissas!$C$20*(1+Premissas!$C$26)^(0) -> 650.57287 | G17: =Premissas!$C$25*(1+Premissas!$C$27)^(0)/12 -> 650 | H17: =E17-F17 -> 12746.472 | I17: =H17-G17 -> 12096.472 | J17: =J16+I17 -> -372753.75 | K17: =K16+I17 -> 147246.25 | L17: =IF(AND(J17>=0,J16<0),"✅ PAYBACK","") | M17: =I17 -> 12096.472 | N17: =SUM(I138:I149) -> 273225.13
A18: 2 | B18: Jan | C18: =Premissas!$C$32+0*(Premissas!$C$33-Premissas!$C$32) -> 0.971 | D18: =(1+Premissas!$C$26)^(1) -> 1.08 | E18: =Dimensionador!$C$22*(Premissas!$C$32+0*(Premissas!$C$33-Premissas!$C$32))*Premissas!$C$21*(1+Premissas!$C$26)^(1) -> 14432.887 | F18: =Dimensionador!$C$23*(Premissas!$C$32+0*(Premissas!$C$33-Premissas!$C$32))*Premissas!$C$20*(1+Premissas!$C$26)^(1) -> 700.87433 | G18: =Premissas!$C$25*(1+Premissas!$C$27)^(1)/12 -> 669.5 | H18: =E18-F18 -> 13732.013 | I18: =H18-G18 -> 13062.513 | J18: =J17+I18 -> -359691.24 | K18: =K17+I18 -> 160308.76 | L18: =IF(AND(J18>=0,J17<0),"✅ PAYBACK","") | M18: =I18 -> 13062.513 | N18: =SUM(I150:I161) -> 289077.58
A19: 2 | B19: Fev | C19: =Premissas!$C$32+0.0833333333*(Premissas!$C$33-Premissas!$C$32) -> 0.96908333 | D19: =(1+Premissas!$C$26)^(1) -> 1.08 | E19: =Dimensionador!$C$22*(Premissas!$C$32+0.0833333333*(Premissas!$C$33-Premissas!$C$32))*Premissas!$C$21*(1+Premissas!$C$26)^(1) -> 14404.398 | F19: =Dimensionador!$C$23*(Premissas!$C$32+0.0833333333*(Premissas!$C$33-Premissas!$C$32))*Premissas!$C$20*(1+Premissas!$C$26)^(1) -> 699.49087 | G19: =Premissas!$C$25*(1+Premissas!$C$27)^(1)/12 -> 669.5 | H19: =E19-F19 -> 13704.907 | I19: =H19-G19 -> 13035.407 | J19: =J18+I19 -> -346655.83 | K19: =K18+I19 -> 173344.17 | L19: =IF(AND(J19>=0,J18<0),"✅ PAYBACK","") | M19: =I19 -> 13035.407 | N19: =SUM(I162:I173) -> 305922.27
A20: 2 | B20: Mar | C20: =Premissas!$C$32+0.1666666667*(Premissas!$C$33-Premissas!$C$32) -> 0.96716667 | D20: =(1+Premissas!$C$26)^(1) -> 1.08 | E20: =Dimensionador!$C$22*(Premissas!$C$32+0.1666666667*(Premissas!$C$33-Premissas!$C$32))*Premissas!$C$21*(1+Premissas!$C$26)^(1) -> 14375.909 | F20: =Dimensionador!$C$23*(Premissas!$C$32+0.1666666667*(Premissas!$C$33-Premissas!$C$32))*Premissas!$C$20*(1+Premissas!$C$26)^(1) -> 698.1074 | G20: =Premissas!$C$25*(1+Premissas!$C$27)^(1)/12 -> 669.5 | H20: =E20-F20 -> 13677.802 | I20: =H20-G20 -> 13008.302 | J20: =J19+I20 -> -333647.53 | K20: =K19+I20 -> 186352.47 | L20: =IF(AND(J20>=0,J19<0),"✅ PAYBACK","") | M20: =I20 -> 13008.302 | N20: =SUM(I174:I185) -> 323584.21
A21: 2 | B21: Abr | C21: =Premissas!$C$32+0.25*(Premissas!$C$33-Premissas!$C$32) -> 0.96525 | D21: =(1+Premissas!$C$26)^(1) -> 1.08 | E21: =Dimensionador!$C$22*(Premissas!$C$32+0.25*(Premissas!$C$33-Premissas!$C$32))*Premissas!$C$21*(1+Premissas!$C$26)^(1) -> 14347.42 | F21: =Dimensionador!$C$23*(Premissas!$C$32+0.25*(Premissas!$C$33-Premissas!$C$32))*Premissas!$C$20*(1+Premissas!$C$26)^(1) -> 696.72394 | G21: =Premissas!$C$25*(1+Premissas!$C$27)^(1)/12 -> 669.5 | H21: =E21-F21 -> 13650.696 | I21: =H21-G21 -> 12981.196 | J21: =J20+I21 -> -320666.33 | K21: =K20+I21 -> 199333.67 | L21: =IF(AND(J21>=0,J20<0),"✅ PAYBACK","") | M21: =I21 -> 12981.196 | N21: =SUM(I186:I197) -> 342313.99
A22: 2 | B22: Mai | C22: =Premissas!$C$32+0.3333333333*(Premissas!$C$33-Premissas!$C$32) -> 0.96333333 | D22: =(1+Premissas!$C$26)^(1) -> 1.08 | E22: =Dimensionador!$C$22*(Premissas!$C$32+0.3333333333*(Premissas!$C$33-Premissas!$C$32))*Premissas!$C$21*(1+Premissas!$C$26)^(1) -> 14318.931 | F22: =Dimensionador!$C$23*(Premissas!$C$32+0.3333333333*(Premissas!$C$33-Premissas!$C$32))*Premissas!$C$20*(1+Premissas!$C$26)^(1) -> 695.34048 | G22: =Premissas!$C$25*(1+Premissas!$C$27)^(1)/12 -> 669.5 | H22: =E22-F22 -> 13623.59 | I22: =H22-G22 -> 12954.09 | J22: =J21+I22 -> -307712.24 | K22: =K21+I22 -> 212287.76 | L22: =IF(AND(J22>=0,J21<0),"✅ PAYBACK","") | M22: =I22 -> 12954.09 | N22: =SUM(I198:I209) -> 362231.69
A23: 2 | B23: Jun | C23: =Premissas!$C$32+0.4166666667*(Premissas!$C$33-Premissas!$C$32) -> 0.96141667 | D23: =(1+Premissas!$C$26)^(1) -> 1.08 | E23: =Dimensionador!$C$22*(Premissas!$C$32+0.4166666667*(Premissas!$C$33-Premissas!$C$32))*Premissas!$C$21*(1+Premissas!$C$26)^(1) -> 14290.441 | F23: =Dimensionador!$C$23*(Premissas!$C$32+0.4166666667*(Premissas!$C$33-Premissas!$C$32))*Premissas!$C$20*(1+Premissas!$C$26)^(1) -> 693.95702 | G23: =Premissas!$C$25*(1+Premissas!$C$27)^(1)/12 -> 669.5 | H23: =E23-F23 -> 13596.484 | I23: =H23-G23 -> 12926.984 | J23: =J22+I23 -> -294785.26 | K23: =K22+I23 -> 225214.74 | L23: =IF(AND(J23>=0,J22<0),"✅ PAYBACK","") | M23: =I23 -> 12926.984 | N23: =SUM(I210:I221) -> 383115.04
A24: 2 | B24: Jul | C24: =Premissas!$C$32+0.5*(Premissas!$C$33-Premissas!$C$32) -> 0.9595 | D24: =(1+Premissas!$C$26)^(1) -> 1.08 | E24: =Dimensionador!$C$22*(Premissas!$C$32+0.5*(Premissas!$C$33-Premissas!$C$32))*Premissas!$C$21*(1+Premissas!$C$26)^(1) -> 14261.952 | F24: =Dimensionador!$C$23*(Premissas!$C$32+0.5*(Premissas!$C$33-Premissas!$C$32))*Premissas!$C$20*(1+Premissas!$C$26)^(1) -> 692.57355 | G24: =Premissas!$C$25*(1+Premissas!$C$27)^(1)/12 -> 669.5 | H24: =E24-F24 -> 13569.379 | I24: =H24-G24 -> 12899.879 | J24: =J23+I24 -> -281885.38 | K24: =K23+I24 -> 238114.62 | L24: =IF(AND(J24>=0,J23<0),"✅ PAYBACK","") | M24: =I24 -> 12899.879 | N24: =SUM(I222:I233) -> 405277.94
A25: 2 | B25: Ago | C25: =Premissas!$C$32+0.5833333333*(Premissas!$C$33-Premissas!$C$32) -> 0.95758333 | D25: =(1+Premissas!$C$26)^(1) -> 1.08 | E25: =Dimensionador!$C$22*(Premissas!$C$32+0.5833333333*(Premissas!$C$33-Premissas!$C$32))*Premissas!$C$21*(1+Premissas!$C$26)^(1) -> 14233.463 | F25: =Dimensionador!$C$23*(Premissas!$C$32+0.5833333333*(Premissas!$C$33-Premissas!$C$32))*Premissas!$C$20*(1+Premissas!$C$26)^(1) -> 691.19009 | G25: =Premissas!$C$25*(1+Premissas!$C$27)^(1)/12 -> 669.5 | H25: =E25-F25 -> 13542.273 | I25: =H25-G25 -> 12872.773 | J25: =J24+I25 -> -269012.61 | K25: =K24+I25 -> 250987.39 | L25: =IF(AND(J25>=0,J24<0),"✅ PAYBACK","") | M25: =I25 -> 12872.773 | N25: =SUM(I234:I245) -> 428870.06
A26: 2 | B26: Set | C26: =Premissas!$C$32+0.6666666667*(Premissas!$C$33-Premissas!$C$32) -> 0.95566667 | D26: =(1+Premissas!$C$26)^(1) -> 1.08 | E26: =Dimensionador!$C$22*(Premissas!$C$32+0.6666666667*(Premissas!$C$33-Premissas!$C$32))*Premissas!$C$21*(1+Premissas!$C$26)^(1) -> 14204.974 | F26: =Dimensionador!$C$23*(Premissas!$C$32+0.6666666667*(Premissas!$C$33-Premissas!$C$32))*Premissas!$C$20*(1+Premissas!$C$26)^(1) -> 689.80663 | G26: =Premissas!$C$25*(1+Premissas!$C$27)^(1)/12 -> 669.5 | H26: =E26-F26 -> 13515.167 | I26: =H26-G26 -> 12845.667 | J26: =J25+I26 -> -256166.94 | K26: =K25+I26 -> 263833.06 | L26: =IF(AND(J26>=0,J25<0),"✅ PAYBACK","") | M26: =I26 -> 12845.667
A27: 2 | B27: Out | C27: =Premissas!$C$32+0.75*(Premissas!$C$33-Premissas!$C$32) -> 0.95375 | D27: =(1+Premissas!$C$26)^(1) -> 1.08 | E27: =Dimensionador!$C$22*(Premissas!$C$32+0.75*(Premissas!$C$33-Premissas!$C$32))*Premissas!$C$21*(1+Premissas!$C$26)^(1) -> 14176.484 | F27: =Dimensionador!$C$23*(Premissas!$C$32+0.75*(Premissas!$C$33-Premissas!$C$32))*Premissas!$C$20*(1+Premissas!$C$26)^(1) -> 688.42316 | G27: =Premissas!$C$25*(1+Premissas!$C$27)^(1)/12 -> 669.5 | H27: =E27-F27 -> 13488.061 | I27: =H27-G27 -> 12818.561 | J27: =J26+I27 -> -243348.38 | K27: =K26+I27 -> 276651.62 | L27: =IF(AND(J27>=0,J26<0),"✅ PAYBACK","") | M27: =I27 -> 12818.561
A28: 2 | B28: Nov | C28: =Premissas!$C$32+0.8333333333*(Premissas!$C$33-Premissas!$C$32) -> 0.95183333 | D28: =(1+Premissas!$C$26)^(1) -> 1.08 | E28: =Dimensionador!$C$22*(Premissas!$C$32+0.8333333333*(Premissas!$C$33-Premissas!$C$32))*Premissas!$C$21*(1+Premissas!$C$26)^(1) -> 14147.995 | F28: =Dimensionador!$C$23*(Premissas!$C$32+0.8333333333*(Premissas!$C$33-Premissas!$C$32))*Premissas!$C$20*(1+Premissas!$C$26)^(1) -> 687.0397 | G28: =Premissas!$C$25*(1+Premissas!$C$27)^(1)/12 -> 669.5 | H28: =E28-F28 -> 13460.956 | I28: =H28-G28 -> 12791.456 | J28: =J27+I28 -> -230556.92 | K28: =K27+I28 -> 289443.08 | L28: =IF(AND(J28>=0,J27<0),"✅ PAYBACK","") | M28: =I28 -> 12791.456
A29: 2 | B29: Dez | C29: =Premissas!$C$32+0.9166666667*(Premissas!$C$33-Premissas!$C$32) -> 0.94991667 | D29: =(1+Premissas!$C$26)^(1) -> 1.08 | E29: =Dimensionador!$C$22*(Premissas!$C$32+0.9166666667*(Premissas!$C$33-Premissas!$C$32))*Premissas!$C$21*(1+Premissas!$C$26)^(1) -> 14119.506 | F29: =Dimensionador!$C$23*(Premissas!$C$32+0.9166666667*(Premissas!$C$33-Premissas!$C$32))*Premissas!$C$20*(1+Premissas!$C$26)^(1) -> 685.65624 | G29: =Premissas!$C$25*(1+Premissas!$C$27)^(1)/12 -> 669.5 | H29: =E29-F29 -> 13433.85 | I29: =H29-G29 -> 12764.35 | J29: =J28+I29 -> -217792.57 | K29: =K28+I29 -> 302207.43 | L29: =IF(AND(J29>=0,J28<0),"✅ PAYBACK","") | M29: =I29 -> 12764.35
A30: 3 | B30: Jan | C30: =Premissas!$C$33+0*(Premissas!$C$34-Premissas!$C$33) -> 0.948 | D30: =(1+Premissas!$C$26)^(2) -> 1.1664 | E30: =Dimensionador!$C$22*(Premissas!$C$33+0*(Premissas!$C$34-Premissas!$C$33))*Premissas!$C$21*(1+Premissas!$C$26)^(2) -> 15218.298 | F30: =Dimensionador!$C$23*(Premissas!$C$33+0*(Premissas!$C$34-Premissas!$C$33))*Premissas!$C$20*(1+Premissas!$C$26)^(2) -> 739.0146 | G30: =Premissas!$C$25*(1+Premissas!$C$27)^(2)/12 -> 689.585 | H30: =E30-F30 -> 14479.284 | I30: =H30-G30 -> 13789.699 | J30: =J29+I30 -> -204002.87 | K30: =K29+I30 -> 315997.13 | L30: =IF(AND(J30>=0,J29<0),"✅ PAYBACK","") | M30: =I30 -> 13789.699
A31: 3 | B31: Fev | C31: =Premissas!$C$33+0.0833333333*(Premissas!$C$34-Premissas!$C$33) -> 0.94625 | D31: =(1+Premissas!$C$26)^(2) -> 1.1664 | E31: =Dimensionador!$C$22*(Premissas!$C$33+0.0833333333*(Premissas!$C$34-Premissas!$C$33))*Premissas!$C$21*(1+Premissas!$C$26)^(2) -> 15190.205 | F31: =Dimensionador!$C$23*(Premissas!$C$33+0.0833333333*(Premissas!$C$34-Premissas!$C$33))*Premissas!$C$20*(1+Premissas!$C$26)^(2) -> 737.65038 | G31: =Premissas!$C$25*(1+Premissas!$C$27)^(2)/12 -> 689.585 | H31: =E31-F31 -> 14452.555 | I31: =H31-G31 -> 13762.97 | J31: =J30+I31 -> -190239.9 | K31: =K30+I31 -> 329760.1 | L31: =IF(AND(J31>=0,J30<0),"✅ PAYBACK","") | M31: =I31 -> 13762.97
A32: 3 | B32: Mar | C32: =Premissas!$C$33+0.1666666667*(Premissas!$C$34-Premissas!$C$33) -> 0.9445 | D32: =(1+Premissas!$C$26)^(2) -> 1.1664 | E32: =Dimensionador!$C$22*(Premissas!$C$33+0.1666666667*(Premissas!$C$34-Premissas!$C$33))*Premissas!$C$21*(1+Premissas!$C$26)^(2) -> 15162.112 | F32: =Dimensionador!$C$23*(Premissas!$C$33+0.1666666667*(Premissas!$C$34-Premissas!$C$33))*Premissas!$C$20*(1+Premissas!$C$26)^(2) -> 736.28617 | G32: =Premissas!$C$25*(1+Premissas!$C$27)^(2)/12 -> 689.585 | H32: =E32-F32 -> 14425.826 | I32: =H32-G32 -> 13736.241 | J32: =J31+I32 -> -176503.66 | K32: =K31+I32 -> 343496.34 | L32: =IF(AND(J32>=0,J31<0),"✅ PAYBACK","") | M32: =I32 -> 13736.241
A33: 3 | B33: Abr | C33: =Premissas!$C$33+0.25*(Premissas!$C$34-Premissas!$C$33) -> 0.94275 | D33: =(1+Premissas!$C$26)^(2) -> 1.1664 | E33: =Dimensionador!$C$22*(Premissas!$C$33+0.25*(Premissas!$C$34-Premissas!$C$33))*Premissas!$C$21*(1+Premissas!$C$26)^(2) -> 15134.02 | F33: =Dimensionador!$C$23*(Premissas!$C$33+0.25*(Premissas!$C$34-Premissas!$C$33))*Premissas!$C$20*(1+Premissas!$C$26)^(2) -> 734.92195 | G33: =Premissas!$C$25*(1+Premissas!$C$27)^(2)/12 -> 689.585 | H33: =E33-F33 -> 14399.098 | I33: =H33-G33 -> 13709.513 | J33: =J32+I33 -> -162794.15 | K33: =K32+I33 -> 357205.85 | L33: =IF(AND(J33>=0,J32<0),"✅ PAYBACK","") | M33: =I33 -> 13709.513
A34: 3 | B34: Mai | C34: =Premissas!$C$33+0.3333333333*(Premissas!$C$34-Premissas!$C$33) -> 0.941 | D34: =(1+Premissas!$C$26)^(2) -> 1.1664 | E34: =Dimensionador!$C$22*(Premissas!$C$33+0.3333333333*(Premissas!$C$34-Premissas!$C$33))*Premissas!$C$21*(1+Premissas!$C$26)^(2) -> 15105.927 | F34: =Dimensionador!$C$23*(Premissas!$C$33+0.3333333333*(Premissas!$C$34-Premissas!$C$33))*Premissas!$C$20*(1+Premissas!$C$26)^(2) -> 733.55774 | G34: =Premissas!$C$25*(1+Premissas!$C$27)^(2)/12 -> 689.585 | H34: =E34-F34 -> 14372.369 | I34: =H34-G34 -> 13682.784 | J34: =J33+I34 -> -149111.37 | K34: =K33+I34 -> 370888.63 | L34: =IF(AND(J34>=0,J33<0),"✅ PAYBACK","") | M34: =I34 -> 13682.784
A35: 3 | B35: Jun | C35: =Premissas!$C$33+0.4166666667*(Premissas!$C$34-Premissas!$C$33) -> 0.93925 | D35: =(1+Premissas!$C$26)^(2) -> 1.1664 | E35: =Dimensionador!$C$22*(Premissas!$C$33+0.4166666667*(Premissas!$C$34-Premissas!$C$33))*Premissas!$C$21*(1+Premissas!$C$26)^(2) -> 15077.834 | F35: =Dimensionador!$C$23*(Premissas!$C$33+0.4166666667*(Premissas!$C$34-Premissas!$C$33))*Premissas!$C$20*(1+Premissas!$C$26)^(2) -> 732.19352 | G35: =Premissas!$C$25*(1+Premissas!$C$27)^(2)/12 -> 689.585 | H35: =E35-F35 -> 14345.64 | I35: =H35-G35 -> 13656.055 | J35: =J34+I35 -> -135455.31 | K35: =K34+I35 -> 384544.69 | L35: =IF(AND(J35>=0,J34<0),"✅ PAYBACK","") | M35: =I35 -> 13656.055
A36: 3 | B36: Jul | C36: =Premissas!$C$33+0.5*(Premissas!$C$34-Premissas!$C$33) -> 0.9375 | D36: =(1+Premissas!$C$26)^(2) -> 1.1664 | E36: =Dimensionador!$C$22*(Premissas!$C$33+0.5*(Premissas!$C$34-Premissas!$C$33))*Premissas!$C$21*(1+Premissas!$C$26)^(2) -> 15049.741 | F36: =Dimensionador!$C$23*(Premissas!$C$33+0.5*(Premissas!$C$34-Premissas!$C$33))*Premissas!$C$20*(1+Premissas!$C$26)^(2) -> 730.82931 | G36: =Premissas!$C$25*(1+Premissas!$C$27)^(2)/12 -> 689.585 | H36: =E36-F36 -> 14318.912 | I36: =H36-G36 -> 13629.327 | J36: =J35+I36 -> -121825.98 | K36: =K35+I36 -> 398174.02 | L36: =IF(AND(J36>=0,J35<0),"✅ PAYBACK","") | M36: =I36 -> 13629.327
A37: 3 | B37: Ago | C37: =Premissas!$C$33+0.5833333333*(Premissas!$C$34-Premissas!$C$33) -> 0.93575 | D37: =(1+Premissas!$C$26)^(2) -> 1.1664 | E37: =Dimensionador!$C$22*(Premissas!$C$33+0.5833333333*(Premissas!$C$34-Premissas!$C$33))*Premissas!$C$21*(1+Premissas!$C$26)^(2) -> 15021.648 | F37: =Dimensionador!$C$23*(Premissas!$C$33+0.5833333333*(Premissas!$C$34-Premissas!$C$33))*Premissas!$C$20*(1+Premissas!$C$26)^(2) -> 729.46509 | G37: =Premissas!$C$25*(1+Premissas!$C$27)^(2)/12 -> 689.585 | H37: =E37-F37 -> 14292.183 | I37: =H37-G37 -> 13602.598 | J37: =J36+I37 -> -108223.39 | K37: =K36+I37 -> 411776.61 | L37: =IF(AND(J37>=0,J36<0),"✅ PAYBACK","") | M37: =I37 -> 13602.598
A38: 3 | B38: Set | C38: =Premissas!$C$33+0.6666666667*(Premissas!$C$34-Premissas!$C$33) -> 0.934 | D38: =(1+Premissas!$C$26)^(2) -> 1.1664 | E38: =Dimensionador!$C$22*(Premissas!$C$33+0.6666666667*(Premissas!$C$34-Premissas!$C$33))*Premissas!$C$21*(1+Premissas!$C$26)^(2) -> 14993.555 | F38: =Dimensionador!$C$23*(Premissas!$C$33+0.6666666667*(Premissas!$C$34-Premissas!$C$33))*Premissas!$C$20*(1+Premissas!$C$26)^(2) -> 728.10088 | G38: =Premissas!$C$25*(1+Premissas!$C$27)^(2)/12 -> 689.585 | H38: =E38-F38 -> 14265.454 | I38: =H38-G38 -> 13575.869 | J38: =J37+I38 -> -94647.516 | K38: =K37+I38 -> 425352.48 | L38: =IF(AND(J38>=0,J37<0),"✅ PAYBACK","") | M38: =I38 -> 13575.869
A39: 3 | B39: Out | C39: =Premissas!$C$33+0.75*(Premissas!$C$34-Premissas!$C$33) -> 0.93225 | D39: =(1+Premissas!$C$26)^(2) -> 1.1664 | E39: =Dimensionador!$C$22*(Premissas!$C$33+0.75*(Premissas!$C$34-Premissas!$C$33))*Premissas!$C$21*(1+Premissas!$C$26)^(2) -> 14965.462 | F39: =Dimensionador!$C$23*(Premissas!$C$33+0.75*(Premissas!$C$34-Premissas!$C$33))*Premissas!$C$20*(1+Premissas!$C$26)^(2) -> 726.73667 | G39: =Premissas!$C$25*(1+Premissas!$C$27)^(2)/12 -> 689.585 | H39: =E39-F39 -> 14238.726 | I39: =H39-G39 -> 13549.141 | J39: =J38+I39 -> -81098.376 | K39: =K38+I39 -> 438901.62 | L39: =IF(AND(J39>=0,J38<0),"✅ PAYBACK","") | M39: =I39 -> 13549.141
A40: 3 | B40: Nov | C40: =Premissas!$C$33+0.8333333333*(Premissas!$C$34-Premissas!$C$33) -> 0.9305 | D40: =(1+Premissas!$C$26)^(2) -> 1.1664 | E40: =Dimensionador!$C$22*(Premissas!$C$33+0.8333333333*(Premissas!$C$34-Premissas!$C$33))*Premissas!$C$21*(1+Premissas!$C$26)^(2) -> 14937.37 | F40: =Dimensionador!$C$23*(Premissas!$C$33+0.8333333333*(Premissas!$C$34-Premissas!$C$33))*Premissas!$C$20*(1+Premissas!$C$26)^(2) -> 725.37245 | G40: =Premissas!$C$25*(1+Premissas!$C$27)^(2)/12 -> 689.585 | H40: =E40-F40 -> 14211.997 | I40: =H40-G40 -> 13522.412 | J40: =J39+I40 -> -67575.963 | K40: =K39+I40 -> 452424.04 | L40: =IF(AND(J40>=0,J39<0),"✅ PAYBACK","") | M40: =I40 -> 13522.412
A41: 3 | B41: Dez | C41: =Premissas!$C$33+0.9166666667*(Premissas!$C$34-Premissas!$C$33) -> 0.92875 | D41: =(1+Premissas!$C$26)^(2) -> 1.1664 | E41: =Dimensionador!$C$22*(Premissas!$C$33+0.9166666667*(Premissas!$C$34-Premissas!$C$33))*Premissas!$C$21*(1+Premissas!$C$26)^(2) -> 14909.277 | F41: =Dimensionador!$C$23*(Premissas!$C$33+0.9166666667*(Premissas!$C$34-Premissas!$C$33))*Premissas!$C$20*(1+Premissas!$C$26)^(2) -> 724.00824 | G41: =Premissas!$C$25*(1+Premissas!$C$27)^(2)/12 -> 689.585 | H41: =E41-F41 -> 14185.269 | I41: =H41-G41 -> 13495.684 | J41: =J40+I41 -> -54080.28 | K41: =K40+I41 -> 465919.72 | L41: =IF(AND(J41>=0,J40<0),"✅ PAYBACK","") | M41: =I41 -> 13495.684
A42: 4 | B42: Jan | C42: =Premissas!$C$34+0*(Premissas!$C$35-Premissas!$C$34) -> 0.927 | D42: =(1+Premissas!$C$26)^(3) -> 1.259712 | E42: =Dimensionador!$C$22*(Premissas!$C$34+0*(Premissas!$C$35-Premissas!$C$34))*Premissas!$C$21*(1+Premissas!$C$26)^(3) -> 16071.679 | F42: =Dimensionador!$C$23*(Premissas!$C$34+0*(Premissas!$C$35-Premissas!$C$34))*Premissas!$C$20*(1+Premissas!$C$26)^(3) -> 780.45554 | G42: =Premissas!$C$25*(1+Premissas!$C$27)^(3)/12 -> 710.27255 | H42: =E42-F42 -> 15291.223 | I42: =H42-G42 -> 14580.951 | J42: =J41+I42 -> -39499.329 | K42: =K41+I42 -> 480500.67 | L42: =IF(AND(J42>=0,J41<0),"✅ PAYBACK","") | M42: =I42 -> 14580.951
A43: 4 | B43: Fev | C43: =Premissas!$C$34+0.0833333333*(Premissas!$C$35-Premissas!$C$34) -> 0.92533333 | D43: =(1+Premissas!$C$26)^(3) -> 1.259712 | E43: =Dimensionador!$C$22*(Premissas!$C$34+0.0833333333*(Premissas!$C$35-Premissas!$C$34))*Premissas!$C$21*(1+Premissas!$C$26)^(3) -> 16042.783 | F43: =Dimensionador!$C$23*(Premissas!$C$34+0.0833333333*(Premissas!$C$35-Premissas!$C$34))*Premissas!$C$20*(1+Premissas!$C$26)^(3) -> 779.05235 | G43: =Premissas!$C$25*(1+Premissas!$C$27)^(3)/12 -> 710.27255 | H43: =E43-F43 -> 15263.731 | I43: =H43-G43 -> 14553.458 | J43: =J42+I43 -> -24945.871 | K43: =K42+I43 -> 495054.13 | L43: =IF(AND(J43>=0,J42<0),"✅ PAYBACK","") | M43: =I43 -> 14553.458
A44: 4 | B44: Mar | C44: =Premissas!$C$34+0.1666666667*(Premissas!$C$35-Premissas!$C$34) -> 0.92366667 | D44: =(1+Premissas!$C$26)^(3) -> 1.259712 | E44: =Dimensionador!$C$22*(Premissas!$C$34+0.1666666667*(Premissas!$C$35-Premissas!$C$34))*Premissas!$C$21*(1+Premissas!$C$26)^(3) -> 16013.888 | F44: =Dimensionador!$C$23*(Premissas!$C$34+0.1666666667*(Premissas!$C$35-Premissas!$C$34))*Premissas!$C$20*(1+Premissas!$C$26)^(3) -> 777.64916 | G44: =Premissas!$C$25*(1+Premissas!$C$27)^(3)/12 -> 710.27255 | H44: =E44-F44 -> 15236.238 | I44: =H44-G44 -> 14525.966 | J44: =J43+I44 -> -10419.905 | K44: =K43+I44 -> 509580.09 | L44: =IF(AND(J44>=0,J43<0),"✅ PAYBACK","") | M44: =I44 -> 14525.966
A45: 4 | B45: Abr | C45: =Premissas!$C$34+0.25*(Premissas!$C$35-Premissas!$C$34) -> 0.922 | D45: =(1+Premissas!$C$26)^(3) -> 1.259712 | E45: =Dimensionador!$C$22*(Premissas!$C$34+0.25*(Premissas!$C$35-Premissas!$C$34))*Premissas!$C$21*(1+Premissas!$C$26)^(3) -> 15984.992 | F45: =Dimensionador!$C$23*(Premissas!$C$34+0.25*(Premissas!$C$35-Premissas!$C$34))*Premissas!$C$20*(1+Premissas!$C$26)^(3) -> 776.24597 | G45: =Premissas!$C$25*(1+Premissas!$C$27)^(3)/12 -> 710.27255 | H45: =E45-F45 -> 15208.746 | I45: =H45-G45 -> 14498.474 | J45: =J44+I45 -> 4078.5685 | K45: =K44+I45 -> 524078.57 | L45: =IF(AND(J45>=0,J44<0),"✅ PAYBACK","") -> ✅ PAYBACK | M45: =I45 -> 14498.474
A46: 4 | B46: Mai | C46: =Premissas!$C$34+0.3333333333*(Premissas!$C$35-Premissas!$C$34) -> 0.92033333 | D46: =(1+Premissas!$C$26)^(3) -> 1.259712 | E46: =Dimensionador!$C$22*(Premissas!$C$34+0.3333333333*(Premissas!$C$35-Premissas!$C$34))*Premissas!$C$21*(1+Premissas!$C$26)^(3) -> 15956.097 | F46: =Dimensionador!$C$23*(Premissas!$C$34+0.3333333333*(Premissas!$C$35-Premissas!$C$34))*Premissas!$C$20*(1+Premissas!$C$26)^(3) -> 774.84277 | G46: =Premissas!$C$25*(1+Premissas!$C$27)^(3)/12 -> 710.27255 | H46: =E46-F46 -> 15181.254 | I46: =H46-G46 -> 14470.981 | J46: =J45+I46 -> 18549.55 | K46: =K45+I46 -> 538549.55 | L46: =IF(AND(J46>=0,J45<0),"✅ PAYBACK","") | M46: =I46 -> 14470.981
A47: 4 | B47: Jun | C47: =Premissas!$C$34+0.4166666667*(Premissas!$C$35-Premissas!$C$34) -> 0.91866667 | D47: =(1+Premissas!$C$26)^(3) -> 1.259712 | E47: =Dimensionador!$C$22*(Premissas!$C$34+0.4166666667*(Premissas!$C$35-Premissas!$C$34))*Premissas!$C$21*(1+Premissas!$C$26)^(3) -> 15927.201 | F47: =Dimensionador!$C$23*(Premissas!$C$34+0.4166666667*(Premissas!$C$35-Premissas!$C$34))*Premissas!$C$20*(1+Premissas!$C$26)^(3) -> 773.43958 | G47: =Premissas!$C$25*(1+Premissas!$C$27)^(3)/12 -> 710.27255 | H47: =E47-F47 -> 15153.762 | I47: =H47-G47 -> 14443.489 | J47: =J46+I47 -> 32993.039 | K47: =K46+I47 -> 552993.04 | L47: =IF(AND(J47>=0,J46<0),"✅ PAYBACK","") | M47: =I47 -> 14443.489
A48: 4 | B48: Jul | C48: =Premissas!$C$34+0.5*(Premissas!$C$35-Premissas!$C$34) -> 0.917 | D48: =(1+Premissas!$C$26)^(3) -> 1.259712 | E48: =Dimensionador!$C$22*(Premissas!$C$34+0.5*(Premissas!$C$35-Premissas!$C$34))*Premissas!$C$21*(1+Premissas!$C$26)^(3) -> 15898.306 | F48: =Dimensionador!$C$23*(Premissas!$C$34+0.5*(Premissas!$C$35-Premissas!$C$34))*Premissas!$C$20*(1+Premissas!$C$26)^(3) -> 772.03639 | G48: =Premissas!$C$25*(1+Premissas!$C$27)^(3)/12 -> 710.27255 | H48: =E48-F48 -> 15126.269 | I48: =H48-G48 -> 14415.997 | J48: =J47+I48 -> 47409.036 | K48: =K47+I48 -> 567409.04 | L48: =IF(AND(J48>=0,J47<0),"✅ PAYBACK","") | M48: =I48 -> 14415.997
A49: 4 | B49: Ago | C49: =Premissas!$C$34+0.5833333333*(Premissas!$C$35-Premissas!$C$34) -> 0.91533333 | D49: =(1+Premissas!$C$26)^(3) -> 1.259712 | E49: =Dimensionador!$C$22*(Premissas!$C$34+0.5833333333*(Premissas!$C$35-Premissas!$C$34))*Premissas!$C$21*(1+Premissas!$C$26)^(3) -> 15869.41 | F49: =Dimensionador!$C$23*(Premissas!$C$34+0.5833333333*(Premissas!$C$35-Premissas!$C$34))*Premissas!$C$20*(1+Premissas!$C$26)^(3) -> 770.6332 | G49: =Premissas!$C$25*(1+Premissas!$C$27)^(3)/12 -> 710.27255 | H49: =E49-F49 -> 15098.777 | I49: =H49-G49 -> 14388.504 | J49: =J48+I49 -> 61797.54 | K49: =K48+I49 -> 581797.54 | L49: =IF(AND(J49>=0,J48<0),"✅ PAYBACK","") | M49: =I49 -> 14388.504
A50: 4 | B50: Set | C50: =Premissas!$C$34+0.6666666667*(Premissas!$C$35-Premissas!$C$34) -> 0.91366667 | D50: =(1+Premissas!$C$26)^(3) -> 1.259712 | E50: =Dimensionador!$C$22*(Premissas!$C$34+0.6666666667*(Premissas!$C$35-Premissas!$C$34))*Premissas!$C$21*(1+Premissas!$C$26)^(3) -> 15840.515 | F50: =Dimensionador!$C$23*(Premissas!$C$34+0.6666666667*(Premissas!$C$35-Premissas!$C$34))*Premissas!$C$20*(1+Premissas!$C$26)^(3) -> 769.23 | G50: =Premissas!$C$25*(1+Premissas!$C$27)^(3)/12 -> 710.27255 | H50: =E50-F50 -> 15071.285 | I50: =H50-G50 -> 14361.012 | J50: =J49+I50 -> 76158.552 | K50: =K49+I50 -> 596158.55 | L50: =IF(AND(J50>=0,J49<0),"✅ PAYBACK","") | M50: =I50 -> 14361.012
A51: 4 | B51: Out | C51: =Premissas!$C$34+0.75*(Premissas!$C$35-Premissas!$C$34) -> 0.912 | D51: =(1+Premissas!$C$26)^(3) -> 1.259712 | E51: =Dimensionador!$C$22*(Premissas!$C$34+0.75*(Premissas!$C$35-Premissas!$C$34))*Premissas!$C$21*(1+Premissas!$C$26)^(3) -> 15811.619 | F51: =Dimensionador!$C$23*(Premissas!$C$34+0.75*(Premissas!$C$35-Premissas!$C$34))*Premissas!$C$20*(1+Premissas!$C$26)^(3) -> 767.82681 | G51: =Premissas!$C$25*(1+Premissas!$C$27)^(3)/12 -> 710.27255 | H51: =E51-F51 -> 15043.792 | I51: =H51-G51 -> 14333.52 | J51: =J50+I51 -> 90492.072 | K51: =K50+I51 -> 610492.07 | L51: =IF(AND(J51>=0,J50<0),"✅ PAYBACK","") | M51: =I51 -> 14333.52
A52: 4 | B52: Nov | C52: =Premissas!$C$34+0.8333333333*(Premissas!$C$35-Premissas!$C$34) -> 0.91033333 | D52: =(1+Premissas!$C$26)^(3) -> 1.259712 | E52: =Dimensionador!$C$22*(Premissas!$C$34+0.8333333333*(Premissas!$C$35-Premissas!$C$34))*Premissas!$C$21*(1+Premissas!$C$26)^(3) -> 15782.724 | F52: =Dimensionador!$C$23*(Premissas!$C$34+0.8333333333*(Premissas!$C$35-Premissas!$C$34))*Premissas!$C$20*(1+Premissas!$C$26)^(3) -> 766.42362 | G52: =Premissas!$C$25*(1+Premissas!$C$27)^(3)/12 -> 710.27255 | H52: =E52-F52 -> 15016.3 | I52: =H52-G52 -> 14306.027 | J52: =J51+I52 -> 104798.1 | K52: =K51+I52 -> 624798.1 | L52: =IF(AND(J52>=0,J51<0),"✅ PAYBACK","") | M52: =I52 -> 14306.027
A53: 4 | B53: Dez | C53: =Premissas!$C$34+0.9166666667*(Premissas!$C$35-Premissas!$C$34) -> 0.90866667 | D53: =(1+Premissas!$C$26)^(3) -> 1.259712 | E53: =Dimensionador!$C$22*(Premissas!$C$34+0.9166666667*(Premissas!$C$35-Premissas!$C$34))*Premissas!$C$21*(1+Premissas!$C$26)^(3) -> 15753.828 | F53: =Dimensionador!$C$23*(Premissas!$C$34+0.9166666667*(Premissas!$C$35-Premissas!$C$34))*Premissas!$C$20*(1+Premissas!$C$26)^(3) -> 765.02043 | G53: =Premissas!$C$25*(1+Premissas!$C$27)^(3)/12 -> 710.27255 | H53: =E53-F53 -> 14988.808 | I53: =H53-G53 -> 14278.535 | J53: =J52+I53 -> 119076.63 | K53: =K52+I53 -> 639076.63 | L53: =IF(AND(J53>=0,J52<0),"✅ PAYBACK","") | M53: =I53 -> 14278.535
A54: 5 | B54: Jan | C54: =Premissas!$C$35+0*(Premissas!$C$36-Premissas!$C$35) -> 0.907 | D54: =(1+Premissas!$C$26)^(4) -> 1.360489 | E54: =Dimensionador!$C$22*(Premissas!$C$35+0*(Premissas!$C$36-Premissas!$C$35))*Premissas!$C$21*(1+Premissas!$C$26)^(4) -> 16982.927 | F54: =Dimensionador!$C$23*(Premissas!$C$35+0*(Premissas!$C$36-Premissas!$C$35))*Premissas!$C$20*(1+Premissas!$C$26)^(4) -> 824.70661 | G54: =Premissas!$C$25*(1+Premissas!$C$27)^(4)/12 -> 731.58073 | H54: =E54-F54 -> 16158.221 | I54: =H54-G54 -> 15426.64 | J54: =J53+I54 -> 134503.27 | K54: =K53+I54 -> 654503.27 | L54: =IF(AND(J54>=0,J53<0),"✅ PAYBACK","") | M54: =I54 -> 15426.64
A55: 5 | B55: Fev | C55: =Premissas!$C$35+0.0833333333*(Premissas!$C$36-Premissas!$C$35) -> 0.90541667 | D55: =(1+Premissas!$C$26)^(4) -> 1.360489 | E55: =Dimensionador!$C$22*(Premissas!$C$35+0.0833333333*(Premissas!$C$36-Premissas!$C$35))*Premissas!$C$21*(1+Premissas!$C$26)^(4) -> 16953.28 | F55: =Dimensionador!$C$23*(Premissas!$C$35+0.0833333333*(Premissas!$C$36-Premissas!$C$35))*Premissas!$C$20*(1+Premissas!$C$26)^(4) -> 823.26694 | G55: =Premissas!$C$25*(1+Premissas!$C$27)^(4)/12 -> 731.58073 | H55: =E55-F55 -> 16130.014 | I55: =H55-G55 -> 15398.433 | J55: =J54+I55 -> 149901.71 | K55: =K54+I55 -> 669901.71 | L55: =IF(AND(J55>=0,J54<0),"✅ PAYBACK","") | M55: =I55 -> 15398.433
A56: 5 | B56: Mar | C56: =Premissas!$C$35+0.1666666667*(Premissas!$C$36-Premissas!$C$35) -> 0.90383333 | D56: =(1+Premissas!$C$26)^(4) -> 1.360489 | E56: =Dimensionador!$C$22*(Premissas!$C$35+0.1666666667*(Premissas!$C$36-Premissas!$C$35))*Premissas!$C$21*(1+Premissas!$C$26)^(4) -> 16923.634 | F56: =Dimensionador!$C$23*(Premissas!$C$35+0.1666666667*(Premissas!$C$36-Premissas!$C$35))*Premissas!$C$20*(1+Premissas!$C$26)^(4) -> 821.82726 | G56: =Premissas!$C$25*(1+Premissas!$C$27)^(4)/12 -> 731.58073 | H56: =E56-F56 -> 16101.806 | I56: =H56-G56 -> 15370.226 | J56: =J55+I56 -> 165271.93 | K56: =K55+I56 -> 685271.93 | L56: =IF(AND(J56>=0,J55<0),"✅ PAYBACK","") | M56: =I56 -> 15370.226
A57: 5 | B57: Abr | C57: =Premissas!$C$35+0.25*(Premissas!$C$36-Premissas!$C$35) -> 0.90225 | D57: =(1+Premissas!$C$26)^(4) -> 1.360489 | E57: =Dimensionador!$C$22*(Premissas!$C$35+0.25*(Premissas!$C$36-Premissas!$C$35))*Premissas!$C$21*(1+Premissas!$C$26)^(4) -> 16893.987 | F57: =Dimensionador!$C$23*(Premissas!$C$35+0.25*(Premissas!$C$36-Premissas!$C$35))*Premissas!$C$20*(1+Premissas!$C$26)^(4) -> 820.38759 | G57: =Premissas!$C$25*(1+Premissas!$C$27)^(4)/12 -> 731.58073 | H57: =E57-F57 -> 16073.599 | I57: =H57-G57 -> 15342.019 | J57: =J56+I57 -> 180613.95 | K57: =K56+I57 -> 700613.95 | L57: =IF(AND(J57>=0,J56<0),"✅ PAYBACK","") | M57: =I57 -> 15342.019
A58: 5 | B58: Mai | C58: =Premissas!$C$35+0.3333333333*(Premissas!$C$36-Premissas!$C$35) -> 0.90066667 | D58: =(1+Premissas!$C$26)^(4) -> 1.360489 | E58: =Dimensionador!$C$22*(Premissas!$C$35+0.3333333333*(Premissas!$C$36-Premissas!$C$35))*Premissas!$C$21*(1+Premissas!$C$26)^(4) -> 16864.34 | F58: =Dimensionador!$C$23*(Premissas!$C$35+0.3333333333*(Premissas!$C$36-Premissas!$C$35))*Premissas!$C$20*(1+Premissas!$C$26)^(4) -> 818.94791 | G58: =Premissas!$C$25*(1+Premissas!$C$27)^(4)/12 -> 731.58073 | H58: =E58-F58 -> 16045.392 | I58: =H58-G58 -> 15313.811 | J58: =J57+I58 -> 195927.76 | K58: =K57+I58 -> 715927.76 | L58: =IF(AND(J58>=0,J57<0),"✅ PAYBACK","") | M58: =I58 -> 15313.811
A59: 5 | B59: Jun | C59: =Premissas!$C$35+0.4166666667*(Premissas!$C$36-Premissas!$C$35) -> 0.89908333 | D59: =(1+Premissas!$C$26)^(4) -> 1.360489 | E59: =Dimensionador!$C$22*(Premissas!$C$35+0.4166666667*(Premissas!$C$36-Premissas!$C$35))*Premissas!$C$21*(1+Premissas!$C$26)^(4) -> 16834.693 | F59: =Dimensionador!$C$23*(Premissas!$C$35+0.4166666667*(Premissas!$C$36-Premissas!$C$35))*Premissas!$C$20*(1+Premissas!$C$26)^(4) -> 817.50824 | G59: =Premissas!$C$25*(1+Premissas!$C$27)^(4)/12 -> 731.58073 | H59: =E59-F59 -> 16017.185 | I59: =H59-G59 -> 15285.604 | J59: =J58+I59 -> 211213.37 | K59: =K58+I59 -> 731213.37 | L59: =IF(AND(J59>=0,J58<0),"✅ PAYBACK","") | M59: =I59 -> 15285.604
A60: 5 | B60: Jul | C60: =Premissas!$C$35+0.5*(Premissas!$C$36-Premissas!$C$35) -> 0.8975 | D60: =(1+Premissas!$C$26)^(4) -> 1.360489 | E60: =Dimensionador!$C$22*(Premissas!$C$35+0.5*(Premissas!$C$36-Premissas!$C$35))*Premissas!$C$21*(1+Premissas!$C$26)^(4) -> 16805.047 | F60: =Dimensionador!$C$23*(Premissas!$C$35+0.5*(Premissas!$C$36-Premissas!$C$35))*Premissas!$C$20*(1+Premissas!$C$26)^(4) -> 816.06856 | G60: =Premissas!$C$25*(1+Premissas!$C$27)^(4)/12 -> 731.58073 | H60: =E60-F60 -> 15988.978 | I60: =H60-G60 -> 15257.397 | J60: =J59+I60 -> 226470.76 | K60: =K59+I60 -> 746470.76 | L60: =IF(AND(J60>=0,J59<0),"✅ PAYBACK","") | M60: =I60 -> 15257.397
A61: 5 | B61: Ago | C61: =Premissas!$C$35+0.5833333333*(Premissas!$C$36-Premissas!$C$35) -> 0.89591667 | D61: =(1+Premissas!$C$26)^(4) -> 1.360489 | E61: =Dimensionador!$C$22*(Premissas!$C$35+0.5833333333*(Premissas!$C$36-Premissas!$C$35))*Premissas!$C$21*(1+Premissas!$C$26)^(4) -> 16775.4 | F61: =Dimensionador!$C$23*(Premissas!$C$35+0.5833333333*(Premissas!$C$36-Premissas!$C$35))*Premissas!$C$20*(1+Premissas!$C$26)^(4) -> 814.62889 | G61: =Premissas!$C$25*(1+Premissas!$C$27)^(4)/12 -> 731.58073 | H61: =E61-F61 -> 15960.771 | I61: =H61-G61 -> 15229.19 | J61: =J60+I61 -> 241699.95 | K61: =K60+I61 -> 761699.95 | L61: =IF(AND(J61>=0,J60<0),"✅ PAYBACK","") | M61: =I61 -> 15229.19
A62: 5 | B62: Set | C62: =Premissas!$C$35+0.6666666667*(Premissas!$C$36-Premissas!$C$35) -> 0.89433333 | D62: =(1+Premissas!$C$26)^(4) -> 1.360489 | E62: =Dimensionador!$C$22*(Premissas!$C$35+0.6666666667*(Premissas!$C$36-Premissas!$C$35))*Premissas!$C$21*(1+Premissas!$C$26)^(4) -> 16745.753 | F62: =Dimensionador!$C$23*(Premissas!$C$35+0.6666666667*(Premissas!$C$36-Premissas!$C$35))*Premissas!$C$20*(1+Premissas!$C$26)^(4) -> 813.18921 | G62: =Premissas!$C$25*(1+Premissas!$C$27)^(4)/12 -> 731.58073 | H62: =E62-F62 -> 15932.564 | I62: =H62-G62 -> 15200.983 | J62: =J61+I62 -> 256900.94 | K62: =K61+I62 -> 776900.94 | L62: =IF(AND(J62>=0,J61<0),"✅ PAYBACK","") | M62: =I62 -> 15200.983
A63: 5 | B63: Out | C63: =Premissas!$C$35+0.75*(Premissas!$C$36-Premissas!$C$35) -> 0.89275 | D63: =(1+Premissas!$C$26)^(4) -> 1.360489 | E63: =Dimensionador!$C$22*(Premissas!$C$35+0.75*(Premissas!$C$36-Premissas!$C$35))*Premissas!$C$21*(1+Premissas!$C$26)^(4) -> 16716.106 | F63: =Dimensionador!$C$23*(Premissas!$C$35+0.75*(Premissas!$C$36-Premissas!$C$35))*Premissas!$C$20*(1+Premissas!$C$26)^(4) -> 811.74954 | G63: =Premissas!$C$25*(1+Premissas!$C$27)^(4)/12 -> 731.58073 | H63: =E63-F63 -> 15904.357 | I63: =H63-G63 -> 15172.776 | J63: =J62+I63 -> 272073.71 | K63: =K62+I63 -> 792073.71 | L63: =IF(AND(J63>=0,J62<0),"✅ PAYBACK","") | M63: =I63 -> 15172.776
A64: 5 | B64: Nov | C64: =Premissas!$C$35+0.8333333333*(Premissas!$C$36-Premissas!$C$35) -> 0.89116667 | D64: =(1+Premissas!$C$26)^(4) -> 1.360489 | E64: =Dimensionador!$C$22*(Premissas!$C$35+0.8333333333*(Premissas!$C$36-Premissas!$C$35))*Premissas!$C$21*(1+Premissas!$C$26)^(4) -> 16686.459 | F64: =Dimensionador!$C$23*(Premissas!$C$35+0.8333333333*(Premissas!$C$36-Premissas!$C$35))*Premissas!$C$20*(1+Premissas!$C$26)^(4) -> 810.30986 | G64: =Premissas!$C$25*(1+Premissas!$C$27)^(4)/12 -> 731.58073 | H64: =E64-F64 -> 15876.15 | I64: =H64-G64 -> 15144.569 | J64: =J63+I64 -> 287218.28 | K64: =K63+I64 -> 807218.28 | L64: =IF(AND(J64>=0,J63<0),"✅ PAYBACK","") | M64: =I64 -> 15144.569
A65: 5 | B65: Dez | C65: =Premissas!$C$35+0.9166666667*(Premissas!$C$36-Premissas!$C$35) -> 0.88958333 | D65: =(1+Premissas!$C$26)^(4) -> 1.360489 | E65: =Dimensionador!$C$22*(Premissas!$C$35+0.9166666667*(Premissas!$C$36-Premissas!$C$35))*Premissas!$C$21*(1+Premissas!$C$26)^(4) -> 16656.813 | F65: =Dimensionador!$C$23*(Premissas!$C$35+0.9166666667*(Premissas!$C$36-Premissas!$C$35))*Premissas!$C$20*(1+Premissas!$C$26)^(4) -> 808.87019 | G65: =Premissas!$C$25*(1+Premissas!$C$27)^(4)/12 -> 731.58073 | H65: =E65-F65 -> 15847.942 | I65: =H65-G65 -> 15116.362 | J65: =J64+I65 -> 302334.64 | K65: =K64+I65 -> 822334.64 | L65: =IF(AND(J65>=0,J64<0),"✅ PAYBACK","") | M65: =I65 -> 15116.362
A66: 6 | B66: Jan | C66: =Premissas!$C$36+0*(Premissas!$C$37-Premissas!$C$36) -> 0.888 | D66: =(1+Premissas!$C$26)^(5) -> 1.4693281 | E66: =Dimensionador!$C$22*(Premissas!$C$36+0*(Premissas!$C$37-Premissas!$C$36))*Premissas!$C$21*(1+Premissas!$C$26)^(5) -> 17957.339 | F66: =Dimensionador!$C$23*(Premissas!$C$36+0*(Premissas!$C$37-Premissas!$C$36))*Premissas!$C$20*(1+Premissas!$C$26)^(5) -> 872.02495 | G66: =Premissas!$C$25*(1+Premissas!$C$27)^(5)/12 -> 753.52815 | H66: =E66-F66 -> 17085.314 | I66: =H66-G66 -> 16331.786 | J66: =J65+I66 -> 318666.43 | K66: =K65+I66 -> 838666.43 | L66: =IF(AND(J66>=0,J65<0),"✅ PAYBACK","") | M66: =I66 -> 16331.786
A67: 6 | B67: Fev | C67: =Premissas!$C$36+0.0833333333*(Premissas!$C$37-Premissas!$C$36) -> 0.8865 | D67: =(1+Premissas!$C$26)^(5) -> 1.4693281 | E67: =Dimensionador!$C$22*(Premissas!$C$36+0.0833333333*(Premissas!$C$37-Premissas!$C$36))*Premissas!$C$21*(1+Premissas!$C$26)^(5) -> 17927.006 | F67: =Dimensionador!$C$23*(Premissas!$C$36+0.0833333333*(Premissas!$C$37-Premissas!$C$36))*Premissas!$C$20*(1+Premissas!$C$26)^(5) -> 870.55194 | G67: =Premissas!$C$25*(1+Premissas!$C$27)^(5)/12 -> 753.52815 | H67: =E67-F67 -> 17056.454 | I67: =H67-G67 -> 16302.926 | J67: =J66+I67 -> 334969.36 | K67: =K66+I67 -> 854969.36 | L67: =IF(AND(J67>=0,J66<0),"✅ PAYBACK","") | M67: =I67 -> 16302.926
A68: 6 | B68: Mar | C68: =Premissas!$C$36+0.1666666667*(Premissas!$C$37-Premissas!$C$36) -> 0.885 | D68: =(1+Premissas!$C$26)^(5) -> 1.4693281 | E68: =Dimensionador!$C$22*(Premissas!$C$36+0.1666666667*(Premissas!$C$37-Premissas!$C$36))*Premissas!$C$21*(1+Premissas!$C$26)^(5) -> 17896.672 | F68: =Dimensionador!$C$23*(Premissas!$C$36+0.1666666667*(Premissas!$C$37-Premissas!$C$36))*Premissas!$C$20*(1+Premissas!$C$26)^(5) -> 869.07892 | G68: =Premissas!$C$25*(1+Premissas!$C$27)^(5)/12 -> 753.52815 | H68: =E68-F68 -> 17027.593 | I68: =H68-G68 -> 16274.065 | J68: =J67+I68 -> 351243.42 | K68: =K67+I68 -> 871243.42 | L68: =IF(AND(J68>=0,J67<0),"✅ PAYBACK","") | M68: =I68 -> 16274.065
A69: 6 | B69: Abr | C69: =Premissas!$C$36+0.25*(Premissas!$C$37-Premissas!$C$36) -> 0.8835 | D69: =(1+Premissas!$C$26)^(5) -> 1.4693281 | E69: =Dimensionador!$C$22*(Premissas!$C$36+0.25*(Premissas!$C$37-Premissas!$C$36))*Premissas!$C$21*(1+Premissas!$C$26)^(5) -> 17866.339 | F69: =Dimensionador!$C$23*(Premissas!$C$36+0.25*(Premissas!$C$37-Premissas!$C$36))*Premissas!$C$20*(1+Premissas!$C$26)^(5) -> 867.60591 | G69: =Premissas!$C$25*(1+Premissas!$C$27)^(5)/12 -> 753.52815 | H69: =E69-F69 -> 16998.733 | I69: =H69-G69 -> 16245.205 | J69: =J68+I69 -> 367488.63 | K69: =K68+I69 -> 887488.63 | L69: =IF(AND(J69>=0,J68<0),"✅ PAYBACK","") | M69: =I69 -> 16245.205
A70: 6 | B70: Mai | C70: =Premissas!$C$36+0.3333333333*(Premissas!$C$37-Premissas!$C$36) -> 0.882 | D70: =(1+Premissas!$C$26)^(5) -> 1.4693281 | E70: =Dimensionador!$C$22*(Premissas!$C$36+0.3333333333*(Premissas!$C$37-Premissas!$C$36))*Premissas!$C$21*(1+Premissas!$C$26)^(5) -> 17836.006 | F70: =Dimensionador!$C$23*(Premissas!$C$36+0.3333333333*(Premissas!$C$37-Premissas!$C$36))*Premissas!$C$20*(1+Premissas!$C$26)^(5) -> 866.13289 | G70: =Premissas!$C$25*(1+Premissas!$C$27)^(5)/12 -> 753.52815 | H70: =E70-F70 -> 16969.873 | I70: =H70-G70 -> 16216.345 | J70: =J69+I70 -> 383704.97 | K70: =K69+I70 -> 903704.97 | L70: =IF(AND(J70>=0,J69<0),"✅ PAYBACK","") | M70: =I70 -> 16216.345
A71: 6 | B71: Jun | C71: =Premissas!$C$36+0.4166666667*(Premissas!$C$37-Premissas!$C$36) -> 0.8805 | D71: =(1+Premissas!$C$26)^(5) -> 1.4693281 | E71: =Dimensionador!$C$22*(Premissas!$C$36+0.4166666667*(Premissas!$C$37-Premissas!$C$36))*Premissas!$C$21*(1+Premissas!$C$26)^(5) -> 17805.672 | F71: =Dimensionador!$C$23*(Premissas!$C$36+0.4166666667*(Premissas!$C$37-Premissas!$C$36))*Premissas!$C$20*(1+Premissas!$C$26)^(5) -> 864.65988 | G71: =Premissas!$C$25*(1+Premissas!$C$27)^(5)/12 -> 753.52815 | H71: =E71-F71 -> 16941.012 | I71: =H71-G71 -> 16187.484 | J71: =J70+I71 -> 399892.45 | K71: =K70+I71 -> 919892.45 | L71: =IF(AND(J71>=0,J70<0),"✅ PAYBACK","") | M71: =I71 -> 16187.484
A72: 6 | B72: Jul | C72: =Premissas!$C$36+0.5*(Premissas!$C$37-Premissas!$C$36) -> 0.879 | D72: =(1+Premissas!$C$26)^(5) -> 1.4693281 | E72: =Dimensionador!$C$22*(Premissas!$C$36+0.5*(Premissas!$C$37-Premissas!$C$36))*Premissas!$C$21*(1+Premissas!$C$26)^(5) -> 17775.339 | F72: =Dimensionador!$C$23*(Premissas!$C$36+0.5*(Premissas!$C$37-Premissas!$C$36))*Premissas!$C$20*(1+Premissas!$C$26)^(5) -> 863.18686 | G72: =Premissas!$C$25*(1+Premissas!$C$27)^(5)/12 -> 753.52815 | H72: =E72-F72 -> 16912.152 | I72: =H72-G72 -> 16158.624 | J72: =J71+I72 -> 416051.08 | K72: =K71+I72 -> 936051.08 | L72: =IF(AND(J72>=0,J71<0),"✅ PAYBACK","") | M72: =I72 -> 16158.624
A73: 6 | B73: Ago | C73: =Premissas!$C$36+0.5833333333*(Premissas!$C$37-Premissas!$C$36) -> 0.8775 | D73: =(1+Premissas!$C$26)^(5) -> 1.4693281 | E73: =Dimensionador!$C$22*(Premissas!$C$36+0.5833333333*(Premissas!$C$37-Premissas!$C$36))*Premissas!$C$21*(1+Premissas!$C$26)^(5) -> 17745.006 | F73: =Dimensionador!$C$23*(Premissas!$C$36+0.5833333333*(Premissas!$C$37-Premissas!$C$36))*Premissas!$C$20*(1+Premissas!$C$26)^(5) -> 861.71385 | G73: =Premissas!$C$25*(1+Premissas!$C$27)^(5)/12 -> 753.52815 | H73: =E73-F73 -> 16883.292 | I73: =H73-G73 -> 16129.764 | J73: =J72+I73 -> 432180.84 | K73: =K72+I73 -> 952180.84 | L73: =IF(AND(J73>=0,J72<0),"✅ PAYBACK","") | M73: =I73 -> 16129.764
A74: 6 | B74: Set | C74: =Premissas!$C$36+0.6666666667*(Premissas!$C$37-Premissas!$C$36) -> 0.876 | D74: =(1+Premissas!$C$26)^(5) -> 1.4693281 | E74: =Dimensionador!$C$22*(Premissas!$C$36+0.6666666667*(Premissas!$C$37-Premissas!$C$36))*Premissas!$C$21*(1+Premissas!$C$26)^(5) -> 17714.672 | F74: =Dimensionador!$C$23*(Premissas!$C$36+0.6666666667*(Premissas!$C$37-Premissas!$C$36))*Premissas!$C$20*(1+Premissas!$C$26)^(5) -> 860.24083 | G74: =Premissas!$C$25*(1+Premissas!$C$27)^(5)/12 -> 753.52815 | H74: =E74-F74 -> 16854.431 | I74: =H74-G74 -> 16100.903 | J74: =J73+I74 -> 448281.75 | K74: =K73+I74 -> 968281.75 | L74: =IF(AND(J74>=0,J73<0),"✅ PAYBACK","") | M74: =I74 -> 16100.903
A75: 6 | B75: Out | C75: =Premissas!$C$36+0.75*(Premissas!$C$37-Premissas!$C$36) -> 0.8745 | D75: =(1+Premissas!$C$26)^(5) -> 1.4693281 | E75: =Dimensionador!$C$22*(Premissas!$C$36+0.75*(Premissas!$C$37-Premissas!$C$36))*Premissas!$C$21*(1+Premissas!$C$26)^(5) -> 17684.339 | F75: =Dimensionador!$C$23*(Premissas!$C$36+0.75*(Premissas!$C$37-Premissas!$C$36))*Premissas!$C$20*(1+Premissas!$C$26)^(5) -> 858.76782 | G75: =Premissas!$C$25*(1+Premissas!$C$27)^(5)/12 -> 753.52815 | H75: =E75-F75 -> 16825.571 | I75: =H75-G75 -> 16072.043 | J75: =J74+I75 -> 464353.79 | K75: =K74+I75 -> 984353.79 | L75: =IF(AND(J75>=0,J74<0),"✅ PAYBACK","") | M75: =I75 -> 16072.043
A76: 6 | B76: Nov | C76: =Premissas!$C$36+0.8333333333*(Premissas!$C$37-Premissas!$C$36) -> 0.873 | D76: =(1+Premissas!$C$26)^(5) -> 1.4693281 | E76: =Dimensionador!$C$22*(Premissas!$C$36+0.8333333333*(Premissas!$C$37-Premissas!$C$36))*Premissas!$C$21*(1+Premissas!$C$26)^(5) -> 17654.006 | F76: =Dimensionador!$C$23*(Premissas!$C$36+0.8333333333*(Premissas!$C$37-Premissas!$C$36))*Premissas!$C$20*(1+Premissas!$C$26)^(5) -> 857.2948 | G76: =Premissas!$C$25*(1+Premissas!$C$27)^(5)/12 -> 753.52815 | H76: =E76-F76 -> 16796.711 | I76: =H76-G76 -> 16043.183 | J76: =J75+I76 -> 480396.97 | K76: =K75+I76 -> 1000397 | L76: =IF(AND(J76>=0,J75<0),"✅ PAYBACK","") | M76: =I76 -> 16043.183
A77: 6 | B77: Dez | C77: =Premissas!$C$36+0.9166666667*(Premissas!$C$37-Premissas!$C$36) -> 0.8715 | D77: =(1+Premissas!$C$26)^(5) -> 1.4693281 | E77: =Dimensionador!$C$22*(Premissas!$C$36+0.9166666667*(Premissas!$C$37-Premissas!$C$36))*Premissas!$C$21*(1+Premissas!$C$26)^(5) -> 17623.672 | F77: =Dimensionador!$C$23*(Premissas!$C$36+0.9166666667*(Premissas!$C$37-Premissas!$C$36))*Premissas!$C$20*(1+Premissas!$C$26)^(5) -> 855.82179 | G77: =Premissas!$C$25*(1+Premissas!$C$27)^(5)/12 -> 753.52815 | H77: =E77-F77 -> 16767.851 | I77: =H77-G77 -> 16014.322 | J77: =J76+I77 -> 496411.29 | K77: =K76+I77 -> 1016411.3 | L77: =IF(AND(J77>=0,J76<0),"✅ PAYBACK","") | M77: =I77 -> 16014.322
A78: 7 | B78: Jan | C78: =Premissas!$C$37+0*(Premissas!$C$38-Premissas!$C$37) -> 0.87 | D78: =(1+Premissas!$C$26)^(6) -> 1.5868743 | E78: =Dimensionador!$C$22*(Premissas!$C$37+0*(Premissas!$C$38-Premissas!$C$37))*Premissas!$C$21*(1+Premissas!$C$26)^(6) -> 19000.806 | F78: =Dimensionador!$C$23*(Premissas!$C$37+0*(Premissas!$C$38-Premissas!$C$37))*Premissas!$C$20*(1+Premissas!$C$26)^(6) -> 922.69667 | G78: =Premissas!$C$25*(1+Premissas!$C$27)^(6)/12 -> 776.13399 | H78: =E78-F78 -> 18078.109 | I78: =H78-G78 -> 17301.975 | J78: =J77+I78 -> 513713.27 | K78: =K77+I78 -> 1033713.3 | L78: =IF(AND(J78>=0,J77<0),"✅ PAYBACK","") | M78: =I78 -> 17301.975
A79: 7 | B79: Fev | C79: =Premissas!$C$37+0.0833333333*(Premissas!$C$38-Premissas!$C$37) -> 0.8685 | D79: =(1+Premissas!$C$26)^(6) -> 1.5868743 | E79: =Dimensionador!$C$22*(Premissas!$C$37+0.0833333333*(Premissas!$C$38-Premissas!$C$37))*Premissas!$C$21*(1+Premissas!$C$26)^(6) -> 18968.046 | F79: =Dimensionador!$C$23*(Premissas!$C$37+0.0833333333*(Premissas!$C$38-Premissas!$C$37))*Premissas!$C$20*(1+Premissas!$C$26)^(6) -> 921.10582 | G79: =Premissas!$C$25*(1+Premissas!$C$27)^(6)/12 -> 776.13399 | H79: =E79-F79 -> 18046.94 | I79: =H79-G79 -> 17270.806 | J79: =J78+I79 -> 530984.08 | K79: =K78+I79 -> 1050984.1 | L79: =IF(AND(J79>=0,J78<0),"✅ PAYBACK","") | M79: =I79 -> 17270.806
A80: 7 | B80: Mar | C80: =Premissas!$C$37+0.1666666667*(Premissas!$C$38-Premissas!$C$37) -> 0.867 | D80: =(1+Premissas!$C$26)^(6) -> 1.5868743 | E80: =Dimensionador!$C$22*(Premissas!$C$37+0.1666666667*(Premissas!$C$38-Premissas!$C$37))*Premissas!$C$21*(1+Premissas!$C$26)^(6) -> 18935.286 | F80: =Dimensionador!$C$23*(Premissas!$C$37+0.1666666667*(Premissas!$C$38-Premissas!$C$37))*Premissas!$C$20*(1+Premissas!$C$26)^(6) -> 919.51496 | G80: =Premissas!$C$25*(1+Premissas!$C$27)^(6)/12 -> 776.13399 | H80: =E80-F80 -> 18015.771 | I80: =H80-G80 -> 17239.637 | J80: =J79+I80 -> 548223.71 | K80: =K79+I80 -> 1068223.7 | L80: =IF(AND(J80>=0,J79<0),"✅ PAYBACK","") | M80: =I80 -> 17239.637
A81: 7 | B81: Abr | C81: =Premissas!$C$37+0.25*(Premissas!$C$38-Premissas!$C$37) -> 0.8655 | D81: =(1+Premissas!$C$26)^(6) -> 1.5868743 | E81: =Dimensionador!$C$22*(Premissas!$C$37+0.25*(Premissas!$C$38-Premissas!$C$37))*Premissas!$C$21*(1+Premissas!$C$26)^(6) -> 18902.526 | F81: =Dimensionador!$C$23*(Premissas!$C$37+0.25*(Premissas!$C$38-Premissas!$C$37))*Premissas!$C$20*(1+Premissas!$C$26)^(6) -> 917.9241 | G81: =Premissas!$C$25*(1+Premissas!$C$27)^(6)/12 -> 776.13399 | H81: =E81-F81 -> 17984.602 | I81: =H81-G81 -> 17208.468 | J81: =J80+I81 -> 565432.18 | K81: =K80+I81 -> 1085432.2 | L81: =IF(AND(J81>=0,J80<0),"✅ PAYBACK","") | M81: =I81 -> 17208.468
A82: 7 | B82: Mai | C82: =Premissas!$C$37+0.3333333333*(Premissas!$C$38-Premissas!$C$37) -> 0.864 | D82: =(1+Premissas!$C$26)^(6) -> 1.5868743 | E82: =Dimensionador!$C$22*(Premissas!$C$37+0.3333333333*(Premissas!$C$38-Premissas!$C$37))*Premissas!$C$21*(1+Premissas!$C$26)^(6) -> 18869.766 | F82: =Dimensionador!$C$23*(Premissas!$C$37+0.3333333333*(Premissas!$C$38-Premissas!$C$37))*Premissas!$C$20*(1+Premissas!$C$26)^(6) -> 916.33325 | G82: =Premissas!$C$25*(1+Premissas!$C$27)^(6)/12 -> 776.13399 | H82: =E82-F82 -> 17953.433 | I82: =H82-G82 -> 17177.299 | J82: =J81+I82 -> 582609.48 | K82: =K81+I82 -> 1102609.5 | L82: =IF(AND(J82>=0,J81<0),"✅ PAYBACK","") | M82: =I82 -> 17177.299
A83: 7 | B83: Jun | C83: =Premissas!$C$37+0.4166666667*(Premissas!$C$38-Premissas!$C$37) -> 0.8625 | D83: =(1+Premissas!$C$26)^(6) -> 1.5868743 | E83: =Dimensionador!$C$22*(Premissas!$C$37+0.4166666667*(Premissas!$C$38-Premissas!$C$37))*Premissas!$C$21*(1+Premissas!$C$26)^(6) -> 18837.006 | F83: =Dimensionador!$C$23*(Premissas!$C$37+0.4166666667*(Premissas!$C$38-Premissas!$C$37))*Premissas!$C$20*(1+Premissas!$C$26)^(6) -> 914.74239 | G83: =Premissas!$C$25*(1+Premissas!$C$27)^(6)/12 -> 776.13399 | H83: =E83-F83 -> 17922.264 | I83: =H83-G83 -> 17146.13 | J83: =J82+I83 -> 599755.61 | K83: =K82+I83 -> 1119755.6 | L83: =IF(AND(J83>=0,J82<0),"✅ PAYBACK","") | M83: =I83 -> 17146.13
A84: 7 | B84: Jul | C84: =Premissas!$C$37+0.5*(Premissas!$C$38-Premissas!$C$37) -> 0.861 | D84: =(1+Premissas!$C$26)^(6) -> 1.5868743 | E84: =Dimensionador!$C$22*(Premissas!$C$37+0.5*(Premissas!$C$38-Premissas!$C$37))*Premissas!$C$21*(1+Premissas!$C$26)^(6) -> 18804.246 | F84: =Dimensionador!$C$23*(Premissas!$C$37+0.5*(Premissas!$C$38-Premissas!$C$37))*Premissas!$C$20*(1+Premissas!$C$26)^(6) -> 913.15153 | G84: =Premissas!$C$25*(1+Premissas!$C$27)^(6)/12 -> 776.13399 | H84: =E84-F84 -> 17891.094 | I84: =H84-G84 -> 17114.96 | J84: =J83+I84 -> 616870.57 | K84: =K83+I84 -> 1136870.6 | L84: =IF(AND(J84>=0,J83<0),"✅ PAYBACK","") | M84: =I84 -> 17114.96
A85: 7 | B85: Ago | C85: =Premissas!$C$37+0.5833333333*(Premissas!$C$38-Premissas!$C$37) -> 0.8595 | D85: =(1+Premissas!$C$26)^(6) -> 1.5868743 | E85: =Dimensionador!$C$22*(Premissas!$C$37+0.5833333333*(Premissas!$C$38-Premissas!$C$37))*Premissas!$C$21*(1+Premissas!$C$26)^(6) -> 18771.486 | F85: =Dimensionador!$C$23*(Premissas!$C$37+0.5833333333*(Premissas!$C$38-Premissas!$C$37))*Premissas!$C$20*(1+Premissas!$C$26)^(6) -> 911.56068 | G85: =Premissas!$C$25*(1+Premissas!$C$27)^(6)/12 -> 776.13399 | H85: =E85-F85 -> 17859.925 | I85: =H85-G85 -> 17083.791 | J85: =J84+I85 -> 633954.36 | K85: =K84+I85 -> 1153954.4 | L85: =IF(AND(J85>=0,J84<0),"✅ PAYBACK","") | M85: =I85 -> 17083.791
A86: 7 | B86: Set | C86: =Premissas!$C$37+0.6666666667*(Premissas!$C$38-Premissas!$C$37) -> 0.858 | D86: =(1+Premissas!$C$26)^(6) -> 1.5868743 | E86: =Dimensionador!$C$22*(Premissas!$C$37+0.6666666667*(Premissas!$C$38-Premissas!$C$37))*Premissas!$C$21*(1+Premissas!$C$26)^(6) -> 18738.726 | F86: =Dimensionador!$C$23*(Premissas!$C$37+0.6666666667*(Premissas!$C$38-Premissas!$C$37))*Premissas!$C$20*(1+Premissas!$C$26)^(6) -> 909.96982 | G86: =Premissas!$C$25*(1+Premissas!$C$27)^(6)/12 -> 776.13399 | H86: =E86-F86 -> 17828.756 | I86: =H86-G86 -> 17052.622 | J86: =J85+I86 -> 651006.98 | K86: =K85+I86 -> 1171007 | L86: =IF(AND(J86>=0,J85<0),"✅ PAYBACK","") | M86: =I86 -> 17052.622
A87: 7 | B87: Out | C87: =Premissas!$C$37+0.75*(Premissas!$C$38-Premissas!$C$37) -> 0.8565 | D87: =(1+Premissas!$C$26)^(6) -> 1.5868743 | E87: =Dimensionador!$C$22*(Premissas!$C$37+0.75*(Premissas!$C$38-Premissas!$C$37))*Premissas!$C$21*(1+Premissas!$C$26)^(6) -> 18705.966 | F87: =Dimensionador!$C$23*(Premissas!$C$37+0.75*(Premissas!$C$38-Premissas!$C$37))*Premissas!$C$20*(1+Premissas!$C$26)^(6) -> 908.37897 | G87: =Premissas!$C$25*(1+Premissas!$C$27)^(6)/12 -> 776.13399 | H87: =E87-F87 -> 17797.587 | I87: =H87-G87 -> 17021.453 | J87: =J86+I87 -> 668028.44 | K87: =K86+I87 -> 1188028.4 | L87: =IF(AND(J87>=0,J86<0),"✅ PAYBACK","") | M87: =I87 -> 17021.453
A88: 7 | B88: Nov | C88: =Premissas!$C$37+0.8333333333*(Premissas!$C$38-Premissas!$C$37) -> 0.855 | D88: =(1+Premissas!$C$26)^(6) -> 1.5868743 | E88: =Dimensionador!$C$22*(Premissas!$C$37+0.8333333333*(Premissas!$C$38-Premissas!$C$37))*Premissas!$C$21*(1+Premissas!$C$26)^(6) -> 18673.206 | F88: =Dimensionador!$C$23*(Premissas!$C$37+0.8333333333*(Premissas!$C$38-Premissas!$C$37))*Premissas!$C$20*(1+Premissas!$C$26)^(6) -> 906.78811 | G88: =Premissas!$C$25*(1+Premissas!$C$27)^(6)/12 -> 776.13399 | H88: =E88-F88 -> 17766.418 | I88: =H88-G88 -> 16990.284 | J88: =J87+I88 -> 685018.72 | K88: =K87+I88 -> 1205018.7 | L88: =IF(AND(J88>=0,J87<0),"✅ PAYBACK","") | M88: =I88 -> 16990.284
A89: 7 | B89: Dez | C89: =Premissas!$C$37+0.9166666667*(Premissas!$C$38-Premissas!$C$37) -> 0.8535 | D89: =(1+Premissas!$C$26)^(6) -> 1.5868743 | E89: =Dimensionador!$C$22*(Premissas!$C$37+0.9166666667*(Premissas!$C$38-Premissas!$C$37))*Premissas!$C$21*(1+Premissas!$C$26)^(6) -> 18640.446 | F89: =Dimensionador!$C$23*(Premissas!$C$37+0.9166666667*(Premissas!$C$38-Premissas!$C$37))*Premissas!$C$20*(1+Premissas!$C$26)^(6) -> 905.19725 | G89: =Premissas!$C$25*(1+Premissas!$C$27)^(6)/12 -> 776.13399 | H89: =E89-F89 -> 17735.249 | I89: =H89-G89 -> 16959.115 | J89: =J88+I89 -> 701977.83 | K89: =K88+I89 -> 1221977.8 | L89: =IF(AND(J89>=0,J88<0),"✅ PAYBACK","") | M89: =I89 -> 16959.115
A90: 8 | B90: Jan | C90: =Premissas!$C$38+0*(Premissas!$C$39-Premissas!$C$38) -> 0.852 | D90: =(1+Premissas!$C$26)^(7) -> 1.7138243 | E90: =Dimensionador!$C$22*(Premissas!$C$38+0*(Premissas!$C$39-Premissas!$C$38))*Premissas!$C$21*(1+Premissas!$C$26)^(7) -> 20096.301 | F90: =Dimensionador!$C$23*(Premissas!$C$38+0*(Premissas!$C$39-Premissas!$C$38))*Premissas!$C$20*(1+Premissas!$C$26)^(7) -> 975.89491 | G90: =Premissas!$C$25*(1+Premissas!$C$27)^(7)/12 -> 799.41801 | H90: =E90-F90 -> 19120.406 | I90: =H90-G90 -> 18320.988 | J90: =J89+I90 -> 720298.82 | K90: =K89+I90 -> 1240298.8 | L90: =IF(AND(J90>=0,J89<0),"✅ PAYBACK","") | M90: =I90 -> 18320.988
A91: 8 | B91: Fev | C91: =Premissas!$C$38+0.0833333333*(Premissas!$C$39-Premissas!$C$38) -> 0.8505 | D91: =(1+Premissas!$C$26)^(7) -> 1.7138243 | E91: =Dimensionador!$C$22*(Premissas!$C$38+0.0833333333*(Premissas!$C$39-Premissas!$C$38))*Premissas!$C$21*(1+Premissas!$C$26)^(7) -> 20060.92 | F91: =Dimensionador!$C$23*(Premissas!$C$38+0.0833333333*(Premissas!$C$39-Premissas!$C$38))*Premissas!$C$20*(1+Premissas!$C$26)^(7) -> 974.17678 | G91: =Premissas!$C$25*(1+Premissas!$C$27)^(7)/12 -> 799.41801 | H91: =E91-F91 -> 19086.743 | I91: =H91-G91 -> 18287.325 | J91: =J90+I91 -> 738586.15 | K91: =K90+I91 -> 1258586.1 | L91: =IF(AND(J91>=0,J90<0),"✅ PAYBACK","") | M91: =I91 -> 18287.325
A92: 8 | B92: Mar | C92: =Premissas!$C$38+0.1666666667*(Premissas!$C$39-Premissas!$C$38) -> 0.849 | D92: =(1+Premissas!$C$26)^(7) -> 1.7138243 | E92: =Dimensionador!$C$22*(Premissas!$C$38+0.1666666667*(Premissas!$C$39-Premissas!$C$38))*Premissas!$C$21*(1+Premissas!$C$26)^(7) -> 20025.539 | F92: =Dimensionador!$C$23*(Premissas!$C$38+0.1666666667*(Premissas!$C$39-Premissas!$C$38))*Premissas!$C$20*(1+Premissas!$C$26)^(7) -> 972.45866 | G92: =Premissas!$C$25*(1+Premissas!$C$27)^(7)/12 -> 799.41801 | H92: =E92-F92 -> 19053.081 | I92: =H92-G92 -> 18253.663 | J92: =J91+I92 -> 756839.81 | K92: =K91+I92 -> 1276839.8 | L92: =IF(AND(J92>=0,J91<0),"✅ PAYBACK","") | M92: =I92 -> 18253.663
A93: 8 | B93: Abr | C93: =Premissas!$C$38+0.25*(Premissas!$C$39-Premissas!$C$38) -> 0.8475 | D93: =(1+Premissas!$C$26)^(7) -> 1.7138243 | E93: =Dimensionador!$C$22*(Premissas!$C$38+0.25*(Premissas!$C$39-Premissas!$C$38))*Premissas!$C$21*(1+Premissas!$C$26)^(7) -> 19990.158 | F93: =Dimensionador!$C$23*(Premissas!$C$38+0.25*(Premissas!$C$39-Premissas!$C$38))*Premissas!$C$20*(1+Premissas!$C$26)^(7) -> 970.74053 | G93: =Premissas!$C$25*(1+Premissas!$C$27)^(7)/12 -> 799.41801 | H93: =E93-F93 -> 19019.418 | I93: =H93-G93 -> 18220 | J93: =J92+I93 -> 775059.81 | K93: =K92+I93 -> 1295059.8 | L93: =IF(AND(J93>=0,J92<0),"✅ PAYBACK","") | M93: =I93 -> 18220
A94: 8 | B94: Mai | C94: =Premissas!$C$38+0.3333333333*(Premissas!$C$39-Premissas!$C$38) -> 0.846 | D94: =(1+Premissas!$C$26)^(7) -> 1.7138243 | E94: =Dimensionador!$C$22*(Premissas!$C$38+0.3333333333*(Premissas!$C$39-Premissas!$C$38))*Premissas!$C$21*(1+Premissas!$C$26)^(7) -> 19954.778 | F94: =Dimensionador!$C$23*(Premissas!$C$38+0.3333333333*(Premissas!$C$39-Premissas!$C$38))*Premissas!$C$20*(1+Premissas!$C$26)^(7) -> 969.02241 | G94: =Premissas!$C$25*(1+Premissas!$C$27)^(7)/12 -> 799.41801 | H94: =E94-F94 -> 18985.755 | I94: =H94-G94 -> 18186.337 | J94: =J93+I94 -> 793246.15 | K94: =K93+I94 -> 1313246.1 | L94: =IF(AND(J94>=0,J93<0),"✅ PAYBACK","") | M94: =I94 -> 18186.337
A95: 8 | B95: Jun | C95: =Premissas!$C$38+0.4166666667*(Premissas!$C$39-Premissas!$C$38) -> 0.8445 | D95: =(1+Premissas!$C$26)^(7) -> 1.7138243 | E95: =Dimensionador!$C$22*(Premissas!$C$38+0.4166666667*(Premissas!$C$39-Premissas!$C$38))*Premissas!$C$21*(1+Premissas!$C$26)^(7) -> 19919.397 | F95: =Dimensionador!$C$23*(Premissas!$C$38+0.4166666667*(Premissas!$C$39-Premissas!$C$38))*Premissas!$C$20*(1+Premissas!$C$26)^(7) -> 967.30428 | G95: =Premissas!$C$25*(1+Premissas!$C$27)^(7)/12 -> 799.41801 | H95: =E95-F95 -> 18952.092 | I95: =H95-G95 -> 18152.674 | J95: =J94+I95 -> 811398.82 | K95: =K94+I95 -> 1331398.8 | L95: =IF(AND(J95>=0,J94<0),"✅ PAYBACK","") | M95: =I95 -> 18152.674
A96: 8 | B96: Jul | C96: =Premissas!$C$38+0.5*(Premissas!$C$39-Premissas!$C$38) -> 0.843 | D96: =(1+Premissas!$C$26)^(7) -> 1.7138243 | E96: =Dimensionador!$C$22*(Premissas!$C$38+0.5*(Premissas!$C$39-Premissas!$C$38))*Premissas!$C$21*(1+Premissas!$C$26)^(7) -> 19884.016 | F96: =Dimensionador!$C$23*(Premissas!$C$38+0.5*(Premissas!$C$39-Premissas!$C$38))*Premissas!$C$20*(1+Premissas!$C$26)^(7) -> 965.58616 | G96: =Premissas!$C$25*(1+Premissas!$C$27)^(7)/12 -> 799.41801 | H96: =E96-F96 -> 18918.43 | I96: =H96-G96 -> 18119.012 | J96: =J95+I96 -> 829517.83 | K96: =K95+I96 -> 1349517.8 | L96: =IF(AND(J96>=0,J95<0),"✅ PAYBACK","") | M96: =I96 -> 18119.012
A97: 8 | B97: Ago | C97: =Premissas!$C$38+0.5833333333*(Premissas!$C$39-Premissas!$C$38) -> 0.8415 | D97: =(1+Premissas!$C$26)^(7) -> 1.7138243 | E97: =Dimensionador!$C$22*(Premissas!$C$38+0.5833333333*(Premissas!$C$39-Premissas!$C$38))*Premissas!$C$21*(1+Premissas!$C$26)^(7) -> 19848.635 | F97: =Dimensionador!$C$23*(Premissas!$C$38+0.5833333333*(Premissas!$C$39-Premissas!$C$38))*Premissas!$C$20*(1+Premissas!$C$26)^(7) -> 963.86803 | G97: =Premissas!$C$25*(1+Premissas!$C$27)^(7)/12 -> 799.41801 | H97: =E97-F97 -> 18884.767 | I97: =H97-G97 -> 18085.349 | J97: =J96+I97 -> 847603.18 | K97: =K96+I97 -> 1367603.2 | L97: =IF(AND(J97>=0,J96<0),"✅ PAYBACK","") | M97: =I97 -> 18085.349
A98: 8 | B98: Set | C98: =Premissas!$C$38+0.6666666667*(Premissas!$C$39-Premissas!$C$38) -> 0.84 | D98: =(1+Premissas!$C$26)^(7) -> 1.7138243 | E98: =Dimensionador!$C$22*(Premissas!$C$38+0.6666666667*(Premissas!$C$39-Premissas!$C$38))*Premissas!$C$21*(1+Premissas!$C$26)^(7) -> 19813.254 | F98: =Dimensionador!$C$23*(Premissas!$C$38+0.6666666667*(Premissas!$C$39-Premissas!$C$38))*Premissas!$C$20*(1+Premissas!$C$26)^(7) -> 962.14991 | G98: =Premissas!$C$25*(1+Premissas!$C$27)^(7)/12 -> 799.41801 | H98: =E98-F98 -> 18851.104 | I98: =H98-G98 -> 18051.686 | J98: =J97+I98 -> 865654.87 | K98: =K97+I98 -> 1385654.9 | L98: =IF(AND(J98>=0,J97<0),"✅ PAYBACK","") | M98: =I98 -> 18051.686
A99: 8 | B99: Out | C99: =Premissas!$C$38+0.75*(Premissas!$C$39-Premissas!$C$38) -> 0.8385 | D99: =(1+Premissas!$C$26)^(7) -> 1.7138243 | E99: =Dimensionador!$C$22*(Premissas!$C$38+0.75*(Premissas!$C$39-Premissas!$C$38))*Premissas!$C$21*(1+Premissas!$C$26)^(7) -> 19777.874 | F99: =Dimensionador!$C$23*(Premissas!$C$38+0.75*(Premissas!$C$39-Premissas!$C$38))*Premissas!$C$20*(1+Premissas!$C$26)^(7) -> 960.43178 | G99: =Premissas!$C$25*(1+Premissas!$C$27)^(7)/12 -> 799.41801 | H99: =E99-F99 -> 18817.442 | I99: =H99-G99 -> 18018.024 | J99: =J98+I99 -> 883672.89 | K99: =K98+I99 -> 1403672.9 | L99: =IF(AND(J99>=0,J98<0),"✅ PAYBACK","") | M99: =I99 -> 18018.024
A100: 8 | B100: Nov | C100: =Premissas!$C$38+0.8333333333*(Premissas!$C$39-Premissas!$C$38) -> 0.837 | D100: =(1+Premissas!$C$26)^(7) -> 1.7138243 | E100: =Dimensionador!$C$22*(Premissas!$C$38+0.8333333333*(Premissas!$C$39-Premissas!$C$38))*Premissas!$C$21*(1+Premissas!$C$26)^(7) -> 19742.493 | F100: =Dimensionador!$C$23*(Premissas!$C$38+0.8333333333*(Premissas!$C$39-Premissas!$C$38))*Premissas!$C$20*(1+Premissas!$C$26)^(7) -> 958.71366 | G100: =Premissas!$C$25*(1+Premissas!$C$27)^(7)/12 -> 799.41801 | H100: =E100-F100 -> 18783.779 | I100: =H100-G100 -> 17984.361 | J100: =J99+I100 -> 901657.25 | K100: =K99+I100 -> 1421657.3 | L100: =IF(AND(J100>=0,J99<0),"✅ PAYBACK","") | M100: =I100 -> 17984.361
A101: 8 | B101: Dez | C101: =Premissas!$C$38+0.9166666667*(Premissas!$C$39-Premissas!$C$38) -> 0.8355 | D101: =(1+Premissas!$C$26)^(7) -> 1.7138243 | E101: =Dimensionador!$C$22*(Premissas!$C$38+0.9166666667*(Premissas!$C$39-Premissas!$C$38))*Premissas!$C$21*(1+Premissas!$C$26)^(7) -> 19707.112 | F101: =Dimensionador!$C$23*(Premissas!$C$38+0.9166666667*(Premissas!$C$39-Premissas!$C$38))*Premissas!$C$20*(1+Premissas!$C$26)^(7) -> 956.99553 | G101: =Premissas!$C$25*(1+Premissas!$C$27)^(7)/12 -> 799.41801 | H101: =E101-F101 -> 18750.116 | I101: =H101-G101 -> 17950.698 | J101: =J100+I101 -> 919607.95 | K101: =K100+I101 -> 1439608 | L101: =IF(AND(J101>=0,J100<0),"✅ PAYBACK","") | M101: =I101 -> 17950.698
...

Sheet Premissas
A1: PREMISSAS — BESS LOAD SHIFTING
A2: Azul = input editável | Verde = calculado | Vinculado ao Dimensionador
B4: EQUIPAMENTO BESS | C4: VALOR | D4: UNIDADE
B5: Potência BESS | C5: 241 | D5: kW
B6: DoD | C6: 1 | D6: p.u. | F6: =C10*C11 -> 4692.1701 | G6: =Dimensionador!C5/F6 -> 0.50083436
B7: η BESS round-trip | C7: 0.9556 | D7: p.u.
B8: η Elétrica | C8: 0.98 | D8: p.u.
B9: η Operacional | C9: 0.99 | D9: p.u.
B10: Dias úteis/mês | C10: 21 | D10: dias
B11: Energia útil/ciclo [calc] | C11: =C5*C6*C7*C8*C9 -> 223.43667 | D11: kWh
B12: Energia útil/mês 1 BESS [calc] | C12: =C11*C10 -> 4692.1701 | D12: kWh
B13: Energia carga/mês 1 BESS [calc] | C13: =((C5*C10*C6)/(C7*C8*C9)) -> 5458.8219 | D13: kWh
B15: TARIFAS — MERCADO LIVRE | C15: VALOR | D15: UNIDADE
B16: TUSD Fora Ponta | C16: 0.12243293 | D16: R$/kWh
B17: TE Fora Ponta ML | C17: 0 | D17: R$/kWh
B18: TUSD Na Ponta | C18: 2.933165 | D18: R$/kWh
B19: TE Na Ponta ML | C19: 0 | D19: R$/kWh
B20: HFP Total [calc] | C20: =C16+C17 -> 0.12243293 | D20: R$/kWh
B21: HP Total [calc] | C21: =C18+C19 -> 2.933165 | D21: R$/kWh
B22: Delta HP-HFP [calc] | C22: =C21-C20 -> 2.810732 | D22: R$/kWh
B24: PARÂMETROS FINANCEIROS | C24: VALOR | D24: UNIDADE
B25: O&M por BESS/ano | C25: =Dimensionador!C8*1.5% -> 7800 | D25: R$/ano
B26: Reajuste energia | C26: 0.08 | D26: % a.a.
B27: Reajuste O&M | C27: 0.03 | D27: % a.a.
B28: TMA | C28: 0.12 | D28: % a.a.
B30: CURVA SOH HUAWEI (1 ciclo/dia, DoD 100%) | C30: SOH | D30: Ano | J30: 215 | K30: 241
B31: Ano 0 | C31: 1 | D31: 0 | J31: 1 | K31: =O31/1 -> 1 | O31: 1
B32: Ano 1 | C32: 0.971 | D32: 1 | J32: 0.93884 | K32: =O32/1 -> 0.971 | O32: 0.971
B33: Ano 2 | C33: 0.948 | D33: 2 | J33: 0.91336 | K33: =O33/1 -> 0.948 | O33: 0.948
B34: Ano 3 | C34: 0.927 | D34: 3 | J34: 0.89358 | K34: =O34/1 -> 0.927 | O34: 0.927
B35: Ano 4 | C35: 0.907 | D35: 4 | J35: 0.87591 | K35: =O35/1 -> 0.907 | O35: 0.907
B36: Ano 5 | C36: 0.888 | D36: 5 | J36: 0.85936 | K36: =O36/1 -> 0.888 | O36: 0.888
B37: Ano 6 | C37: 0.87 | D37: 6 | J37: 0.84357 | K37: =O37/1 -> 0.87 | O37: 0.87
B38: Ano 7 | C38: 0.852 | D38: 7 | J38: 0.82835 | K38: =O38/1 -> 0.852 | O38: 0.852
B39: Ano 8 | C39: 0.834 | D39: 8 | J39: 0.81357 | K39: =O39/1 -> 0.834 | O39: 0.834
B40: Ano 9 | C40: 0.817 | D40: 9 | J40: 0.79916 | K40: =O40/1 -> 0.817 | O40: 0.817
B41: Ano 10 | C41: 0.799 | D41: 10 | J41: 0.78506 | K41: =O41/1 -> 0.799 | O41: 0.799
B42: Ano 11 | C42: 0.783 | D42: 11 | J42: 0.77122 | K42: =O42/1 -> 0.783 | O42: 0.783
... B51: Ano 20 | C51: 0.645 | D51: 20 | J51: 0.65454 | K51: =O51/1 -> 0.645 | O51: 0.645
